Workbook
Name \a: #REF!
Name \a: #REF!
Name \c: #REF!
Name \c: #REF!
Name \f: '[1]TAB1-01P'!#REF!
Name \f: '[1]TAB1-01P'!#REF!
Name \i: '[1]TAB1-01P'!#REF!
Name \i: '[1]TAB1-01P'!#REF!
Name \P: #REF!
Name \P: #REF!
Name \s: '[1]TAB1-01P'!#REF!
Name \s: '[1]TAB1-01P'!#REF!
Name \w: '[1]TAB1-01P'!#REF!
Name \w: '[1]TAB1-01P'!#REF!
Name ___: #REF!
Name ___: #REF!
Name ___: #REF!
Name _________________________________________________________________________________________: #REF!
Name _________________________________________________________________________________________: #REF!
Name __________________________________________________________________________cto2: [2]!_p1
Name __________________________________________________________________________cto2: [2]!_p1
Name __________________________________________________________________________er1: [2]!_p1
Name __________________________________________________________________________er1: [2]!_p1
Name __________________________________________________________________________rr2: [2]!_p1
Name __________________________________________________________________________rr2: [2]!_p1
Name _______________________________________________bh1: [3]!__________________p1
Name _______________________________________________bh1: [3]!__________________p1
Name _______________________________________________bh2: [3]!__________________p1
Name _______________________________________________bh2: [3]!__________________p1
Name _______________________________________________bh3: [3]!__________________p1
Name _______________________________________________bh3: [3]!__________________p1
Name _______________________________________________bh4: [3]!__________________p1
Name _______________________________________________bh4: [3]!__________________p1
Name _______________________________________________bh5: [3]!__________________p1
Name _______________________________________________bh5: [3]!__________________p1
Name _______________________________________________bh6: [3]!__________________p1
Name _______________________________________________bh6: [3]!__________________p1
Name _______________________________________________bh7: [3]!__________________p1
Name _______________________________________________bh7: [3]!__________________p1
Name _______________________________________________bh8: [3]!__________________p1
Name _______________________________________________bh8: [3]!__________________p1
Name _______________________________________________bh9: [3]!__________________p1
Name _______________________________________________bh9: [3]!__________________p1
Name _______________________________________________rio1: [3]!__________________p1
Name _______________________________________________rio1: [3]!__________________p1
Name _______________________________________________rio2: [3]!__________________p1
Name _______________________________________________rio2: [3]!__________________p1
Name _______________________________________________rio3: [3]!__________________p1
Name _______________________________________________rio3: [3]!__________________p1
Name _______________________________________________rj1: [3]!__________________p1
Name _______________________________________________rj1: [3]!__________________p1
Name _______________________________________________rj2: [3]!__________________p1
Name _______________________________________________rj2: [3]!__________________p1
Name _______________________________________________rj3: [3]!__________________p1
Name _______________________________________________rj3: [3]!__________________p1
Name _______________________________________________rj4: [3]!__________________p1
Name _______________________________________________rj4: [3]!__________________p1
Name _______________________________________________rj5: [3]!__________________p1
Name _______________________________________________rj5: [3]!__________________p1
Name _______________________________________________rj6: [3]!__________________p1

Sheet Resumo do plano
B2: Resumo do plano
B4: Tipo de midia | C4: Valor líquido | D4: Share | E4: Impactos | F4: CPM View | H4: Ambiente | I4: Valor líquido | J4: Share | K4: Impactos | L4: CPM View | N4: Formato | O4: Valor líquido | P4: Share | Q4: Impactos | R4: CPM View | U4: Praça | V4: Valor líquido | W4: Share | X4: Impactos | Y4: CPM View | AA4: Exibidor | AB4: Valor líquido | AC4: Share | AD4: Impactos | AE4: CPM View
B5: Total | C5: =SUM(C6:C500) -> 0 | D5: =SUM(D6:D500) -> #DIV/0! | E5: =SUM(E6:E500) -> 0 | F5: =+C5/(E5/1000) -> #DIV/0! | H5: Total | I5: =SUM(I6:I500) -> 0 | J5: =SUM(J6:J500) -> #DIV/0! | K5: =SUM(K6:K500) -> 0 | L5: =+I5/(K5/1000) -> #DIV/0! | N5: Total | O5: =SUM(O6:O500) -> 0 | P5: =SUM(P6:P500) -> #DIV/0! | Q5: =SUM(Q6:Q500) -> 0 | R5: =+O5/(Q5/1000) -> #DIV/0! | U5: Total | V5: =SUM(V6:V500) -> 0 | W5: =SUM(W6:W500) -> #DIV/0! | X5: =SUM(X6:X500) -> 0 | Y5: =+V5/(X5/1000) -> #DIV/0! | AA5: Total | AB5: =SUM(AB6:AB500) -> 0 | AC5: =SUM(AC6:AC500) -> #DIV/0! | AD5: =SUM(AD6:AD500) -> 0 | AE5: =+AB5/(AD5/1000) -> #DIV/0!
B6: Digital | C6: =SUMIFS(OOH!CV:CV,OOH!R:R,'Resumo do plano'!B6) -> 0 | D6: =+C6/$C$5 -> #DIV/0! | E6: =SUMIFS(OOH!CX:CX,OOH!R:R,'Resumo do plano'!B6) -> 0 | F6: =+C6/(E6/1000) -> #DIV/0! | H6: {=_xlfn._xlws.SORT(_xlfn.UNIQUE(OOH!N3:N490))} -> 0 | I6: =SUMIFS(OOH!CV:CV,OOH!N:N,'Resumo do plano'!H6) -> 0 | J6: =+I6/$C$5 -> #DIV/0! | K6: =SUMIFS(OOH!CX:CX,OOH!N:N,'Resumo do plano'!H6) -> 0 | L6: =IFERROR(I6/(K6/1000),0) -> 0 | N6: {=_xlfn._xlws.SORT(_xlfn.UNIQUE(OOH!O3:O490))} -> Abrigo De Ônibus Estático | O6: =SUMIFS(OOH!CV:CV,OOH!O:O,'Resumo do plano'!N6) -> 0 | P6: =+O6/$C$5 -> #DIV/0! | Q6: =SUMIFS(OOH!CX:CX,OOH!O:O,'Resumo do plano'!N6) -> 0 | R6: =IFERROR(O6/(Q6/1000),0) -> 0 | T6: Praça 1 | U6: {=_xlfn._xlws.SORT(_xlfn.UNIQUE(OOH!L3:L490))} -> 0 | V6: =SUMIFS(OOH!CV:CV,OOH!L:L,'Resumo do plano'!U6) -> 0 | W6: =+V6/$C$5 -> #DIV/0! | X6: =SUMIFS(OOH!CX:CX,OOH!L:L,'Resumo do plano'!U6) -> 0 | Y6: =IFERROR(V6/(X6/1000),0) -> 0 | AA6: {=_xlfn._xlws.SORT(_xlfn.UNIQUE(OOH!M3:M490))} -> 0 | AB6: =SUMIFS(OOH!CV:CV,OOH!M:M,'Resumo do plano'!AA6) -> 0 | AC6: =+AB6/$C$5 -> #DIV/0! | AD6: =SUMIFS(OOH!CX:CX,OOH!M:M,'Resumo do plano'!AA6) -> 0 | AE6: =IFERROR(AB6/(AD6/1000),0) -> 0
B7: Estático | C7: =SUMIFS(OOH!CV:CV,OOH!R:R,'Resumo do plano'!B7) -> 0 | D7: =+C7/$C$5 -> #DIV/0! | E7: =SUMIFS(OOH!CX:CX,OOH!R:R,'Resumo do plano'!B7) -> 0 | F7: =+C7/(E7/1000) -> #DIV/0! | I7: =SUMIFS(OOH!CV:CV,OOH!N:N,'Resumo do plano'!H7) -> 0 | J7: =+I7/$C$5 -> #DIV/0! | K7: =SUMIFS(OOH!CX:CX,OOH!N:N,'Resumo do plano'!H7) -> 0 | L7: =IFERROR(I7/(K7/1000),0) -> 0 | N7: 0 | O7: =SUMIFS(OOH!CV:CV,OOH!O:O,'Resumo do plano'!N7) -> 0 | P7: =+O7/$C$5 -> #DIV/0! | Q7: =SUMIFS(OOH!CX:CX,OOH!O:O,'Resumo do plano'!N7) -> 0 | R7: =IFERROR(O7/(Q7/1000),0) -> 0 | T7: Praça 2 | V7: =SUMIFS(OOH!CV:CV,OOH!L:L,'Resumo do plano'!U7) -> 0 | W7: =+V7/$C$5 -> #DIV/0! | X7: =SUMIFS(OOH!CX:CX,OOH!L:L,'Resumo do plano'!U7) -> 0 | Y7: =IFERROR(V7/(X7/1000),0) -> 0 | AB7: =SUMIFS(OOH!CV:CV,OOH!M:M,'Resumo do plano'!AA7) -> 0 | AC7: =+AB7/$C$5 -> #DIV/0! | AD7: =SUMIFS(OOH!CX:CX,OOH!M:M,'Resumo do plano'!AA7) -> 0 | AE7: =IFERROR(AB7/(AD7/1000),0) -> 0
I8: =SUMIFS(OOH!CV:CV,OOH!N:N,'Resumo do plano'!H8) -> 0 | J8: =+I8/$C$5 -> #DIV/0! | K8: =SUMIFS(OOH!CX:CX,OOH!N:N,'Resumo do plano'!H8) -> 0 | L8: =IFERROR(I8/(K8/1000),0) -> 0 | O8: =SUMIFS(OOH!CV:CV,OOH!O:O,'Resumo do plano'!N8) -> 0 | P8: =+O8/$C$5 -> #DIV/0! | Q8: =SUMIFS(OOH!CX:CX,OOH!O:O,'Resumo do plano'!N8) -> 0 | R8: =IFERROR(O8/(Q8/1000),0) -> 0 | T8: Praça 3 | V8: =SUMIFS(OOH!CV:CV,OOH!L:L,'Resumo do plano'!U8) -> 0 | W8: =+V8/$C$5 -> #DIV/0! | X8: =SUMIFS(OOH!CX:CX,OOH!L:L,'Resumo do plano'!U8) -> 0 | Y8: =IFERROR(V8/(X8/1000),0) -> 0 | AB8: =SUMIFS(OOH!CV:CV,OOH!M:M,'Resumo do plano'!AA8) -> 0 | AC8: =+AB8/$C$5 -> #DIV/0! | AD8: =SUMIFS(OOH!CX:CX,OOH!M:M,'Resumo do plano'!AA8) -> 0 | AE8: =IFERROR(AB8/(AD8/1000),0) -> 0
I9: =SUMIFS(OOH!CV:CV,OOH!N:N,'Resumo do plano'!H9) -> 0 | J9: =+I9/$C$5 -> #DIV/0! | K9: =SUMIFS(OOH!CX:CX,OOH!N:N,'Resumo do plano'!H9) -> 0 | L9: =IFERROR(I9/(K9/1000),0) -> 0 | O9: =SUMIFS(OOH!CV:CV,OOH!O:O,'Resumo do plano'!N9) -> 0 | P9: =+O9/$C$5 -> #DIV/0! | Q9: =SUMIFS(OOH!CX:CX,OOH!O:O,'Resumo do plano'!N9) -> 0 | R9: =IFERROR(O9/(Q9/1000),0) -> 0 | T9: Praça 4 | V9: =SUMIFS(OOH!CV:CV,OOH!L:L,'Resumo do plano'!U9) -> 0 | W9: =+V9/$C$5 -> #DIV/0! | X9: =SUMIFS(OOH!CX:CX,OOH!L:L,'Resumo do plano'!U9) -> 0 | Y9: =IFERROR(V9/(X9/1000),0) -> 0 | AB9: =SUMIFS(OOH!CV:CV,OOH!M:M,'Resumo do plano'!AA9) -> 0 | AC9: =+AB9/$C$5 -> #DIV/0! | AD9: =SUMIFS(OOH!CX:CX,OOH!M:M,'Resumo do plano'!AA9) -> 0 | AE9: =IFERROR(AB9/(AD9/1000),0) -> 0
I10: =SUMIFS(OOH!CV:CV,OOH!N:N,'Resumo do plano'!H10) -> 0 | J10: =+I10/$C$5 -> #DIV/0! | K10: =SUMIFS(OOH!CX:CX,OOH!N:N,'Resumo do plano'!H10) -> 0 | L10: =IFERROR(I10/(K10/1000),0) -> 0 | O10: =SUMIFS(OOH!CV:CV,OOH!O:O,'Resumo do plano'!N10) -> 0 | P10: =+O10/$C$5 -> #DIV/0! | Q10: =SUMIFS(OOH!CX:CX,OOH!O:O,'Resumo do plano'!N10) -> 0 | R10: =IFERROR(O10/(Q10/1000),0) -> 0 | T10: Praça 5 | V10: =SUMIFS(OOH!CV:CV,OOH!L:L,'Resumo do plano'!U10) -> 0 | W10: =+V10/$C$5 -> #DIV/0! | X10: =SUMIFS(OOH!CX:CX,OOH!L:L,'Resumo do plano'!U10) -> 0 | Y10: =IFERROR(V10/(X10/1000),0) -> 0 | AB10: =SUMIFS(OOH!CV:CV,OOH!M:M,'Resumo do plano'!AA10) -> 0 | AC10: =+AB10/$C$5 -> #DIV/0! | AD10: =SUMIFS(OOH!CX:CX,OOH!M:M,'Resumo do plano'!AA10) -> 0 | AE10: =IFERROR(AB10/(AD10/1000),0) -> 0
I11: =SUMIFS(OOH!CV:CV,OOH!N:N,'Resumo do plano'!H11) -> 0 | J11: =+I11/$C$5 -> #DIV/0! | K11: =SUMIFS(OOH!CX:CX,OOH!N:N,'Resumo do plano'!H11) -> 0 | L11: =IFERROR(I11/(K11/1000),0) -> 0 | O11: =SUMIFS(OOH!CV:CV,OOH!O:O,'Resumo do plano'!N11) -> 0 | P11: =+O11/$C$5 -> #DIV/0! | Q11: =SUMIFS(OOH!CX:CX,OOH!O:O,'Resumo do plano'!N11) -> 0 | R11: =IFERROR(O11/(Q11/1000),0) -> 0 | T11: Praça 6 | V11: =SUMIFS(OOH!CV:CV,OOH!L:L,'Resumo do plano'!U11) -> 0 | W11: =+V11/$C$5 -> #DIV/0! | X11: =SUMIFS(OOH!CX:CX,OOH!L:L,'Resumo do plano'!U11) -> 0 | Y11: =IFERROR(V11/(X11/1000),0) -> 0 | AB11: =SUMIFS(OOH!CV:CV,OOH!M:M,'Resumo do plano'!AA11) -> 0 | AC11: =+AB11/$C$5 -> #DIV/0! | AD11: =SUMIFS(OOH!CX:CX,OOH!M:M,'Resumo do plano'!AA11) -> 0 | AE11: =IFERROR(AB11/(AD11/1000),0) -> 0
I12: =SUMIFS(OOH!CV:CV,OOH!N:N,'Resumo do plano'!H12) -> 0 | J12: =+I12/$C$5 -> #DIV/0! | K12: =SUMIFS(OOH!CX:CX,OOH!N:N,'Resumo do plano'!H12) -> 0 | L12: =IFERROR(I12/(K12/1000),0) -> 0 | O12: =SUMIFS(OOH!CV:CV,OOH!O:O,'Resumo do plano'!N12) -> 0 | P12: =+O12/$C$5 -> #DIV/0! | Q12: =SUMIFS(OOH!CX:CX,OOH!O:O,'Resumo do plano'!N12) -> 0 | R12: =IFERROR(O12/(Q12/1000),0) -> 0 | T12: Praça 7 | V12: =SUMIFS(OOH!CV:CV,OOH!L:L,'Resumo do plano'!U12) -> 0 | W12: =+V12/$C$5 -> #DIV/0! | X12: =SUMIFS(OOH!CX:CX,OOH!L:L,'Resumo do plano'!U12) -> 0 | Y12: =IFERROR(V12/(X12/1000),0) -> 0 | AB12: =SUMIFS(OOH!CV:CV,OOH!M:M,'Resumo do plano'!AA12) -> 0 | AC12: =+AB12/$C$5 -> #DIV/0! | AD12: =SUMIFS(OOH!CX:CX,OOH!M:M,'Resumo do plano'!AA12) -> 0 | AE12: =IFERROR(AB12/(AD12/1000),0) -> 0
I13: =SUMIFS(OOH!CV:CV,OOH!N:N,'Resumo do plano'!H13) -> 0 | J13: =+I13/$C$5 -> #DIV/0! | K13: =SUMIFS(OOH!CX:CX,OOH!N:N,'Resumo do plano'!H13) -> 0 | L13: =IFERROR(I13/(K13/1000),0) -> 0 | O13: =SUMIFS(OOH!CV:CV,OOH!O:O,'Resumo do plano'!N13) -> 0 | P13: =+O13/$C$5 -> #DIV/0! | Q13: =SUMIFS(OOH!CX:CX,OOH!O:O,'Resumo do plano'!N13) -> 0 | R13: =IFERROR(O13/(Q13/1000),0) -> 0 | T13: Praça 8 | V13: =SUMIFS(OOH!CV:CV,OOH!L:L,'Resumo do plano'!U13) -> 0 | W13: =+V13/$C$5 -> #DIV/0! | X13: =SUMIFS(OOH!CX:CX,OOH!L:L,'Resumo do plano'!U13) -> 0 | Y13: =IFERROR(V13/(X13/1000),0) -> 0 | AB13: =SUMIFS(OOH!CV:CV,OOH!M:M,'Resumo do plano'!AA13) -> 0 | AC13: =+AB13/$C$5 -> #DIV/0! | AD13: =SUMIFS(OOH!CX:CX,OOH!M:M,'Resumo do plano'!AA13) -> 0 | AE13: =IFERROR(AB13/(AD13/1000),0) -> 0
I14: =SUMIFS(OOH!CV:CV,OOH!N:N,'Resumo do plano'!H14) -> 0 | J14: =+I14/$C$5 -> #DIV/0! | K14: =SUMIFS(OOH!CX:CX,OOH!N:N,'Resumo do plano'!H14) -> 0 | L14: =IFERROR(I14/(K14/1000),0) -> 0 | O14: =SUMIFS(OOH!CV:CV,OOH!O:O,'Resumo do plano'!N14) -> 0 | P14: =+O14/$C$5 -> #DIV/0! | Q14: =SUMIFS(OOH!CX:CX,OOH!O:O,'Resumo do plano'!N14) -> 0 | R14: =IFERROR(O14/(Q14/1000),0) -> 0 | T14: Praça 9 | V14: =SUMIFS(OOH!CV:CV,OOH!L:L,'Resumo do plano'!U14) -> 0 | W14: =+V14/$C$5 -> #DIV/0! | X14: =SUMIFS(OOH!CX:CX,OOH!L:L,'Resumo do plano'!U14) -> 0 | Y14: =IFERROR(V14/(X14/1000),0) -> 0 | AB14: =SUMIFS(OOH!CV:CV,OOH!M:M,'Resumo do plano'!AA14) -> 0 | AC14: =+AB14/$C$5 -> #DIV/0! | AD14: =SUMIFS(OOH!CX:CX,OOH!M:M,'Resumo do plano'!AA14) -> 0 | AE14: =IFERROR(AB14/(AD14/1000),0) -> 0
I15: =SUMIFS(OOH!CV:CV,OOH!N:N,'Resumo do plano'!H15) -> 0 | J15: =+I15/$C$5 -> #DIV/0! | K15: =SUMIFS(OOH!CX:CX,OOH!N:N,'Resumo do plano'!H15) -> 0 | L15: =IFERROR(I15/(K15/1000),0) -> 0 | O15: =SUMIFS(OOH!CV:CV,OOH!O:O,'Resumo do plano'!N15) -> 0 | P15: =+O15/$C$5 -> #DIV/0! | Q15: =SUMIFS(OOH!CX:CX,OOH!O:O,'Resumo do plano'!N15) -> 0 | R15: =IFERROR(O15/(Q15/1000),0) -> 0 | T15: Praça 10 | V15: =SUMIFS(OOH!CV:CV,OOH!L:L,'Resumo do plano'!U15) -> 0 | W15: =+V15/$C$5 -> #DIV/0! | X15: =SUMIFS(OOH!CX:CX,OOH!L:L,'Resumo do plano'!U15) -> 0 | Y15: =IFERROR(V15/(X15/1000),0) -> 0 | AB15: =SUMIFS(OOH!CV:CV,OOH!M:M,'Resumo do plano'!AA15) -> 0 | AC15: =+AB15/$C$5 -> #DIV/0! | AD15: =SUMIFS(OOH!CX:CX,OOH!M:M,'Resumo do plano'!AA15) -> 0 | AE15: =IFERROR(AB15/(AD15/1000),0) -> 0
I16: =SUMIFS(OOH!CV:CV,OOH!N:N,'Resumo do plano'!H16) -> 0 | J16: =+I16/$C$5 -> #DIV/0! | K16: =SUMIFS(OOH!CX:CX,OOH!N:N,'Resumo do plano'!H16) -> 0 | L16: =IFERROR(I16/(K16/1000),0) -> 0 | O16: =SUMIFS(OOH!CV:CV,OOH!O:O,'Resumo do plano'!N16) -> 0 | P16: =+O16/$C$5 -> #DIV/0! | Q16: =SUMIFS(OOH!CX:CX,OOH!O:O,'Resumo do plano'!N16) -> 0 | R16: =IFERROR(O16/(Q16/1000),0) -> 0 | T16: Praça 11 | V16: =SUMIFS(OOH!CV:CV,OOH!L:L,'Resumo do plano'!U16) -> 0 | W16: =+V16/$C$5 -> #DIV/0! | X16: =SUMIFS(OOH!CX:CX,OOH!L:L,'Resumo do plano'!U16) -> 0 | Y16: =IFERROR(V16/(X16/1000),0) -> 0 | AB16: =SUMIFS(OOH!CV:CV,OOH!M:M,'Resumo do plano'!AA16) -> 0 | AC16: =+AB16/$C$5 -> #DIV/0! | AD16: =SUMIFS(OOH!CX:CX,OOH!M:M,'Resumo do plano'!AA16) -> 0 | AE16: =IFERROR(AB16/(AD16/1000),0) -> 0
I17: =SUMIFS(OOH!CV:CV,OOH!N:N,'Resumo do plano'!H17) -> 0 | J17: =+I17/$C$5 -> #DIV/0! | K17: =SUMIFS(OOH!CX:CX,OOH!N:N,'Resumo do plano'!H17) -> 0 | L17: =IFERROR(I17/(K17/1000),0) -> 0 | O17: =SUMIFS(OOH!CV:CV,OOH!O:O,'Resumo do plano'!N17) -> 0 | P17: =+O17/$C$5 -> #DIV/0! | Q17: =SUMIFS(OOH!CX:CX,OOH!O:O,'Resumo do plano'!N17) -> 0 | R17: =IFERROR(O17/(Q17/1000),0) -> 0 | T17: Praça 12 | V17: =SUMIFS(OOH!CV:CV,OOH!L:L,'Resumo do plano'!U17) -> 0 | W17: =+V17/$C$5 -> #DIV/0! | X17: =SUMIFS(OOH!CX:CX,OOH!L:L,'Resumo do plano'!U17) -> 0 | Y17: =IFERROR(V17/(X17/1000),0) -> 0 | AB17: =SUMIFS(OOH!CV:CV,OOH!M:M,'Resumo do plano'!AA17) -> 0 | AC17: =+AB17/$C$5 -> #DIV/0! | AD17: =SUMIFS(OOH!CX:CX,OOH!M:M,'Resumo do plano'!AA17) -> 0 | AE17: =IFERROR(AB17/(AD17/1000),0) -> 0
I18: =SUMIFS(OOH!CV:CV,OOH!N:N,'Resumo do plano'!H18) -> 0 | J18: =+I18/$C$5 -> #DIV/0! | K18: =SUMIFS(OOH!CX:CX,OOH!N:N,'Resumo do plano'!H18) -> 0 | L18: =IFERROR(I18/(K18/1000),0) -> 0 | O18: =SUMIFS(OOH!CV:CV,OOH!O:O,'Resumo do plano'!N18) -> 0 | P18: =+O18/$C$5 -> #DIV/0! | Q18: =SUMIFS(OOH!CX:CX,OOH!O:O,'Resumo do plano'!N18) -> 0 | R18: =IFERROR(O18/(Q18/1000),0) -> 0 | T18: Praça 13 | V18: =SUMIFS(OOH!CV:CV,OOH!L:L,'Resumo do plano'!U18) -> 0 | W18: =+V18/$C$5 -> #DIV/0! | X18: =SUMIFS(OOH!CX:CX,OOH!L:L,'Resumo do plano'!U18) -> 0 | Y18: =IFERROR(V18/(X18/1000),0) -> 0 | AB18: =SUMIFS(OOH!CV:CV,OOH!M:M,'Resumo do plano'!AA18) -> 0 | AC18: =+AB18/$C$5 -> #DIV/0! | AD18: =SUMIFS(OOH!CX:CX,OOH!M:M,'Resumo do plano'!AA18) -> 0 | AE18: =IFERROR(AB18/(AD18/1000),0) -> 0
I19: =SUMIFS(OOH!CV:CV,OOH!N:N,'Resumo do plano'!H19) -> 0 | J19: =+I19/$C$5 -> #DIV/0! | K19: =SUMIFS(OOH!CX:CX,OOH!N:N,'Resumo do plano'!H19) -> 0 | L19: =IFERROR(I19/(K19/1000),0) -> 0 | O19: =SUMIFS(OOH!CV:CV,OOH!O:O,'Resumo do plano'!N19) -> 0 | P19: =+O19/$C$5 -> #DIV/0! | Q19: =SUMIFS(OOH!CX:CX,OOH!O:O,'Resumo do plano'!N19) -> 0 | R19: =IFERROR(O19/(Q19/1000),0) -> 0 | T19: Praça 14 | V19: =SUMIFS(OOH!CV:CV,OOH!L:L,'Resumo do plano'!U19) -> 0 | W19: =+V19/$C$5 -> #DIV/0! | X19: =SUMIFS(OOH!CX:CX,OOH!L:L,'Resumo do plano'!U19) -> 0 | Y19: =IFERROR(V19/(X19/1000),0) -> 0 | AB19: =SUMIFS(OOH!CV:CV,OOH!M:M,'Resumo do plano'!AA19) -> 0 | AC19: =+AB19/$C$5 -> #DIV/0! | AD19: =SUMIFS(OOH!CX:CX,OOH!M:M,'Resumo do plano'!AA19) -> 0 | AE19: =IFERROR(AB19/(AD19/1000),0) -> 0
... I24: =SUMIFS(OOH!CV:CV,OOH!N:N,'Resumo do plano'!H24) -> 0 | J24: =+I24/$C$5 -> #DIV/0! | K24: =SUMIFS(OOH!CX:CX,OOH!N:N,'Resumo do plano'!H24) -> 0 | L24: =IFERROR(I24/(K24/1000),0) -> 0 | O24: =SUMIFS(OOH!CV:CV,OOH!O:O,'Resumo do plano'!N24) -> 0 | P24: =+O24/$C$5 -> #DIV/0! | Q24: =SUMIFS(OOH!CX:CX,OOH!O:O,'Resumo do plano'!N24) -> 0 | R24: =IFERROR(O24/(Q24/1000),0) -> 0 | T24: Praça 19 | V24: =SUMIFS(OOH!CV:CV,OOH!L:L,'Resumo do plano'!U24) -> 0 | W24: =+V24/$C$5 -> #DIV/0! | X24: =SUMIFS(OOH!CX:CX,OOH!L:L,'Resumo do plano'!U24) -> 0 | Y24: =IFERROR(V24/(X24/1000),0) -> 0 | AB24: =SUMIFS(OOH!CV:CV,OOH!M:M,'Resumo do plano'!AA24) -> 0 | AC24: =+AB24/$C$5 -> #DIV/0! | AD24: =SUMIFS(OOH!CX:CX,OOH!M:M,'Resumo do plano'!AA24) -> 0 | AE24: =IFERROR(AB24/(AD24/1000),0) -> 0
T25: Praça 20
T26: Praça 21
T27: Praça 22
T28: Praça 23
T29: Praça 24
T30: Praça 25
T31: Praça 26
T32: Praça 27
T33: Praça 28
T34: Praça 29
T35: Praça 30
T36: Praça 31
... T125: Praça 120

Sheet Parametros
B1: TIPO DE NEGOCIAÇÃO | E1: TIPO DE PERÍODO | F1: No. dias | H1: Exibidores | J1: Formato | K1: Grupo | L1: IPV | N1: Estado | O1: Cidade | Q1: Estado | S1: Tipos de midia | V1: Ambiente | W1: IPV | Z1: Tipo de plano | AB1: Mês | AC1: No. de dias | AE1: Targets por marca | AI1: Classif para P1A | AL1: Deflator de visibilidade | AM1: Coef
B2: Carta | C2: Faturável | E2: Bi-semana | F2: 14 | H2: JCDECAUX | J2: Abrigo De Ônibus Digital | K2: G5MD | L2: 0.6 | N2: GO | O2: ABADIA DE GOIÁS | Q2: SP | S2: Estático | V2: Via pública | Z2: Megabrands | AB2: 45658 | AC2: 31 | AL2: Baixa visibilidade | AM2: 0.25
B3: Compromisso | C3: Faturável | E3: Quinzenal | F3: 15 | H3: ELETROMIDIA | J3: Abrigo De Ônibus Estático | K3: G3ME | L3: 0.5 | N3: GO | O3: ABADIÂNIA | Q3: RJ | S3: Digital | V3: Academia | W3: 0.4 | Z3: Avulso M G | AB3: =EDATE(AB2,1) -> 45689 | AC3: 28 | AE3: CERVEJA MAINSTREAM | AF3: Brahma | AG3: AS ABCDE 18+ | AI3: Jcdecaux | AJ3: Jcdecaux | AL3: Média visibilidade | AM3: 0.5
B4: Avulso | C4: Faturável | E4: Semanal | F4: 7 | H4: CLEAR CHANNEL | J4: Abrigo De Ônibus Sequencial | K4: G3ME | L4: 0.5 | N4: SC | O4: ABELARDO LUZ | Q4: BH | S4: Itinerante | V4: Aeroporto | W4: 0.5 | Z4: Avulso P | AB4: =EDATE(AB3,1) -> 45717 | AC4: 31 | AE4: CERVEJA MAINSTREAM | AF4: Skol | AG4: AS CDE 18+ | AI4: Eletromidia | AJ4: Eletromidia | AL4: Moderada visibilidade | AM4: 0.75
B5: Pontos fixos | C5: Faturável | E5: 28 dias | F5: 28 | H5: MOVIE MIDIA | J5: Adesivação De Bloqueios | K5: G6 | L5: 0.15 | N5: PE | O5: ABREU E LIMA | Q5: MG | S5: Spot | V5: Agência Bancaria | W5: 0.4 | AB5: =EDATE(AB4,1) -> 45748 | AC5: 30 | AE5: CERVEJA PREMIUM | AF5: Stella Artois | AG5: AS ABC 25+ | AI5: Urbia | AJ5: Urbia | AL5: Alta visibilidade | AM5: 1
B6: Rateio | C6: Faturável | E6: Diária | F6: 1 | H6: MUDE | J6: Adesivação De Escada Rolante | K6: G6 | L6: 0.15 | N6: MA | O6: AÇAILÂNDIA | Q6: ES | V6: Bar | W6: 0.4 | AB6: =EDATE(AB5,1) -> 45778 | AC6: 31 | AE6: Bebida Mista | AF6: Beats | AG6: AS ABC 18-34 | AI6: Pacote empena RJ | AJ6: Pacote empena RJ
B7: Reaplicação compromisso | C7: Não faturável | E7: 26 dias | F7: 26 | H7: KALLAS | J7: Adesivação Externa Fingers | K7: G6 | L7: 0.15 | N7: SP | O7: ABREU E LIMA | Q7: PE | V7: Brt | W7: 0.15 | AB7: =EDATE(AB6,1) -> 45809 | AC7: 30 | AE7: CERVEJA PREMIUM | AF7: Corona | AG7: AS AB 18+ | AI7: Rateio SSA | AJ7: Rateio SSA
B8: Reaplicação carta | C8: Não faturável | E8: Mensal | F8: 30 | H8: URBIA | J8: Adesivação Interna Fingers | K8: G6 | L8: 0.15 | N8: RS | O8: AGRONOMIA | Q8: BA | V8: Centro Comercial | W8: 0.4 | AB8: =EDATE(AB7,1) -> 45839 | AC8: 31 | AE8: CERVEJA PREMIUM | AF8: Budweiser | AG8: AS ABC 18+ | AI8: Banka | AJ8: Pacote banka
B9: Reaplicação avulsa | C9: Não faturável | H9: NEOOH | J9: Adesivo | K9: G6 | L9: 0.15 | N9: SP | O9: ÁGUAS DE LINDÓIA | Q9: RS | V9: Clube | W9: 0.6 | AB9: =EDATE(AB8,1) -> 45870 | AC9: 31 | AE9: CERVEJA PREMIUM | AF9: Spaten | AG9: AS ABC 18+ | AI9: Demais OOH | AJ9: Demais OOH
B10: Reaplicação ESG | C10: Não faturável | H10: HEZAGONO | J10: Adesivo Fundo De Esteira | K10: G6 | L10: 0.15 | N10: SC | O10: ÁGUAS MORNAS | Q10: SC | V10: Comunidade | W10: 0.25 | AB10: =EDATE(AB9,1) -> 45901 | AC10: 30 | AE10: Refrigerante | AF10: Guaraná | AG10: AS ABCD 18+
B11: Rebate | C11: Não faturável | H11: HELLOO | J11: Adesivo Lateral | K11: G6 | L11: 0.15 | N11: BA | O11: ALAGOINHAS | Q11: PR | V11: Cptm | W11: 0.15 | AB11: =EDATE(AB10,1) -> 45931 | AC11: 30 | AF11: MIKES | AG11: AS ABC 18-34
B12: Bonificação | C12: Não faturável | H12: URBANA MIDIA | J12: Ambientação | K12: G6 | L12: 0.15 | N12: SP | O12: ALAMBARI | Q12: AC | V12: Edifício Comercial | W12: 0.75 | AB12: =EDATE(AB11,1) -> 45962 | AC12: 30 | AF12: BRUTAL | AG12: AS ABC 18-34
B13: Empenas RJ | C13: Faturável | H13: GRUPO CORUJA | J13: Backbus | K13: G4 | L13: 0.4 | N13: MG | O13: ALÉM PARAÍBA | Q13: AL | V13: Edifício Residencial | W13: 0.75 | AB13: =EDATE(AB12,1) -> 45992 | AC13: 31 | AF13: ZÉ DELIVERY | AG13: AS ABCDE 20-44
B14: Rateio SSA | C14: Não faturável | H14: NÓS | J14: Backlight | K14: G6 | L14: 0.15 | N14: GO | O14: ALEXÂNIA | Q14: AM | V14: Estabelecimento comercial | W14: 0.4 | AF14: TONICA | AG14: AS AB 25+
H15: RZK | J15: Backseat | K15: G6 | L15: 0.09 | N15: MG | O15: ALFENAS | Q15: AP | V15: Estadio e casas de show | W15: 0.4 | AF15: FUSION | AG15: AS ABCDE 18+
H16: WESUPEROOH | J16: Banca De Jornal Digital | K16: G5MD | L16: 0.6 | N16: PE | O16: ALIANÇA | Q16: CE | V16: Farmácia | W16: 0.4 | AF16: AMA | AG16: AS ABCDE 18+
H17: MULTIPLAN | J17: Banca De Jornal Estática | K17: G3ME | L17: 0.5 | N17: PR | O17: ALMIRANTE TAMANDARÉ | Q17: DF | V17: Hotel | W17: 0.6
H18: OOH BRASIL | J18: Banca Estação | K18: G6 | L18: 0.15 | N18: RS | O18: ALPESTRE | Q18: GO | V18: Loja de Conveniência | W18: 0.4
H19: PRISMA RJ | J19: Banner | K19: G6 | L19: 0.15 | N19: RS | O19: ALTO PETRÓPOLIS | Q19: MA | V19: Metrô | W19: 0.15
H20: REDE OUTLIGHT | J20: Banner De Led | K20: G6 | L20: 0.15 | N20: SP | O20: ALUMÍNIO | Q20: MS | V20: Monotrilho | W20: 0.15
H21: BANDEIRANTES | J21: Banner Digital | K21: G2D | L21: 0.788 | N21: RS | O21: ALVORADA | Q21: MT | V21: Padaria | W21: 0.4
H22: ALTO IMPACTO | J22: Biciletário Estático | K22: G3ME | L22: 0.5 | N22: SP | O22: AMERICANA | Q22: PA | V22: Parque | W22: 0.4
H23: CAPITAL MIDIA | J23: Big Adesivo | K23: G6 | L23: 0.15 | N23: SP | O23: AMPARO | Q23: PB | V23: Porto | W23: 0.15
H24: SINERGY | J24: Big Led | K24: G2D | L24: 0.788 | N24: PA | O24: ANANINDEUA | Q24: PI | V24: Praia | W24: 0.6
H25: RIOVERDE | J25: Big Mupi | K25: G2D | L25: 0.788 | N25: GO | O25: ANÁPOLIS | Q25: RN | V25: Restaurantes | W25: 0.4
H26: LACTOM | J26: Big Testeira | K26: G6 | L26: 0.15 | N26: RS | O26: ANCHIETA | Q26: RO | V26: Rodoviária | W26: 0.15
H27: TOMI | J27: Brt Envelopado | K27: G4 | L27: 0.4 | N27: MG | O27: ANDRADAS | Q27: RR | V27: Salão de Beleza / Barbearia | W27: 0.6
H28: RETAIL MEDIA | J28: Busdoor | K28: G4 | L28: 0.4 | N28: SP | O28: ANDRADINA | Q28: SE | V28: Saúde | W28: 0.4
H29: PRISMA - BELEM | J29: Caixa Dagua | K29: G1E | L29: 0.92 | N29: RJ | O29: ANGRA DOS REIS | Q29: TO | V29: Shopping | W29: 0.6
H30: I7 MÍDIA | J30: Caixa De Pizza | K30: G6 | L30: 0.15 | N30: PR | O30: ANTÔNIO OLINTO | V30: Supermercado | W30: 0.5
H31: WAM PLANEJAMENTO | J31: Cancela De Pedágio | K31: G2E | L31: 0.75 | N31: GO | O31: APARECIDA DE GOIÂNIA | V31: Supervia | W31: 0.15
H32: GRUPO SOOH | J32: Carro De Som | K32: G4 | L32: 0.4 | N32: SP | O32: APIAÍ | V32: Táxi / Carro Aplicativo | W32: 0.15
H33: ROTA MÍDIA | J33: Carrossel Esteiras De Bagagem | K33: G6 | L33: 0.15 | N33: PR | O33: APUCARANA | V33: Terminal Náutico | W33: 0.15
H34: FAVRETTO | J34: Circuito Air Mub | K34: G6 | L34: 0.15 | N34: MS | O34: AQUIDAUANA | V34: Terminal Urbano | W34: 0.15
H35: PIXEL MIDIA | J35: Circuito Digital Indoor | K35: G6 | L35: 0.15 | N35: CE | O35: AQUIRAZ | V35: Universidade | W35: 0.4
H36: MOBEES | J36: Circuito Digital + Icônico Circular | K36: G6 | L36: 0.15 | N36: SE | O36: ARACAJU | V36: Vlt | W36: 0.15
H37: ALINHARES | J37: Circuito Experiência | K37: G6 | L37: 0.15 | N37: CE | O37: ARACATI
H38: BIG DOOH | J38: Circuito Passarelas | K38: G6 | L38: 0.15 | N38: SP | O38: ARAÇATUBA
H39: COOHNECT | J39: Colunas | K39: G6 | L39: 0.15 | N39: GO | O39: ARAGUAPAZ
H40: RPMIDIA | J40: Conjunto De Vidro | K40: G6 | L40: 0.15 | N40: MG | O40: ARAGUARI
H41: JCPM | J41: Digital – Fids | K41: G6 | L41: 0.15 | N41: AL | O41: ARAPIRACA
H42: BE 180 | J42: Digital Interno De Trem | K42: G6 | L42: 0.15 | N42: PR | O42: ARAPONGAS
H43: IDEAL PUBLICIDADE | J43: Display Digital | K43: G6 | L43: 0.15 | N43: SC | O43: ARAQUARI
H44: TREND | J44: Dominação | K44: G6 | L44: 0.15 | N44: SC | O44: ARARANGUÁ
H45: MILLENIUM | J45: Empena Digital | K45: G1D | L45: 0.966 | N45: SP | O45: ARARAQUARA
H46: OUTMIDIA | J46: Empena Dupla | K46: G1E | L46: 0.92 | N46: SP | O46: ARARAS
H47: ONBUS | J47: Empena Estática | K47: G1E | L47: 0.92 | N47: RS | O47: ARARICÁ
H48: BDROPS | J48: E-Truck | K48: G4 | L48: 0.4 | N48: PE | O48: ARARIPINA
... H138: A7 RNF | J138: Painel Estático | K138: G6 | L138: 0.15 | N138: SC | O138: CAMBORIU
H139: DESTAQUE OUTDOOR | N139: MG | O139: CAMBUÍ
H140: PUBLIRIO | N140: MG | O140: CAMPANÁRIO
H141: COLOR OUTDOOR | N141: PB | O141: CAMPINA GRANDE
H142: SERGILUX | N142: PR | O142: CAMPINA GRANDE DO SUL
H143: MIDAS MIDIA | N143: SP | O143: CAMPINAS
H144: FLIX MÍDIA | N144: GO | O144: CAMPINORTE
H145: A13 MÍDIA | N145: GO | O145: CAMPO ALEGRE DE GOIÁS
H146: GOL MIDIA | N146: MG | O146: CAMPO BELO
H147: NURBS | N147: RS | O147: CAMPO BOM
H148: EL MÍDIA | N148: PR | O148: CAMPO DO TENENTE
H149: PONTO OUTDOOR | N149: MS | O149: CAMPO GRANDE
H150: ADVANTAGE | N150: PR | O150: CAMPO LARGO
... H252: DISPLAYTECH | N252: GO | O252: FORMOSA
H253: #N/A | N253: BA | O253: FORMOSA DO RIO PRETO
H254: 12 OUTDOOR | N254: CE | O254: FORTALEZA
H255: 29HORAS | N255: PR | O255: FOZ DO IGUAÇU
H256: AÇÃO VISUAL | N256: SP | O256: FRANCA
H257: ADTRACK | N257: PR | O257: FRANCISCO BELTRÃO
H258: ALIANSCE | N258: SP | O258: FRANCISCO MORATO
H259: ALMEIDA JUNIOR | N259: SP | O259: FRANCO DA ROCHA
H260: ALOHA | N260: MG | O260: FRUTAL
H261: AMERICAN SAT | N261: PE | O261: GARANHUNS
H262: AMPLA | N262: SP | O262: GARÇA
H263: ANCAR | N263: SC | O263: GAROPABA
H264: ARACAJU OUTDOOR | N264: SC | O264: GARUVA
H265: BAURU OUTDOOR | N265: SC | O265: GASPAR
... H413: YES OUTDOOR | N413: RS | O413: LOMBA DO PINHEIRO
N414: PR | O414: LONDRINA
N415: SP | O415: LORENA
N416: SP | O416: LOUVEIRA
N417: MT | O417: LUCAS DO RIO VERDE
N418: BA | O418: LUÍS EDUARDO MAGALHÃES
N419: MG | O419: LUZ
N420: GO | O420: LUZIÂNIA
N421: RJ | O421: MACAÉ
N422: AP | O422: MACAPÁ
N423: AL | O423: MACEIÃ
N424: AL | O424: MACEIÓ
N425: MG | O425: MACHADO
... N766: SC | O766: XANXERE

Sheet OOH
B1: Digitar | D1: Digitar | E1: Digitar | F1: Digitar | G1: Escolher | H1: Escolher | I1: Digitar | J1: Escolher | K1: Fórmula | L1: Escolher | M1: Escolher | N1: Escolher | O1: Escolher | P1: Digitar | Q1: Fórmula | R1: Escolher | S1: Digitar | T1: Fórmula | U1: Digitar | V1: Digitar | W1: Digitar | X1: Digitar | Y1: Fórmula | Z1: Fórmula | AA1: Digitar | AB1: Digitar | AC1: Digitar | AD1: Digitar | AE1: Digitar | AF1: Fórmula | AG1: Digitar | AH1: Digitar | AI1: Digitar não obrigat[orio | AJ1: Fórmula | AK1: Digitar | AL1: Digitar | AM1: Digitar | AN1: Digitar | AO1: Digitar | AP1: Digitar | AQ1: Digitar | AR1: Digitar | AS1: Digitar | AT1: Digitar | AU1: Digitar | AV1: Digitar | AW1: Digitar | AX1: Digitar | AY1: Digitar | AZ1: Digitar | BA1: Digitar | BB1: Digitar | BC1: Digitar | BD1: Digitar | BE1: Digitar | BF1: Digitar | BG1: Digitar | BH1: Digitar | BI1: Digitar | BJ1: Digitar | BK1: Digitar | BL1: Digitar | BM1: Digitar | BN1: Digitar | BO1: Digitar | BP1: Digitar | BQ1: Digitar | BR1: Digitar | BS1: Digitar | BT1: Digitar | BU1: Digitar | BV1: Digitar | BW1: Digitar | BX1: Digitar | BY1: Digitar | BZ1: Digitar | CA1: Digitar | CB1: Digitar | CC1: Digitar | CD1: Digitar | CE1: Digitar | CF1: Digitar | CG1: Digitar | CH1: Digitar | CI1: Digitar | CJ1: Digitar | CK1: Digitar | CL1: Fórmula | CM1: Fórmula | CN1: Digitar | CO1: Digitar | CP1: Digitar | CQ1: Fórmula | CR1: Fórmula | CS1: Digitar | CT1: Fórmula | CU1: Fórmula | CV1: Fórmula | CW1: Fórmula | CX1: Fórmula | CY1: Fórmula | DA1: Fórmula | DB1: Fórmula | DC1: Fórmula | DD1: Fórmula | DE1: Digitar | DH1: Digitar | DI1: Digitar | DJ1: Fórmula | DK1: Fórmula | DM1: Fórmula | DN1: Digitar | DO1: Digitar | DP1: Fórmula | DQ1: Digitar | DR1: Digitar | DS1: Digitar | DT1: Digitar | DU1: Fórmula | DW1: Fórmula | DY1: Digitar | DZ1: Digitar | EA1: Digitar | EB1: Fórmula | EC1: Fórmula | ED1: Fórmula | EE1: Fórmula | EF1: Fórmula | EG1: Fórmula | EH1: Fórmula | EI1: Fórmula | EJ1: Fórmula | EP1: JANEIRO | ET1: FEVEREIRO | EX1: MARÇO | FC1: ABRIL | FG1: MAIO | FL1: JUNHO | FP1: JULHO | FT1: AGOSTO | FY1: SETEMBRO | GC1: OUTUBRO | GG1: NOVEMBRO | GL1: DEZEMBRO
B2: STATUS DO JOB | C2: ID | D2: JOB | E2: Campanha | F2: Produto | G2: Classif para P1A Escolher manual Pacote SSA Empenas RJ | H2: TIPO DE NEGOCIAÇÃO | I2: Descrição Ex Pacote Lola, Pacote Carnaval | J2: GEO | K2: UF | L2: PRAÇA | M2: EXIBIDOR | N2: AMBIENTE | O2: FORMATO | P2: DESCRIÇÃO | Q2: GRUPO | R2: TIPO | S2: KV | T2: ESPECIFICAÇÕES | U2: Numero de SLOTS | V2: Especificações Digital inserções | W2: Especificações Digital secundagem | X2: Numero de horas disponíveis | Y2: Número máximo de inserções | Z2: Número de inserções compradas | AA2: Especificação Estático Largura | AB2: Especificação Estático Altura | AC2: Deflator de visibilidade (se estático) | AD2: TT DE PONTOS | AE2: PERIODO DA TABELA | AF2: NUMERO DE DIAS REFERENCIA | AG2: INÍCIO | AH2: TÉRMINO | AI2: PERÍODO | AJ2: No. dias Campanha Digitar manualmente caso períodos com intervalos | AK2: 46026 | AL2: =AK2+7 -> 46033 | AM2: =AL2+7 -> 46040 | AN2: =AM2+7 -> 46047 | AO2: =AN2+7 -> 46054 | AP2: =AO2+7 -> 46061 | AQ2: =AP2+7 -> 46068 | AR2: =AQ2+7 -> 46075 | AS2: =AR2+7 -> 46082 | ... CJ2: =CI2+7 -> 46383 | CK2: Divisor para cálculo de flight e face | CL2: TT Flights | CM2: TT Faces | CN2: Modelo de compra (faces ou flights) | CO2: Justficativa do valor tabela diferente / métrica OBRIGATÓRIO | CP2: Tabela ORIGINAL DO VEICULO | CQ2: TABELA Unitária | CR2: Tabela Total | CS2: % | CT2: Negociado | CU2: Total Negociado | CV2: Valor líquido | CW2: Faturavel ou NÃO faturável | CX2: Impacto IPV | CY2: CpView | DA2: PRODUÇÃO Finalização | DB2: PRODUÇÃO Impressão | DD2: Prazo de Pagamento | DE2: Tabela Vigente | DH2: QTD de formatos | DI2: QTD de layouts | DJ2: Valor unitário | DK2: Valor total | DM2: QTD faces | DN2: QTD de produções | DO2: Reserva Técnica (%) | DP2: QTD Faces para produção | DQ2: Largura (m) | DR2: Altura (m) | DS2: Valor Unitário (R$/face) | DT2: Valor Unitário (R$/m²) | DU2: Total Parcial (R$) | DV2: Custo de Instalação (R$) | DW2: Total Final (R$) | DY2: Base para cálculo | DZ2: Impacto se informação for Semanal | EA2: Impacto se informação for mensal | EB2: TT de Dias Campanha | EC2: Público/ local no período da campanha | ED2: Soma do TT locais OU flights (p/ circuitos) | EE2: Fluxo de passantes | EF2: IPV ajustado | EG2: Impacto IPV | EH2: IPV Original | EI2: % inserções compradas / disponíveis | EJ2: Deflator de visibilidade - somente estáticos | EP2: W1 | EQ2: W2 | ER2: W3 | ES2: W4 | ET2: W5 | EU2: W6 | EV2: W7 | EW2: W8 | EX2: W9 | EY2: W10 | EZ2: W11 | FA2: W12 | FB2: W13 | FC2: W14 | FD2: W15 | FE2: W16 | FF2: W17 | FG2: W18 | FH2: W19 | FI2: W20 | FJ2: W21 | FK2: W22 | FL2: W23 | FM2: W24 | FN2: W25 | FO2: W26 | FP2: W27 | FQ2: W28 | FR2: W29 | FS2: W30 | FT2: W31 | FU2: W32 | FV2: W33 | FW2: W34 | FX2: W35 | FY2: W36 | FZ2: W37 | GA2: W38 | GB2: W39 | GC2: W40 | GD2: W41 | GE2: W42 | GF2: W43 | GG2: W44 | GH2: W45 | GI2: W46 | GJ2: W47 | GK2: W48 | GL2: W49 | GM2: W50 | GN2: W51 | GO2: W52 | GQ2: JAN | GR2: FEV | GS2: MAR | GT2: ABR | GU2: MAI | GV2: JUN | GW2: JUL | GX2: AGO | GY2: SET | GZ2: OUT | HA2: NOV | HB2: DEZ
C3: 1 | D3: 0 | E3: 0 | F3: 0 | G3: =IF(M3="","",IF(ISERROR(VLOOKUP(M3,Parametros!AI:AJ,2,0)),"Demais OOH",VLOOKUP(M3,Parametros!AI:AJ,2,0))) | J3: =IFERROR(VLOOKUP(K3,'GEOS AMBEV'!B:C,2,0),"") | K3: =_xlfn.XLOOKUP(L3,POPULAÇÃO!D:D,POPULAÇÃO!C:C) -> 0 | O3: Abrigo De Ônibus Estático | Q3: =IFERROR(VLOOKUP(O3,Parametros!J:K,2,0),"") -> G3ME | T3: =IF(R3="","",IF(R3="digital",W3&"""- "&V3&" ins/dia",TEXT(AA3,"0,00")&" x "&TEXT(AB3,"0,00")&"m")) | Y3: =IFERROR(86400/W3/24*X3,0) -> 0 | Z3: =+U3*V3 -> 0 | AF3: =IFERROR(VLOOKUP(AE3,Parametros!E:F,2,0),0) -> 0 | AJ3: =IF(AG3="","",AH3-AG3+1) | AK3: 40 | AL3: 40 | CK3: 1 | CL3: =IFERROR(COUNT(AK3:CJ3)/CK3,0) -> 2 | CM3: =IFERROR(SUM(AK3:CJ3)/CK3,0) -> 80 | CN3: Faces | CQ3: =IF(AE3="diária",CP3*AJ3*U3,IF(AJ3>AF3,CP3,AJ3/AF3*CP3)*U3) -> 0 | CR3: =IF(CN3="","0",IF(CN3="Faces",CQ3*CM3,CQ3*CL3)) -> 0 | CS3: 0.72 | CT3: =CP3*(1-CS3) -> 0 | CU3: =CR3*(1-CS3) -> 0 | CV3: =CU3*0.8 -> 0 | CW3: =IF(H3="","",IFERROR(VLOOKUP(H3,Parametros!B:C,2,0),0)) | CX3: =EG3 -> 0 | CY3: =IF(OR(CX3=0,CX3="Sem base de dados"),0,CV3/CX3*1000) -> 0 | DA3: =DK3 -> 0 | DB3: =DW3 -> 0 | DD3: =IF(AG3="",0,EDATE(DATE(YEAR(AG3),MONTH(AG3),1),5)) -> 0 | DE3: 2025 | DJ3: 800 | DK3: =DJ3*DI3*DH3 -> 0 | DM3: =IF(R3="Digital",0,IF(SUM(AK3:CJ3)=0,0,LARGE(AK3:CJ3,1))) -> 40 | DP3: =ROUNDUP(DN3*DM3*(1+DO3),0) -> 0 | DU3: =PRODUCT(DP3:DT3) -> 0 | DW3: =(DU3+DV3) -> 0 | DZ3: =SUMIFS('Mediana dos Impactos'!D:D,'Mediana dos Impactos'!C:C,OOH!O3,'Mediana dos Impactos'!B:B,OOH!L3) -> 0 | EB3: =AJ3 | EC3: =IFERROR(IF(DZ3<>"",DZ3/7*EB3,$EA3/30*EB3),0) -> 0 | ED3: =IF(DY3="",0,IF(DY3="Face",CM3,CL3)) -> 0 | EE3: =IF(DY3="Sem base de dados",DY3,EC3*ED3) -> 0 | EF3: =IF(R3="digital",(EI3*EH3),EJ3*EH3) -> 0 | EG3: =+EE3*EF3 -> 0 | EH3: =IFERROR(IF(N3="via pública",VLOOKUP($O3,Parametros!$J:$L,3,0),VLOOKUP(N3,Parametros!V:W,2,0)),0) -> 0 | EI3: =IFERROR(Z3/Y3,0) -> 0 | EJ3: =IFERROR(VLOOKUP(AC3,Parametros!AL:AM,2,0),1) -> 1 | EM3: =SUM(EP3:GO3) -> 0 | EN3: =EM3=CV3 -> TRUE | EP3: {=_xlfn.IFS(AK3="","",AK3,$CV3/$CM3/$CK3*AK3)} -> 0 | EQ3: {=_xlfn.IFS(AL3="","",AL3,$CV3/$CM3/$CK3*AL3)} -> 0 | ER3: {=_xlfn.IFS(AM3="","",AM3,$CV3/$CM3/$CK3*AM3)} | ES3: {=_xlfn.IFS(AN3="","",AN3,$CV3/$CM3/$CK3*AN3)} | ET3: {=_xlfn.IFS(AO3="","",AO3,$CV3/$CM3/$CK3*AO3)} | EU3: {=_xlfn.IFS(AP3="","",AP3,$CV3/$CM3/$CK3*AP3)} | EV3: {=_xlfn.IFS(AQ3="","",AQ3,$CV3/$CM3/$CK3*AQ3)} | EW3: {=_xlfn.IFS(AR3="","",AR3,$CV3/$CM3/$CK3*AR3)} | ... GO3: {=_xlfn.IFS(CJ3="","",CJ3,$CV3/$CM3/$CK3*CJ3)} | GQ3: =SUM(EP3:ES3) -> 0 | GR3: =SUM(ET3:EW3) -> 0 | GS3: =SUM(EX3:FB3) -> 0 | GT3: =SUM(FC3:FF3) -> 0 | GU3: =SUM(FG3:FK3) -> 0 | GV3: =SUM(FL3:FO3) -> 0 | GW3: =SUM(FP3:FS3) -> 0 | GX3: =SUM(FT3:FX3) -> 0 | GY3: =SUM(FY3:GB3) -> 0 | GZ3: =SUM(GC3:GF3) -> 0 | HA3: =SUM(GG3:GK3) -> 0 | HB3: =SUM(GL3:GO3) -> 0
C4: =+C3+1 -> 2 | D4: 0 | E4: 0 | F4: 0 | G4: =IF(M4="","",IF(ISERROR(VLOOKUP(M4,Parametros!AI:AJ,2,0)),"Demais OOH",VLOOKUP(M4,Parametros!AI:AJ,2,0))) | J4: =IFERROR(VLOOKUP(K4,'GEOS AMBEV'!B:C,2,0),"") | K4: =_xlfn.XLOOKUP(L4,POPULAÇÃO!D:D,POPULAÇÃO!C:C) -> 0 | Q4: =IFERROR(VLOOKUP(O4,Parametros!J:K,2,0),"") | T4: =IF(R4="","",IF(R4="digital",W4&"""- "&V4&" ins/dia",TEXT(AA4,"0,00")&" x "&TEXT(AB4,"0,00")&"m")) | Y4: =IFERROR(86400/W4/24*X4,0) -> 0 | Z4: =+U4*V4 -> 0 | AF4: =IFERROR(VLOOKUP(AE4,Parametros!E:F,2,0),0) -> 0 | AJ4: =IF(AG4="","",AH4-AG4+1) | CL4: =IFERROR(COUNT(AK4:CJ4)/CK4,0) -> 0 | CM4: =IFERROR(SUM(AK4:CJ4)/CK4,0) -> 0 | CQ4: =IF(AE4="diária",CP4*AJ4*U4,IF(AJ4>AF4,CP4,AJ4/AF4*CP4)*U4) -> 0 | CR4: =IF(CN4="","0",IF(CN4="Faces",CQ4*CM4,CQ4*CL4)) -> 0 | CS4: 0.72 | CT4: =CP4*(1-CS4) -> 0 | CU4: =CR4*(1-CS4) -> 0 | CV4: =CU4*0.8 -> 0 | CW4: =IF(H4="","",IFERROR(VLOOKUP(H4,Parametros!B:C,2,0),0)) | CX4: =EG4 -> 0 | CY4: =IF(OR(CX4=0,CX4="Sem base de dados"),0,CV4/CX4*1000) -> 0 | DA4: =DK4 -> 0 | DB4: =DW4 -> 0 | DD4: =IF(AG4="",0,EDATE(DATE(YEAR(AG4),MONTH(AG4),1),5)) -> 0 | DE4: 2025 | DJ4: 800 | DK4: =DJ4*DI4*DH4 -> 0 | DM4: =IF(R4="Digital",0,IF(SUM(AK4:CJ4)=0,0,LARGE(AK4:CJ4,1))) -> 0 | DP4: =ROUNDUP(DN4*DM4*(1+DO4),0) -> 0 | DU4: =PRODUCT(DP4:DT4) -> 0 | DW4: =(DU4+DV4) -> 0 | DZ4: =SUMIFS('Mediana dos Impactos'!D:D,'Mediana dos Impactos'!C:C,OOH!O4,'Mediana dos Impactos'!B:B,OOH!L4) -> 0 | EB4: =AJ4 | EC4: =IFERROR(IF(DZ4<>"",DZ4/7*EB4,$EA4/30*EB4),0) -> 0 | ED4: =IF(DY4="",0,IF(DY4="Face",CM4,CL4)) -> 0 | EE4: =IF(DY4="Sem base de dados",DY4,EC4*ED4) -> 0 | EF4: =IF(R4="digital",(EI4*EH4),EJ4*EH4) -> 0 | EG4: =+EE4*EF4 -> 0 | EH4: =IFERROR(IF(N4="via pública",VLOOKUP($O4,Parametros!$J:$L,3,0),VLOOKUP(N4,Parametros!V:W,2,0)),0) -> 0 | EI4: =IFERROR(Z4/Y4,0) -> 0 | EJ4: =IFERROR(VLOOKUP(AC4,Parametros!AL:AM,2,0),1) -> 1 | EM4: =SUM(EP4:GO4) -> 0 | EN4: =EM4=CV4 -> TRUE | EP4: {=_xlfn.IFS(AK4="","",AK4,$CV4/$CM4/$CK4*AK4)} | EQ4: {=_xlfn.IFS(AL4="","",AL4,$CV4/$CM4/$CK4*AL4)} | ER4: {=_xlfn.IFS(AM4="","",AM4,$CV4/$CM4/$CK4*AM4)} | ES4: {=_xlfn.IFS(AN4="","",AN4,$CV4/$CM4/$CK4*AN4)} | ET4: {=_xlfn.IFS(AO4="","",AO4,$CV4/$CM4/$CK4*AO4)} | EU4: {=_xlfn.IFS(AP4="","",AP4,$CV4/$CM4/$CK4*AP4)} | EV4: {=_xlfn.IFS(AQ4="","",AQ4,$CV4/$CM4/$CK4*AQ4)} | EW4: {=_xlfn.IFS(AR4="","",AR4,$CV4/$CM4/$CK4*AR4)} | ... GO4: {=_xlfn.IFS(CJ4="","",CJ4,$CV4/$CM4/$CK4*CJ4)} | GQ4: =SUM(EP4:ES4) -> 0 | GR4: =SUM(ET4:EW4) -> 0 | GS4: =SUM(EX4:FB4) -> 0 | GT4: =SUM(FC4:FF4) -> 0 | GU4: =SUM(FG4:FK4) -> 0 | GV4: =SUM(FL4:FO4) -> 0 | GW4: =SUM(FP4:FS4) -> 0 | GX4: =SUM(FT4:FX4) -> 0 | GY4: =SUM(FY4:GB4) -> 0 | GZ4: =SUM(GC4:GF4) -> 0 | HA4: =SUM(GG4:GK4) -> 0 | HB4: =SUM(GL4:GO4) -> 0
C5: =+C4+1 -> 3 | D5: 0 | E5: 0 | F5: 0 | G5: =IF(M5="","",IF(ISERROR(VLOOKUP(M5,Parametros!AI:AJ,2,0)),"Demais OOH",VLOOKUP(M5,Parametros!AI:AJ,2,0))) | J5: =IFERROR(VLOOKUP(K5,'GEOS AMBEV'!B:C,2,0),"") | K5: =_xlfn.XLOOKUP(L5,POPULAÇÃO!D:D,POPULAÇÃO!C:C) -> 0 | Q5: =IFERROR(VLOOKUP(O5,Parametros!J:K,2,0),"") | T5: =IF(R5="","",IF(R5="digital",W5&"""- "&V5&" ins/dia",TEXT(AA5,"0,00")&" x "&TEXT(AB5,"0,00")&"m")) | Y5: =IFERROR(86400/W5/24*X5,0) -> 0 | Z5: =+U5*V5 -> 0 | AF5: =IFERROR(VLOOKUP(AE5,Parametros!E:F,2,0),0) -> 0 | AJ5: =IF(AG5="","",AH5-AG5+1) | CL5: =IFERROR(COUNT(AK5:CJ5)/CK5,0) -> 0 | CM5: =IFERROR(SUM(AK5:CJ5)/CK5,0) -> 0 | CQ5: =IF(AE5="diária",CP5*AJ5*U5,IF(AJ5>AF5,CP5,AJ5/AF5*CP5)*U5) -> 0 | CR5: =IF(CN5="","0",IF(CN5="Faces",CQ5*CM5,CQ5*CL5)) -> 0 | CS5: 0.72 | CT5: =CP5*(1-CS5) -> 0 | CU5: =CR5*(1-CS5) -> 0 | CV5: =CU5*0.8 -> 0 | CW5: =IF(H5="","",IFERROR(VLOOKUP(H5,Parametros!B:C,2,0),0)) | CX5: =EG5 -> 0 | CY5: =IF(OR(CX5=0,CX5="Sem base de dados"),0,CV5/CX5*1000) -> 0 | DA5: =DK5 -> 0 | DB5: =DW5 -> 0 | DD5: =IF(AG5="",0,EDATE(DATE(YEAR(AG5),MONTH(AG5),1),5)) -> 0 | DE5: 2025 | DJ5: 800 | DK5: =DJ5*DI5*DH5 -> 0 | DM5: =IF(R5="Digital",0,IF(SUM(AK5:CJ5)=0,0,LARGE(AK5:CJ5,1))) -> 0 | DP5: =ROUNDUP(DN5*DM5*(1+DO5),0) -> 0 | DU5: =PRODUCT(DP5:DT5) -> 0 | DW5: =(DU5+DV5) -> 0 | DZ5: =SUMIFS('Mediana dos Impactos'!D:D,'Mediana dos Impactos'!C:C,OOH!O5,'Mediana dos Impactos'!B:B,OOH!L5) -> 0 | EB5: =AJ5 | EC5: =IFERROR(IF(DZ5<>"",DZ5/7*EB5,$EA5/30*EB5),0) -> 0 | ED5: =IF(DY5="",0,IF(DY5="Face",CM5,CL5)) -> 0 | EE5: =IF(DY5="Sem base de dados",DY5,EC5*ED5) -> 0 | EF5: =IF(R5="digital",(EI5*EH5),EJ5*EH5) -> 0 | EG5: =+EE5*EF5 -> 0 | EH5: =IFERROR(IF(N5="via pública",VLOOKUP($O5,Parametros!$J:$L,3,0),VLOOKUP(N5,Parametros!V:W,2,0)),0) -> 0 | EI5: =IFERROR(Z5/Y5,0) -> 0 | EJ5: =IFERROR(VLOOKUP(AC5,Parametros!AL:AM,2,0),1) -> 1 | EM5: =SUM(EP5:GO5) -> 0 | EN5: =EM5=CV5 -> TRUE | EP5: {=_xlfn.IFS(AK5="","",AK5,$CV5/$CM5/$CK5*AK5)} | EQ5: {=_xlfn.IFS(AL5="","",AL5,$CV5/$CM5/$CK5*AL5)} | ER5: {=_xlfn.IFS(AM5="","",AM5,$CV5/$CM5/$CK5*AM5)} | ES5: {=_xlfn.IFS(AN5="","",AN5,$CV5/$CM5/$CK5*AN5)} | ET5: {=_xlfn.IFS(AO5="","",AO5,$CV5/$CM5/$CK5*AO5)} | EU5: {=_xlfn.IFS(AP5="","",AP5,$CV5/$CM5/$CK5*AP5)} | EV5: {=_xlfn.IFS(AQ5="","",AQ5,$CV5/$CM5/$CK5*AQ5)} | EW5: {=_xlfn.IFS(AR5="","",AR5,$CV5/$CM5/$CK5*AR5)} | ... GO5: {=_xlfn.IFS(CJ5="","",CJ5,$CV5/$CM5/$CK5*CJ5)} | GQ5: =SUM(EP5:ES5) -> 0 | GR5: =SUM(ET5:EW5) -> 0 | GS5: =SUM(EX5:FB5) -> 0 | GT5: =SUM(FC5:FF5) -> 0 | GU5: =SUM(FG5:FK5) -> 0 | GV5: =SUM(FL5:FO5) -> 0 | GW5: =SUM(FP5:FS5) -> 0 | GX5: =SUM(FT5:FX5) -> 0 | GY5: =SUM(FY5:GB5) -> 0 | GZ5: =SUM(GC5:GF5) -> 0 | HA5: =SUM(GG5:GK5) -> 0 | HB5: =SUM(GL5:GO5) -> 0
C6: =+C5+1 -> 4 | D6: 0 | E6: 0 | F6: 0 | G6: =IF(M6="","",IF(ISERROR(VLOOKUP(M6,Parametros!AI:AJ,2,0)),"Demais OOH",VLOOKUP(M6,Parametros!AI:AJ,2,0))) | J6: =IFERROR(VLOOKUP(K6,'GEOS AMBEV'!B:C,2,0),"") | K6: =_xlfn.XLOOKUP(L6,POPULAÇÃO!D:D,POPULAÇÃO!C:C) -> 0 | Q6: =IFERROR(VLOOKUP(O6,Parametros!J:K,2,0),"") | T6: =IF(R6="","",IF(R6="digital",W6&"""- "&V6&" ins/dia",TEXT(AA6,"0,00")&" x "&TEXT(AB6,"0,00")&"m")) | Y6: =IFERROR(86400/W6/24*X6,0) -> 0 | Z6: =+U6*V6 -> 0 | AF6: =IFERROR(VLOOKUP(AE6,Parametros!E:F,2,0),0) -> 0 | AJ6: =IF(AG6="","",AH6-AG6+1) | CL6: =IFERROR(COUNT(AK6:CJ6)/CK6,0) -> 0 | CM6: =IFERROR(SUM(AK6:CJ6)/CK6,0) -> 0 | CQ6: =IF(AE6="diária",CP6*AJ6*U6,IF(AJ6>AF6,CP6,AJ6/AF6*CP6)*U6) -> 0 | CR6: =IF(CN6="","0",IF(CN6="Faces",CQ6*CM6,CQ6*CL6)) -> 0 | CS6: 0.72 | CT6: =CP6*(1-CS6) -> 0 | CU6: =CR6*(1-CS6) -> 0 | CV6: =CU6*0.8 -> 0 | CW6: =IF(H6="","",IFERROR(VLOOKUP(H6,Parametros!B:C,2,0),0)) | CX6: =EG6 -> 0 | CY6: =IF(OR(CX6=0,CX6="Sem base de dados"),0,CV6/CX6*1000) -> 0 | DA6: =DK6 -> 0 | DB6: =DW6 -> 0 | DD6: =IF(AG6="",0,EDATE(DATE(YEAR(AG6),MONTH(AG6),1),5)) -> 0 | DE6: 2025 | DJ6: 800 | DK6: =DJ6*DI6*DH6 -> 0 | DM6: =IF(R6="Digital",0,IF(SUM(AK6:CJ6)=0,0,LARGE(AK6:CJ6,1))) -> 0 | DP6: =ROUNDUP(DN6*DM6*(1+DO6),0) -> 0 | DU6: =PRODUCT(DP6:DT6) -> 0 | DW6: =(DU6+DV6) -> 0 | DZ6: =SUMIFS('Mediana dos Impactos'!D:D,'Mediana dos Impactos'!C:C,OOH!O6,'Mediana dos Impactos'!B:B,OOH!L6) -> 0 | EB6: =AJ6 | EC6: =IFERROR(IF(DZ6<>"",DZ6/7*EB6,$EA6/30*EB6),0) -> 0 | ED6: =IF(DY6="",0,IF(DY6="Face",CM6,CL6)) -> 0 | EE6: =IF(DY6="Sem base de dados",DY6,EC6*ED6) -> 0 | EF6: =IF(R6="digital",(EI6*EH6),EJ6*EH6) -> 0 | EG6: =+EE6*EF6 -> 0 | EH6: =IFERROR(IF(N6="via pública",VLOOKUP($O6,Parametros!$J:$L,3,0),VLOOKUP(N6,Parametros!V:W,2,0)),0) -> 0 | EI6: =IFERROR(Z6/Y6,0) -> 0 | EJ6: =IFERROR(VLOOKUP(AC6,Parametros!AL:AM,2,0),1) -> 1 | EM6: =SUM(EP6:GO6) -> 0 | EN6: =EM6=CV6 -> TRUE | EP6: {=_xlfn.IFS(AK6="","",AK6,$CV6/$CM6/$CK6*AK6)} | EQ6: {=_xlfn.IFS(AL6="","",AL6,$CV6/$CM6/$CK6*AL6)} | ER6: {=_xlfn.IFS(AM6="","",AM6,$CV6/$CM6/$CK6*AM6)} | ES6: {=_xlfn.IFS(AN6="","",AN6,$CV6/$CM6/$CK6*AN6)} | ET6: {=_xlfn.IFS(AO6="","",AO6,$CV6/$CM6/$CK6*AO6)} | EU6: {=_xlfn.IFS(AP6="","",AP6,$CV6/$CM6/$CK6*AP6)} | EV6: {=_xlfn.IFS(AQ6="","",AQ6,$CV6/$CM6/$CK6*AQ6)} | EW6: {=_xlfn.IFS(AR6="","",AR6,$CV6/$CM6/$CK6*AR6)} | ... GO6: {=_xlfn.IFS(CJ6="","",CJ6,$CV6/$CM6/$CK6*CJ6)} | GQ6: =SUM(EP6:ES6) -> 0 | GR6: =SUM(ET6:EW6) -> 0 | GS6: =SUM(EX6:FB6) -> 0 | GT6: =SUM(FC6:FF6) -> 0 | GU6: =SUM(FG6:FK6) -> 0 | GV6: =SUM(FL6:FO6) -> 0 | GW6: =SUM(FP6:FS6) -> 0 | GX6: =SUM(FT6:FX6) -> 0 | GY6: =SUM(FY6:GB6) -> 0 | GZ6: =SUM(GC6:GF6) -> 0 | HA6: =SUM(GG6:GK6) -> 0 | HB6: =SUM(GL6:GO6) -> 0
C7: =+C6+1 -> 5 | D7: 0 | E7: 0 | F7: 0 | G7: =IF(M7="","",IF(ISERROR(VLOOKUP(M7,Parametros!AI:AJ,2,0)),"Demais OOH",VLOOKUP(M7,Parametros!AI:AJ,2,0))) | J7: =IFERROR(VLOOKUP(K7,'GEOS AMBEV'!B:C,2,0),"") | K7: =_xlfn.XLOOKUP(L7,POPULAÇÃO!D:D,POPULAÇÃO!C:C) -> 0 | Q7: =IFERROR(VLOOKUP(O7,Parametros!J:K,2,0),"") | T7: =IF(R7="","",IF(R7="digital",W7&"""- "&V7&" ins/dia",TEXT(AA7,"0,00")&" x "&TEXT(AB7,"0,00")&"m")) | Y7: =IFERROR(86400/W7/24*X7,0) -> 0 | Z7: =+U7*V7 -> 0 | AF7: =IFERROR(VLOOKUP(AE7,Parametros!E:F,2,0),0) -> 0 | AJ7: =IF(AG7="","",AH7-AG7+1) | CL7: =IFERROR(COUNT(AK7:CJ7)/CK7,0) -> 0 | CM7: =IFERROR(SUM(AK7:CJ7)/CK7,0) -> 0 | CQ7: =IF(AE7="diária",CP7*AJ7*U7,IF(AJ7>AF7,CP7,AJ7/AF7*CP7)*U7) -> 0 | CR7: =IF(CN7="","0",IF(CN7="Faces",CQ7*CM7,CQ7*CL7)) -> 0 | CS7: 0.72 | CT7: =CP7*(1-CS7) -> 0 | CU7: =CR7*(1-CS7) -> 0 | CV7: =CU7*0.8 -> 0 | CW7: =IF(H7="","",IFERROR(VLOOKUP(H7,Parametros!B:C,2,0),0)) | CX7: =EG7 -> 0 | CY7: =IF(OR(CX7=0,CX7="Sem base de dados"),0,CV7/CX7*1000) -> 0 | DA7: =DK7 -> 0 | DB7: =DW7 -> 0 | DD7: =IF(AG7="",0,EDATE(DATE(YEAR(AG7),MONTH(AG7),1),5)) -> 0 | DE7: 2025 | DJ7: 800 | DK7: =DJ7*DI7*DH7 -> 0 | DM7: =IF(R7="Digital",0,IF(SUM(AK7:CJ7)=0,0,LARGE(AK7:CJ7,1))) -> 0 | DP7: =ROUNDUP(DN7*DM7*(1+DO7),0) -> 0 | DU7: =PRODUCT(DP7:DT7) -> 0 | DW7: =(DU7+DV7) -> 0 | DZ7: =SUMIFS('Mediana dos Impactos'!D:D,'Mediana dos Impactos'!C:C,OOH!O7,'Mediana dos Impactos'!B:B,OOH!L7) -> 0 | EB7: =AJ7 | EC7: =IFERROR(IF(DZ7<>"",DZ7/7*EB7,$EA7/30*EB7),0) -> 0 | ED7: =IF(DY7="",0,IF(DY7="Face",CM7,CL7)) -> 0 | EE7: =IF(DY7="Sem base de dados",DY7,EC7*ED7) -> 0 | EF7: =IF(R7="digital",(EI7*EH7),EJ7*EH7) -> 0 | EG7: =+EE7*EF7 -> 0 | EH7: =IFERROR(IF(N7="via pública",VLOOKUP($O7,Parametros!$J:$L,3,0),VLOOKUP(N7,Parametros!V:W,2,0)),0) -> 0 | EI7: =IFERROR(Z7/Y7,0) -> 0 | EJ7: =IFERROR(VLOOKUP(AC7,Parametros!AL:AM,2,0),1) -> 1 | EM7: =SUM(EP7:GO7) -> 0 | EN7: =EM7=CV7 -> TRUE | EP7: {=_xlfn.IFS(AK7="","",AK7,$CV7/$CM7/$CK7*AK7)} | EQ7: {=_xlfn.IFS(AL7="","",AL7,$CV7/$CM7/$CK7*AL7)} | ER7: {=_xlfn.IFS(AM7="","",AM7,$CV7/$CM7/$CK7*AM7)} | ES7: {=_xlfn.IFS(AN7="","",AN7,$CV7/$CM7/$CK7*AN7)} | ET7: {=_xlfn.IFS(AO7="","",AO7,$CV7/$CM7/$CK7*AO7)} | EU7: {=_xlfn.IFS(AP7="","",AP7,$CV7/$CM7/$CK7*AP7)} | EV7: {=_xlfn.IFS(AQ7="","",AQ7,$CV7/$CM7/$CK7*AQ7)} | EW7: {=_xlfn.IFS(AR7="","",AR7,$CV7/$CM7/$CK7*AR7)} | ... GO7: {=_xlfn.IFS(CJ7="","",CJ7,$CV7/$CM7/$CK7*CJ7)} | GQ7: =SUM(EP7:ES7) -> 0 | GR7: =SUM(ET7:EW7) -> 0 | GS7: =SUM(EX7:FB7) -> 0 | GT7: =SUM(FC7:FF7) -> 0 | GU7: =SUM(FG7:FK7) -> 0 | GV7: =SUM(FL7:FO7) -> 0 | GW7: =SUM(FP7:FS7) -> 0 | GX7: =SUM(FT7:FX7) -> 0 | GY7: =SUM(FY7:GB7) -> 0 | GZ7: =SUM(GC7:GF7) -> 0 | HA7: =SUM(GG7:GK7) -> 0 | HB7: =SUM(GL7:GO7) -> 0
C8: =+C7+1 -> 6 | D8: 0 | E8: 0 | F8: 0 | G8: =IF(M8="","",IF(ISERROR(VLOOKUP(M8,Parametros!AI:AJ,2,0)),"Demais OOH",VLOOKUP(M8,Parametros!AI:AJ,2,0))) | J8: =IFERROR(VLOOKUP(K8,'GEOS AMBEV'!B:C,2,0),"") | K8: =_xlfn.XLOOKUP(L8,POPULAÇÃO!D:D,POPULAÇÃO!C:C) -> 0 | Q8: =IFERROR(VLOOKUP(O8,Parametros!J:K,2,0),"") | T8: =IF(R8="","",IF(R8="digital",W8&"""- "&V8&" ins/dia",TEXT(AA8,"0,00")&" x "&TEXT(AB8,"0,00")&"m")) | Y8: =IFERROR(86400/W8/24*X8,0) -> 0 | Z8: =+U8*V8 -> 0 | AF8: =IFERROR(VLOOKUP(AE8,Parametros!E:F,2,0),0) -> 0 | AJ8: =IF(AG8="","",AH8-AG8+1) | CL8: =IFERROR(COUNT(AK8:CJ8)/CK8,0) -> 0 | CM8: =IFERROR(SUM(AK8:CJ8)/CK8,0) -> 0 | CQ8: =IF(AE8="diária",CP8*AJ8*U8,IF(AJ8>AF8,CP8,AJ8/AF8*CP8)*U8) -> 0 | CR8: =IF(CN8="","0",IF(CN8="Faces",CQ8*CM8,CQ8*CL8)) -> 0 | CS8: 0.65 | CT8: =CP8*(1-CS8) -> 0 | CU8: =CR8*(1-CS8) -> 0 | CV8: =CU8*0.8 -> 0 | CW8: =IF(H8="","",IFERROR(VLOOKUP(H8,Parametros!B:C,2,0),0)) | CX8: =EG8 -> 0 | CY8: =IF(OR(CX8=0,CX8="Sem base de dados"),0,CV8/CX8*1000) -> 0 | DA8: =DK8 -> 0 | DB8: =DW8 -> 0 | DD8: =IF(AG8="",0,EDATE(DATE(YEAR(AG8),MONTH(AG8),1),5)) -> 0 | DE8: 2025 | DJ8: 800 | DK8: =DJ8*DI8*DH8 -> 0 | DM8: =IF(R8="Digital",0,IF(SUM(AK8:CJ8)=0,0,LARGE(AK8:CJ8,1))) -> 0 | DP8: =ROUNDUP(DN8*DM8*(1+DO8),0) -> 0 | DU8: =PRODUCT(DP8:DT8) -> 0 | DW8: =(DU8+DV8) -> 0 | DZ8: =SUMIFS('Mediana dos Impactos'!D:D,'Mediana dos Impactos'!C:C,OOH!O8,'Mediana dos Impactos'!B:B,OOH!L8) -> 0 | EB8: =AJ8 | EC8: =IFERROR(IF(DZ8<>"",DZ8/7*EB8,$EA8/30*EB8),0) -> 0 | ED8: =IF(DY8="",0,IF(DY8="Face",CM8,CL8)) -> 0 | EE8: =IF(DY8="Sem base de dados",DY8,EC8*ED8) -> 0 | EF8: =IF(R8="digital",(EI8*EH8),EJ8*EH8) -> 0 | EG8: =+EE8*EF8 -> 0 | EH8: =IFERROR(IF(N8="via pública",VLOOKUP($O8,Parametros!$J:$L,3,0),VLOOKUP(N8,Parametros!V:W,2,0)),0) -> 0 | EI8: =IFERROR(Z8/Y8,0) -> 0 | EJ8: =IFERROR(VLOOKUP(AC8,Parametros!AL:AM,2,0),1) -> 1 | EM8: =SUM(EP8:GO8) -> 0 | EN8: =EM8=CV8 -> TRUE | EP8: {=_xlfn.IFS(AK8="","",AK8,$CV8/$CM8/$CK8*AK8)} | EQ8: {=_xlfn.IFS(AL8="","",AL8,$CV8/$CM8/$CK8*AL8)} | ER8: {=_xlfn.IFS(AM8="","",AM8,$CV8/$CM8/$CK8*AM8)} | ES8: {=_xlfn.IFS(AN8="","",AN8,$CV8/$CM8/$CK8*AN8)} | ET8: {=_xlfn.IFS(AO8="","",AO8,$CV8/$CM8/$CK8*AO8)} | EU8: {=_xlfn.IFS(AP8="","",AP8,$CV8/$CM8/$CK8*AP8)} | EV8: {=_xlfn.IFS(AQ8="","",AQ8,$CV8/$CM8/$CK8*AQ8)} | EW8: {=_xlfn.IFS(AR8="","",AR8,$CV8/$CM8/$CK8*AR8)} | ... GO8: {=_xlfn.IFS(CJ8="","",CJ8,$CV8/$CM8/$CK8*CJ8)} | GQ8: =SUM(EP8:ES8) -> 0 | GR8: =SUM(ET8:EW8) -> 0 | GS8: =SUM(EX8:FB8) -> 0 | GT8: =SUM(FC8:FF8) -> 0 | GU8: =SUM(FG8:FK8) -> 0 | GV8: =SUM(FL8:FO8) -> 0 | GW8: =SUM(FP8:FS8) -> 0 | GX8: =SUM(FT8:FX8) -> 0 | GY8: =SUM(FY8:GB8) -> 0 | GZ8: =SUM(GC8:GF8) -> 0 | HA8: =SUM(GG8:GK8) -> 0 | HB8: =SUM(GL8:GO8) -> 0
C9: =+C8+1 -> 7 | D9: 0 | E9: 0 | F9: 0 | G9: =IF(M9="","",IF(ISERROR(VLOOKUP(M9,Parametros!AI:AJ,2,0)),"Demais OOH",VLOOKUP(M9,Parametros!AI:AJ,2,0))) | J9: =IFERROR(VLOOKUP(K9,'GEOS AMBEV'!B:C,2,0),"") | K9: =_xlfn.XLOOKUP(L9,POPULAÇÃO!D:D,POPULAÇÃO!C:C) -> 0 | Q9: =IFERROR(VLOOKUP(O9,Parametros!J:K,2,0),"") | T9: =IF(R9="","",IF(R9="digital",W9&"""- "&V9&" ins/dia",TEXT(AA9,"0,00")&" x "&TEXT(AB9,"0,00")&"m")) | Y9: =IFERROR(86400/W9/24*X9,0) -> 0 | Z9: =+U9*V9 -> 0 | AF9: =IFERROR(VLOOKUP(AE9,Parametros!E:F,2,0),0) -> 0 | AJ9: =IF(AG9="","",AH9-AG9+1) | CL9: =IFERROR(COUNT(AK9:CJ9)/CK9,0) -> 0 | CM9: =IFERROR(SUM(AK9:CJ9)/CK9,0) -> 0 | CQ9: =IF(AE9="diária",CP9*AJ9*U9,IF(AJ9>AF9,CP9,AJ9/AF9*CP9)*U9) -> 0 | CR9: =IF(CN9="","0",IF(CN9="Faces",CQ9*CM9,CQ9*CL9)) -> 0 | CS9: 0.65 | CT9: =CP9*(1-CS9) -> 0 | CU9: =CR9*(1-CS9) -> 0 | CV9: =CU9*0.8 -> 0 | CW9: =IF(H9="","",IFERROR(VLOOKUP(H9,Parametros!B:C,2,0),0)) | CX9: =EG9 -> 0 | CY9: =IF(OR(CX9=0,CX9="Sem base de dados"),0,CV9/CX9*1000) -> 0 | DA9: =DK9 -> 0 | DB9: =DW9 -> 0 | DD9: =IF(AG9="",0,EDATE(DATE(YEAR(AG9),MONTH(AG9),1),5)) -> 0 | DE9: 2025 | DJ9: 800 | DK9: =DJ9*DI9*DH9 -> 0 | DM9: =IF(R9="Digital",0,IF(SUM(AK9:CJ9)=0,0,LARGE(AK9:CJ9,1))) -> 0 | DP9: =ROUNDUP(DN9*DM9*(1+DO9),0) -> 0 | DU9: =PRODUCT(DP9:DT9) -> 0 | DW9: =(DU9+DV9) -> 0 | DZ9: =SUMIFS('Mediana dos Impactos'!D:D,'Mediana dos Impactos'!C:C,OOH!O9,'Mediana dos Impactos'!B:B,OOH!L9) -> 0 | EB9: =AJ9 | EC9: =IFERROR(IF(DZ9<>"",DZ9/7*EB9,$EA9/30*EB9),0) -> 0 | ED9: =IF(DY9="",0,IF(DY9="Face",CM9,CL9)) -> 0 | EE9: =IF(DY9="Sem base de dados",DY9,EC9*ED9) -> 0 | EF9: =IF(R9="digital",(EI9*EH9),EJ9*EH9) -> 0 | EG9: =+EE9*EF9 -> 0 | EH9: =IFERROR(IF(N9="via pública",VLOOKUP($O9,Parametros!$J:$L,3,0),VLOOKUP(N9,Parametros!V:W,2,0)),0) -> 0 | EI9: =IFERROR(Z9/Y9,0) -> 0 | EJ9: =IFERROR(VLOOKUP(AC9,Parametros!AL:AM,2,0),1) -> 1 | EM9: =SUM(EP9:GO9) -> 0 | EN9: =EM9=CV9 -> TRUE | EP9: {=_xlfn.IFS(AK9="","",AK9,$CV9/$CM9/$CK9*AK9)} | EQ9: {=_xlfn.IFS(AL9="","",AL9,$CV9/$CM9/$CK9*AL9)} | ER9: {=_xlfn.IFS(AM9="","",AM9,$CV9/$CM9/$CK9*AM9)} | ES9: {=_xlfn.IFS(AN9="","",AN9,$CV9/$CM9/$CK9*AN9)} | ET9: {=_xlfn.IFS(AO9="","",AO9,$CV9/$CM9/$CK9*AO9)} | EU9: {=_xlfn.IFS(AP9="","",AP9,$CV9/$CM9/$CK9*AP9)} | EV9: {=_xlfn.IFS(AQ9="","",AQ9,$CV9/$CM9/$CK9*AQ9)} | EW9: {=_xlfn.IFS(AR9="","",AR9,$CV9/$CM9/$CK9*AR9)} | ... GO9: {=_xlfn.IFS(CJ9="","",CJ9,$CV9/$CM9/$CK9*CJ9)} | GQ9: =SUM(EP9:ES9) -> 0 | GR9: =SUM(ET9:EW9) -> 0 | GS9: =SUM(EX9:FB9) -> 0 | GT9: =SUM(FC9:FF9) -> 0 | GU9: =SUM(FG9:FK9) -> 0 | GV9: =SUM(FL9:FO9) -> 0 | GW9: =SUM(FP9:FS9) -> 0 | GX9: =SUM(FT9:FX9) -> 0 | GY9: =SUM(FY9:GB9) -> 0 | GZ9: =SUM(GC9:GF9) -> 0 | HA9: =SUM(GG9:GK9) -> 0 | HB9: =SUM(GL9:GO9) -> 0
C10: =+C9+1 -> 8 | D10: 0 | E10: 0 | F10: 0 | G10: =IF(M10="","",IF(ISERROR(VLOOKUP(M10,Parametros!AI:AJ,2,0)),"Demais OOH",VLOOKUP(M10,Parametros!AI:AJ,2,0))) | J10: =IFERROR(VLOOKUP(K10,'GEOS AMBEV'!B:C,2,0),"") | K10: =_xlfn.XLOOKUP(L10,POPULAÇÃO!D:D,POPULAÇÃO!C:C) -> 0 | Q10: =IFERROR(VLOOKUP(O10,Parametros!J:K,2,0),"") | T10: =IF(R10="","",IF(R10="digital",W10&"""- "&V10&" ins/dia",TEXT(AA10,"0,00")&" x "&TEXT(AB10,"0,00")&"m")) | Y10: =IFERROR(86400/W10/24*X10,0) -> 0 | Z10: =+U10*V10 -> 0 | AF10: =IFERROR(VLOOKUP(AE10,Parametros!E:F,2,0),0) -> 0 | AJ10: =IF(AG10="","",AH10-AG10+1) | CL10: =IFERROR(COUNT(AK10:CJ10)/CK10,0) -> 0 | CM10: =IFERROR(SUM(AK10:CJ10)/CK10,0) -> 0 | CQ10: =IF(AE10="diária",CP10*AJ10*U10,IF(AJ10>AF10,CP10,AJ10/AF10*CP10)*U10) -> 0 | CR10: =IF(CN10="","0",IF(CN10="Faces",CQ10*CM10,CQ10*CL10)) -> 0 | CS10: 0.65 | CT10: =CP10*(1-CS10) -> 0 | CU10: =CR10*(1-CS10) -> 0 | CV10: =CU10*0.8 -> 0 | CW10: =IF(H10="","",IFERROR(VLOOKUP(H10,Parametros!B:C,2,0),0)) | CX10: =EG10 -> 0 | CY10: =IF(OR(CX10=0,CX10="Sem base de dados"),0,CV10/CX10*1000) -> 0 | DA10: =DK10 -> 0 | DB10: =DW10 -> 0 | DD10: =IF(AG10="",0,EDATE(DATE(YEAR(AG10),MONTH(AG10),1),5)) -> 0 | DE10: 2025 | DJ10: 800 | DK10: =DJ10*DI10*DH10 -> 0 | DM10: =IF(R10="Digital",0,IF(SUM(AK10:CJ10)=0,0,LARGE(AK10:CJ10,1))) -> 0 | DP10: =ROUNDUP(DN10*DM10*(1+DO10),0) -> 0 | DU10: =PRODUCT(DP10:DT10) -> 0 | DW10: =(DU10+DV10) -> 0 | DZ10: =SUMIFS('Mediana dos Impactos'!D:D,'Mediana dos Impactos'!C:C,OOH!O10,'Mediana dos Impactos'!B:B,OOH!L10) -> 0 | EB10: =AJ10 | EC10: =IFERROR(IF(DZ10<>"",DZ10/7*EB10,$EA10/30*EB10),0) -> 0 | ED10: =IF(DY10="",0,IF(DY10="Face",CM10,CL10)) -> 0 | EE10: =IF(DY10="Sem base de dados",DY10,EC10*ED10) -> 0 | EF10: =IF(R10="digital",(EI10*EH10),EJ10*EH10) -> 0 | EG10: =+EE10*EF10 -> 0 | EH10: =IFERROR(IF(N10="via pública",VLOOKUP($O10,Parametros!$J:$L,3,0),VLOOKUP(N10,Parametros!V:W,2,0)),0) -> 0 | EI10: =IFERROR(Z10/Y10,0) -> 0 | EJ10: =IFERROR(VLOOKUP(AC10,Parametros!AL:AM,2,0),1) -> 1 | EM10: =SUM(EP10:GO10) -> 0 | EN10: =EM10=CV10 -> TRUE | EP10: {=_xlfn.IFS(AK10="","",AK10,$CV10/$CM10/$CK10*AK10)} | EQ10: {=_xlfn.IFS(AL10="","",AL10,$CV10/$CM10/$CK10*AL10)} | ER10: {=_xlfn.IFS(AM10="","",AM10,$CV10/$CM10/$CK10*AM10)} | ES10: {=_xlfn.IFS(AN10="","",AN10,$CV10/$CM10/$CK10*AN10)} | ET10: {=_xlfn.IFS(AO10="","",AO10,$CV10/$CM10/$CK10*AO10)} | EU10: {=_xlfn.IFS(AP10="","",AP10,$CV10/$CM10/$CK10*AP10)} | EV10: {=_xlfn.IFS(AQ10="","",AQ10,$CV10/$CM10/$CK10*AQ10)} | EW10: {=_xlfn.IFS(AR10="","",AR10,$CV10/$CM10/$CK10*AR10)} | ... GO10: {=_xlfn.IFS(CJ10="","",CJ10,$CV10/$CM10/$CK10*CJ10)} | GQ10: =SUM(EP10:ES10) -> 0 | GR10: =SUM(ET10:EW10) -> 0 | GS10: =SUM(EX10:FB10) -> 0 | GT10: =SUM(FC10:FF10) -> 0 | GU10: =SUM(FG10:FK10) -> 0 | GV10: =SUM(FL10:FO10) -> 0 | GW10: =SUM(FP10:FS10) -> 0 | GX10: =SUM(FT10:FX10) -> 0 | GY10: =SUM(FY10:GB10) -> 0 | GZ10: =SUM(GC10:GF10) -> 0 | HA10: =SUM(GG10:GK10) -> 0 | HB10: =SUM(GL10:GO10) -> 0
C11: =+C10+1 -> 9 | D11: 0 | E11: 0 | F11: 0 | G11: =IF(M11="","",IF(ISERROR(VLOOKUP(M11,Parametros!AI:AJ,2,0)),"Demais OOH",VLOOKUP(M11,Parametros!AI:AJ,2,0))) | J11: =IFERROR(VLOOKUP(K11,'GEOS AMBEV'!B:C,2,0),"") | K11: =_xlfn.XLOOKUP(L11,[39]POPULAÇÃO!D:D,[39]POPULAÇÃO!C:C) -> 0 | Q11: =IFERROR(VLOOKUP(O11,[39]Parametros!J:K,2,0),"") | T11: =IF(R11="","",IF(R11="digital",W11&"""- "&V11&" ins/dia",TEXT(AA11,"0,00")&" x "&TEXT(AB11,"0,00")&"m")) | Y11: =IFERROR(86400/W11/24*X11,0) -> 0 | Z11: =+U11*V11 -> 0 | AF11: =IFERROR(VLOOKUP(AE11,Parametros!E:F,2,0),0) -> 0 | AJ11: =IF(AG11="","",AH11-AG11+1) | CL11: =IFERROR(COUNT(AK11:CJ11)/CK11,0) -> 0 | CM11: =IFERROR(SUM(AK11:CJ11)/CK11,0) -> 0 | CQ11: =IF(AE11="diária",CP11*AJ11*U11,IF(AJ11>AF11,CP11,AJ11/AF11*CP11)*U11) -> 0 | CR11: =IF(CN11="","0",IF(CN11="Faces",CQ11*CM11,CQ11*CL11)) -> 0 | CS11: 0.65 | CT11: =CP11*(1-CS11) -> 0 | CU11: =CR11*(1-CS11) -> 0 | CV11: =CU11*0.8 -> 0 | CW11: =IF(H11="","",IFERROR(VLOOKUP(H11,[39]Parametros!B:C,2,0),0)) | CX11: =EG11 -> 0 | CY11: =IF(OR(CX11=0,CX11="Sem base de dados"),0,CV11/CX11*1000) -> 0 | DA11: =DK11 -> 0 | DB11: =DW11 -> 0 | DD11: =IF(AG11="",0,EDATE(DATE(YEAR(AG11),MONTH(AG11),1),5)) -> 0 | DE11: 2025 | DJ11: 800 | DK11: =DJ11*DI11*DH11 -> 0 | DM11: =IF(R11="Digital",0,IF(SUM(AK11:CJ11)=0,0,LARGE(AK11:CJ11,1))) -> 0 | DP11: =ROUNDUP(DN11*DM11*(1+DO11),0) -> 0 | DU11: =PRODUCT(DP11:DT11) -> 0 | DW11: =(DU11+DV11) -> 0 | DZ11: =SUMIFS('Mediana dos Impactos'!D:D,'Mediana dos Impactos'!C:C,OOH!O11,'Mediana dos Impactos'!B:B,OOH!L11) -> 0 | EB11: =AJ11 | EC11: =IFERROR(IF(DZ11<>"",DZ11/7*EB11,$EA11/30*EB11),0) -> 0 | ED11: =IF(DY11="",0,IF(DY11="Face",CM11,CL11)) -> 0 | EE11: =IF(DY11="Sem base de dados",DY11,EC11*ED11) -> 0 | EF11: =IF(R11="digital",(EI11*EH11),EJ11*EH11) -> 0 | EG11: =+EE11*EF11 -> 0 | EH11: =IFERROR(IF(N11="via pública",VLOOKUP($O11,Parametros!$J:$L,3,0),VLOOKUP(N11,Parametros!V:W,2,0)),0) -> 0 | EI11: =IFERROR(Z11/Y11,0) -> 0 | EJ11: =IFERROR(VLOOKUP(AC11,Parametros!AL:AM,2,0),1) -> 1 | EM11: =SUM(EP11:GO11) -> 0 | EN11: =EM11=CV11 -> TRUE | EP11: {=_xlfn.IFS(AK11="","",AK11,$CV11/$CM11/$CK11*AK11)} | EQ11: {=_xlfn.IFS(AL11="","",AL11,$CV11/$CM11/$CK11*AL11)} | ER11: {=_xlfn.IFS(AM11="","",AM11,$CV11/$CM11/$CK11*AM11)} | ES11: {=_xlfn.IFS(AN11="","",AN11,$CV11/$CM11/$CK11*AN11)} | ET11: {=_xlfn.IFS(AO11="","",AO11,$CV11/$CM11/$CK11*AO11)} | EU11: {=_xlfn.IFS(AP11="","",AP11,$CV11/$CM11/$CK11*AP11)} | EV11: {=_xlfn.IFS(AQ11="","",AQ11,$CV11/$CM11/$CK11*AQ11)} | EW11: {=_xlfn.IFS(AR11="","",AR11,$CV11/$CM11/$CK11*AR11)} | ... GO11: {=_xlfn.IFS(CJ11="","",CJ11,$CV11/$CM11/$CK11*CJ11)} | GQ11: =SUM(EP11:ES11) -> 0 | GR11: =SUM(ET11:EW11) -> 0 | GS11: =SUM(EX11:FB11) -> 0 | GT11: =SUM(FC11:FF11) -> 0 | GU11: =SUM(FG11:FK11) -> 0 | GV11: =SUM(FL11:FO11) -> 0 | GW11: =SUM(FP11:FS11) -> 0 | GX11: =SUM(FT11:FX11) -> 0 | GY11: =SUM(FY11:GB11) -> 0 | GZ11: =SUM(GC11:GF11) -> 0 | HA11: =SUM(GG11:GK11) -> 0 | HB11: =SUM(GL11:GO11) -> 0
C12: =+C11+1 -> 10 | D12: 0 | E12: 0 | F12: 0 | G12: =IF(M12="","",IF(ISERROR(VLOOKUP(M12,Parametros!AI:AJ,2,0)),"Demais OOH",VLOOKUP(M12,Parametros!AI:AJ,2,0))) | J12: =IFERROR(VLOOKUP(K12,'GEOS AMBEV'!B:C,2,0),"") | K12: =_xlfn.XLOOKUP(L12,POPULAÇÃO!D:D,POPULAÇÃO!C:C) -> 0 | Q12: =IFERROR(VLOOKUP(O12,Parametros!J:K,2,0),"") | T12: =IF(R12="","",IF(R12="digital",W12&"""- "&V12&" ins/dia",TEXT(AA12,"0,00")&" x "&TEXT(AB12,"0,00")&"m")) | Y12: =IFERROR(86400/W12/24*X12,0) -> 0 | Z12: =+U12*V12 -> 0 | AF12: =IFERROR(VLOOKUP(AE12,Parametros!E:F,2,0),0) -> 0 | AJ12: =IF(AG12="","",AH12-AG12+1) | CL12: =IFERROR(COUNT(AK12:CJ12)/CK12,0) -> 0 | CM12: =IFERROR(SUM(AK12:CJ12)/CK12,0) -> 0 | CQ12: =IF(AE12="diária",CP12*AJ12*U12,IF(AJ12>AF12,CP12,AJ12/AF12*CP12)*U12) -> 0 | CR12: =IF(CN12="","0",IF(CN12="Faces",CQ12*CM12,CQ12*CL12)) -> 0 | CS12: 0.7 | CT12: =CP12*(1-CS12) -> 0 | CU12: =CR12*(1-CS12) -> 0 | CV12: =CU12*0.8 -> 0 | CW12: =IF(H12="","",IFERROR(VLOOKUP(H12,Parametros!B:C,2,0),0)) | CX12: =EG12 -> 0 | CY12: =IF(OR(CX12=0,CX12="Sem base de dados"),0,CV12/CX12*1000) -> 0 | DA12: =DK12 -> 0 | DB12: =DW12 -> 0 | DD12: =IF(AG12="",0,EDATE(DATE(YEAR(AG12),MONTH(AG12),1),5)) -> 0 | DE12: 2025 | DJ12: 800 | DK12: =DJ12*DI12*DH12 -> 0 | DM12: =IF(R12="Digital",0,IF(SUM(AK12:CJ12)=0,0,LARGE(AK12:CJ12,1))) -> 0 | DP12: =ROUNDUP(DN12*DM12*(1+DO12),0) -> 0 | DU12: =PRODUCT(DP12:DT12) -> 0 | DW12: =(DU12+DV12) -> 0 | DZ12: =SUMIFS('Mediana dos Impactos'!D:D,'Mediana dos Impactos'!C:C,OOH!O12,'Mediana dos Impactos'!B:B,OOH!L12) -> 0 | EB12: =AJ12 | EC12: =IFERROR(IF(DZ12<>"",DZ12/7*EB12,$EA12/30*EB12),0) -> 0 | ED12: =IF(DY12="",0,IF(DY12="Face",CM12,CL12)) -> 0 | EE12: =IF(DY12="Sem base de dados",DY12,EC12*ED12) -> 0 | EF12: =IF(R12="digital",(EI12*EH12),EJ12*EH12) -> 0 | EG12: =+EE12*EF12 -> 0 | EH12: =IFERROR(IF(N12="via pública",VLOOKUP($O12,Parametros!$J:$L,3,0),VLOOKUP(N12,Parametros!V:W,2,0)),0) -> 0 | EI12: =IFERROR(Z12/Y12,0) -> 0 | EJ12: =IFERROR(VLOOKUP(AC12,Parametros!AL:AM,2,0),1) -> 1 | EM12: =SUM(EP12:GO12) -> 0 | EN12: =EM12=CV12 -> TRUE | EP12: {=_xlfn.IFS(AK12="","",AK12,$CV12/$CM12/$CK12*AK12)} | EQ12: {=_xlfn.IFS(AL12="","",AL12,$CV12/$CM12/$CK12*AL12)} | ER12: {=_xlfn.IFS(AM12="","",AM12,$CV12/$CM12/$CK12*AM12)} | ES12: {=_xlfn.IFS(AN12="","",AN12,$CV12/$CM12/$CK12*AN12)} | ET12: {=_xlfn.IFS(AO12="","",AO12,$CV12/$CM12/$CK12*AO12)} | EU12: {=_xlfn.IFS(AP12="","",AP12,$CV12/$CM12/$CK12*AP12)} | EV12: {=_xlfn.IFS(AQ12="","",AQ12,$CV12/$CM12/$CK12*AQ12)} | EW12: {=_xlfn.IFS(AR12="","",AR12,$CV12/$CM12/$CK12*AR12)} | ... GO12: {=_xlfn.IFS(CJ12="","",CJ12,$CV12/$CM12/$CK12*CJ12)} | GQ12: =SUM(EP12:ES12) -> 0 | GR12: =SUM(ET12:EW12) -> 0 | GS12: =SUM(EX12:FB12) -> 0 | GT12: =SUM(FC12:FF12) -> 0 | GU12: =SUM(FG12:FK12) -> 0 | GV12: =SUM(FL12:FO12) -> 0 | GW12: =SUM(FP12:FS12) -> 0 | GX12: =SUM(FT12:FX12) -> 0 | GY12: =SUM(FY12:GB12) -> 0 | GZ12: =SUM(GC12:GF12) -> 0 | HA12: =SUM(GG12:GK12) -> 0 | HB12: =SUM(GL12:GO12) -> 0
C13: =+C12+1 -> 11 | D13: 0 | E13: 0 | F13: 0 | G13: =IF(M13="","",IF(ISERROR(VLOOKUP(M13,Parametros!AI:AJ,2,0)),"Demais OOH",VLOOKUP(M13,Parametros!AI:AJ,2,0))) | J13: =IFERROR(VLOOKUP(K13,'GEOS AMBEV'!B:C,2,0),"") | K13: =_xlfn.XLOOKUP(L13,POPULAÇÃO!D:D,POPULAÇÃO!C:C) -> 0 | Q13: =IFERROR(VLOOKUP(O13,Parametros!J:K,2,0),"") | T13: =IF(R13="","",IF(R13="digital",W13&"""- "&V13&" ins/dia",TEXT(AA13,"0,00")&" x "&TEXT(AB13,"0,00")&"m")) | Y13: =IFERROR(86400/W13/24*X13,0) -> 0 | Z13: =+U13*V13 -> 0 | AF13: =IFERROR(VLOOKUP(AE13,Parametros!E:F,2,0),0) -> 0 | AJ13: =IF(AG13="","",AH13-AG13+1) | CL13: =IFERROR(COUNT(AK13:CJ13)/CK13,0) -> 0 | CM13: =IFERROR(SUM(AK13:CJ13)/CK13,0) -> 0 | CQ13: =IF(AE13="diária",CP13*AJ13*U13,IF(AJ13>AF13,CP13,AJ13/AF13*CP13)*U13) -> 0 | CR13: =IF(CN13="","0",IF(CN13="Faces",CQ13*CM13,CQ13*CL13)) -> 0 | CS13: 0.7 | CT13: =CP13*(1-CS13) -> 0 | CU13: =CR13*(1-CS13) -> 0 | CV13: =CU13*0.8 -> 0 | CW13: =IF(H13="","",IFERROR(VLOOKUP(H13,Parametros!B:C,2,0),0)) | CX13: =EG13 -> 0 | CY13: =IF(OR(CX13=0,CX13="Sem base de dados"),0,CV13/CX13*1000) -> 0 | DA13: =DK13 -> 0 | DB13: =DW13 -> 0 | DD13: =IF(AG13="",0,EDATE(DATE(YEAR(AG13),MONTH(AG13),1),5)) -> 0 | DE13: 2025 | DJ13: 800 | DK13: =DJ13*DI13*DH13 -> 0 | DM13: =IF(R13="Digital",0,IF(SUM(AK13:CJ13)=0,0,LARGE(AK13:CJ13,1))) -> 0 | DP13: =ROUNDUP(DN13*DM13*(1+DO13),0) -> 0 | DU13: =PRODUCT(DP13:DT13) -> 0 | DW13: =(DU13+DV13) -> 0 | DZ13: =SUMIFS('Mediana dos Impactos'!D:D,'Mediana dos Impactos'!C:C,OOH!O13,'Mediana dos Impactos'!B:B,OOH!L13) -> 0 | EB13: =AJ13 | EC13: =IFERROR(IF(DZ13<>"",DZ13/7*EB13,$EA13/30*EB13),0) -> 0 | ED13: =IF(DY13="",0,IF(DY13="Face",CM13,CL13)) -> 0 | EE13: =IF(DY13="Sem base de dados",DY13,EC13*ED13) -> 0 | EF13: =IF(R13="digital",(EI13*EH13),EJ13*EH13) -> 0 | EG13: =+EE13*EF13 -> 0 | EH13: =IFERROR(IF(N13="via pública",VLOOKUP($O13,Parametros!$J:$L,3,0),VLOOKUP(N13,Parametros!V:W,2,0)),0) -> 0 | EI13: =IFERROR(Z13/Y13,0) -> 0 | EJ13: =IFERROR(VLOOKUP(AC13,Parametros!AL:AM,2,0),1) -> 1 | EM13: =SUM(EP13:GO13) -> 0 | EN13: =EM13=CV13 -> TRUE | EP13: {=_xlfn.IFS(AK13="","",AK13,$CV13/$CM13/$CK13*AK13)} | EQ13: {=_xlfn.IFS(AL13="","",AL13,$CV13/$CM13/$CK13*AL13)} | ER13: {=_xlfn.IFS(AM13="","",AM13,$CV13/$CM13/$CK13*AM13)} | ES13: {=_xlfn.IFS(AN13="","",AN13,$CV13/$CM13/$CK13*AN13)} | ET13: {=_xlfn.IFS(AO13="","",AO13,$CV13/$CM13/$CK13*AO13)} | EU13: {=_xlfn.IFS(AP13="","",AP13,$CV13/$CM13/$CK13*AP13)} | EV13: {=_xlfn.IFS(AQ13="","",AQ13,$CV13/$CM13/$CK13*AQ13)} | EW13: {=_xlfn.IFS(AR13="","",AR13,$CV13/$CM13/$CK13*AR13)} | ... GO13: {=_xlfn.IFS(CJ13="","",CJ13,$CV13/$CM13/$CK13*CJ13)} | GQ13: =SUM(EP13:ES13) -> 0 | GR13: =SUM(ET13:EW13) -> 0 | GS13: =SUM(EX13:FB13) -> 0 | GT13: =SUM(FC13:FF13) -> 0 | GU13: =SUM(FG13:FK13) -> 0 | GV13: =SUM(FL13:FO13) -> 0 | GW13: =SUM(FP13:FS13) -> 0 | GX13: =SUM(FT13:FX13) -> 0 | GY13: =SUM(FY13:GB13) -> 0 | GZ13: =SUM(GC13:GF13) -> 0 | HA13: =SUM(GG13:GK13) -> 0 | HB13: =SUM(GL13:GO13) -> 0
C14: =+C13+1 -> 12 | D14: 0 | E14: 0 | F14: 0 | G14: =IF(M14="","",IF(ISERROR(VLOOKUP(M14,Parametros!AI:AJ,2,0)),"Demais OOH",VLOOKUP(M14,Parametros!AI:AJ,2,0))) | J14: =IFERROR(VLOOKUP(K14,'GEOS AMBEV'!B:C,2,0),"") | K14: =_xlfn.XLOOKUP(L14,POPULAÇÃO!D:D,POPULAÇÃO!C:C) -> 0 | Q14: =IFERROR(VLOOKUP(O14,Parametros!J:K,2,0),"") | T14: =IF(R14="","",IF(R14="digital",W14&"""- "&V14&" ins/dia",TEXT(AA14,"0,00")&" x "&TEXT(AB14,"0,00")&"m")) | Y14: =IFERROR(86400/W14/24*X14,0) -> 0 | Z14: =+U14*V14 -> 0 | AF14: =IFERROR(VLOOKUP(AE14,Parametros!E:F,2,0),0) -> 0 | AJ14: =IF(AG14="","",AH14-AG14+1) | CL14: =IFERROR(COUNT(AK14:CJ14)/CK14,0) -> 0 | CM14: =IFERROR(SUM(AK14:CJ14)/CK14,0) -> 0 | CQ14: =IF(AE14="diária",CP14*AJ14*U14,IF(AJ14>AF14,CP14,AJ14/AF14*CP14)*U14) -> 0 | CR14: =IF(CN14="","0",IF(CN14="Faces",CQ14*CM14,CQ14*CL14)) -> 0 | CS14: 0.7 | CT14: =CP14*(1-CS14) -> 0 | CU14: =CR14*(1-CS14) -> 0 | CV14: =CU14*0.8 -> 0 | CW14: =IF(H14="","",IFERROR(VLOOKUP(H14,Parametros!B:C,2,0),0)) | CX14: =EG14 -> 0 | CY14: =IF(OR(CX14=0,CX14="Sem base de dados"),0,CV14/CX14*1000) -> 0 | DA14: =DK14 -> 0 | DB14: =DW14 -> 0 | DD14: =IF(AG14="",0,EDATE(DATE(YEAR(AG14),MONTH(AG14),1),5)) -> 0 | DE14: 2025 | DJ14: 800 | DK14: =DJ14*DI14*DH14 -> 0 | DM14: =IF(R14="Digital",0,IF(SUM(AK14:CJ14)=0,0,LARGE(AK14:CJ14,1))) -> 0 | DP14: =ROUNDUP(DN14*DM14*(1+DO14),0) -> 0 | DU14: =PRODUCT(DP14:DT14) -> 0 | DW14: =(DU14+DV14) -> 0 | DZ14: =SUMIFS('Mediana dos Impactos'!D:D,'Mediana dos Impactos'!C:C,OOH!O14,'Mediana dos Impactos'!B:B,OOH!L14) -> 0 | EB14: =AJ14 | EC14: =IFERROR(IF(DZ14<>"",DZ14/7*EB14,$EA14/30*EB14),0) -> 0 | ED14: =IF(DY14="",0,IF(DY14="Face",CM14,CL14)) -> 0 | EE14: =IF(DY14="Sem base de dados",DY14,EC14*ED14) -> 0 | EF14: =IF(R14="digital",(EI14*EH14),EJ14*EH14) -> 0 | EG14: =+EE14*EF14 -> 0 | EH14: =IFERROR(IF(N14="via pública",VLOOKUP($O14,Parametros!$J:$L,3,0),VLOOKUP(N14,Parametros!V:W,2,0)),0) -> 0 | EI14: =IFERROR(Z14/Y14,0) -> 0 | EJ14: =IFERROR(VLOOKUP(AC14,Parametros!AL:AM,2,0),1) -> 1 | EM14: =SUM(EP14:GO14) -> 0 | EN14: =EM14=CV14 -> TRUE | EP14: {=_xlfn.IFS(AK14="","",AK14,$CV14/$CM14/$CK14*AK14)} | EQ14: {=_xlfn.IFS(AL14="","",AL14,$CV14/$CM14/$CK14*AL14)} | ER14: {=_xlfn.IFS(AM14="","",AM14,$CV14/$CM14/$CK14*AM14)} | ES14: {=_xlfn.IFS(AN14="","",AN14,$CV14/$CM14/$CK14*AN14)} | ET14: {=_xlfn.IFS(AO14="","",AO14,$CV14/$CM14/$CK14*AO14)} | EU14: {=_xlfn.IFS(AP14="","",AP14,$CV14/$CM14/$CK14*AP14)} | EV14: {=_xlfn.IFS(AQ14="","",AQ14,$CV14/$CM14/$CK14*AQ14)} | EW14: {=_xlfn.IFS(AR14="","",AR14,$CV14/$CM14/$CK14*AR14)} | ... GO14: {=_xlfn.IFS(CJ14="","",CJ14,$CV14/$CM14/$CK14*CJ14)} | GQ14: =SUM(EP14:ES14) -> 0 | GR14: =SUM(ET14:EW14) -> 0 | GS14: =SUM(EX14:FB14) -> 0 | GT14: =SUM(FC14:FF14) -> 0 | GU14: =SUM(FG14:FK14) -> 0 | GV14: =SUM(FL14:FO14) -> 0 | GW14: =SUM(FP14:FS14) -> 0 | GX14: =SUM(FT14:FX14) -> 0 | GY14: =SUM(FY14:GB14) -> 0 | GZ14: =SUM(GC14:GF14) -> 0 | HA14: =SUM(GG14:GK14) -> 0 | HB14: =SUM(GL14:GO14) -> 0
C15: =+C14+1 -> 13 | D15: 0 | E15: 0 | F15: 0 | G15: =IF(M15="","",IF(ISERROR(VLOOKUP(M15,Parametros!AI:AJ,2,0)),"Demais OOH",VLOOKUP(M15,Parametros!AI:AJ,2,0))) | J15: =IFERROR(VLOOKUP(K15,'GEOS AMBEV'!B:C,2,0),"") | K15: =_xlfn.XLOOKUP(L15,POPULAÇÃO!D:D,POPULAÇÃO!C:C) -> 0 | Q15: =IFERROR(VLOOKUP(O15,Parametros!J:K,2,0),"") | T15: =IF(R15="","",IF(R15="digital",W15&"""- "&V15&" ins/dia",TEXT(AA15,"0,00")&" x "&TEXT(AB15,"0,00")&"m")) | Y15: =IFERROR(86400/W15/24*X15,0) -> 0 | Z15: =+U15*V15 -> 0 | AF15: =IFERROR(VLOOKUP(AE15,Parametros!E:F,2,0),0) -> 0 | AJ15: =IF(AG15="","",AH15-AG15+1) | CL15: =IFERROR(COUNT(AK15:CJ15)/CK15,0) -> 0 | CM15: =IFERROR(SUM(AK15:CJ15)/CK15,0) -> 0 | CQ15: =IF(AE15="diária",CP15*AJ15*U15,IF(AJ15>AF15,CP15,AJ15/AF15*CP15)*U15) -> 0 | CR15: =IF(CN15="","0",IF(CN15="Faces",CQ15*CM15,CQ15*CL15)) -> 0 | CS15: 0.7 | CT15: =CP15*(1-CS15) -> 0 | CU15: =CR15*(1-CS15) -> 0 | CV15: =CU15*0.8 -> 0 | CW15: =IF(H15="","",IFERROR(VLOOKUP(H15,Parametros!B:C,2,0),0)) | CX15: =EG15 -> 0 | CY15: =IF(OR(CX15=0,CX15="Sem base de dados"),0,CV15/CX15*1000) -> 0 | DA15: =DK15 -> 0 | DB15: =DW15 -> 0 | DD15: =IF(AG15="",0,EDATE(DATE(YEAR(AG15),MONTH(AG15),1),5)) -> 0 | DE15: 2025 | DJ15: 800 | DK15: =DJ15*DI15*DH15 -> 0 | DM15: =IF(R15="Digital",0,IF(SUM(AK15:CJ15)=0,0,LARGE(AK15:CJ15,1))) -> 0 | DP15: =ROUNDUP(DN15*DM15*(1+DO15),0) -> 0 | DU15: =PRODUCT(DP15:DT15) -> 0 | DW15: =(DU15+DV15) -> 0 | DZ15: =SUMIFS('Mediana dos Impactos'!D:D,'Mediana dos Impactos'!C:C,OOH!O15,'Mediana dos Impactos'!B:B,OOH!L15) -> 0 | EB15: =AJ15 | EC15: =IFERROR(IF(DZ15<>"",DZ15/7*EB15,$EA15/30*EB15),0) -> 0 | ED15: =IF(DY15="",0,IF(DY15="Face",CM15,CL15)) -> 0 | EE15: =IF(DY15="Sem base de dados",DY15,EC15*ED15) -> 0 | EF15: =IF(R15="digital",(EI15*EH15),EJ15*EH15) -> 0 | EG15: =+EE15*EF15 -> 0 | EH15: =IFERROR(IF(N15="via pública",VLOOKUP($O15,Parametros!$J:$L,3,0),VLOOKUP(N15,Parametros!V:W,2,0)),0) -> 0 | EI15: =IFERROR(Z15/Y15,0) -> 0 | EJ15: =IFERROR(VLOOKUP(AC15,Parametros!AL:AM,2,0),1) -> 1 | EM15: =SUM(EP15:GO15) -> 0 | EN15: =EM15=CV15 -> TRUE | EP15: {=_xlfn.IFS(AK15="","",AK15,$CV15/$CM15/$CK15*AK15)} | EQ15: {=_xlfn.IFS(AL15="","",AL15,$CV15/$CM15/$CK15*AL15)} | ER15: {=_xlfn.IFS(AM15="","",AM15,$CV15/$CM15/$CK15*AM15)} | ES15: {=_xlfn.IFS(AN15="","",AN15,$CV15/$CM15/$CK15*AN15)} | ET15: {=_xlfn.IFS(AO15="","",AO15,$CV15/$CM15/$CK15*AO15)} | EU15: {=_xlfn.IFS(AP15="","",AP15,$CV15/$CM15/$CK15*AP15)} | EV15: {=_xlfn.IFS(AQ15="","",AQ15,$CV15/$CM15/$CK15*AQ15)} | EW15: {=_xlfn.IFS(AR15="","",AR15,$CV15/$CM15/$CK15*AR15)} | ... GO15: {=_xlfn.IFS(CJ15="","",CJ15,$CV15/$CM15/$CK15*CJ15)} | GQ15: =SUM(EP15:ES15) -> 0 | GR15: =SUM(ET15:EW15) -> 0 | GS15: =SUM(EX15:FB15) -> 0 | GT15: =SUM(FC15:FF15) -> 0 | GU15: =SUM(FG15:FK15) -> 0 | GV15: =SUM(FL15:FO15) -> 0 | GW15: =SUM(FP15:FS15) -> 0 | GX15: =SUM(FT15:FX15) -> 0 | GY15: =SUM(FY15:GB15) -> 0 | GZ15: =SUM(GC15:GF15) -> 0 | HA15: =SUM(GG15:GK15) -> 0 | HB15: =SUM(GL15:GO15) -> 0
C16: =+C15+1 -> 14 | D16: 0 | E16: 0 | F16: 0 | G16: =IF(M16="","",IF(ISERROR(VLOOKUP(M16,Parametros!AI:AJ,2,0)),"Demais OOH",VLOOKUP(M16,Parametros!AI:AJ,2,0))) | J16: =IFERROR(VLOOKUP(K16,'GEOS AMBEV'!B:C,2,0),"") | K16: =_xlfn.XLOOKUP(L16,POPULAÇÃO!D:D,POPULAÇÃO!C:C) -> 0 | Q16: =IFERROR(VLOOKUP(O16,Parametros!J:K,2,0),"") | T16: =IF(R16="","",IF(R16="digital",W16&"""- "&V16&" ins/dia",TEXT(AA16,"0,00")&" x "&TEXT(AB16,"0,00")&"m")) | Y16: =IFERROR(86400/W16/24*X16,0) -> 0 | Z16: =+U16*V16 -> 0 | AF16: =IFERROR(VLOOKUP(AE16,Parametros!E:F,2,0),0) -> 0 | AJ16: =IF(AG16="","",AH16-AG16+1) | CL16: =IFERROR(COUNT(AK16:CJ16)/CK16,0) -> 0 | CM16: =IFERROR(SUM(AK16:CJ16)/CK16,0) -> 0 | CQ16: =IF(AE16="diária",CP16*AJ16*U16,IF(AJ16>AF16,CP16,AJ16/AF16*CP16)*U16) -> 0 | CR16: =IF(CN16="","0",IF(CN16="Faces",CQ16*CM16,CQ16*CL16)) -> 0 | CS16: 0.7931838 | CT16: =CP16*(1-CS16) -> 0 | CU16: =CR16*(1-CS16) -> 0 | CV16: =CU16*0.8 -> 0 | CW16: =IF(H16="","",IFERROR(VLOOKUP(H16,Parametros!B:C,2,0),0)) | CX16: =EG16 -> 0 | CY16: =IF(OR(CX16=0,CX16="Sem base de dados"),0,CV16/CX16*1000) -> 0 | DA16: =DK16 -> 0 | DB16: =DW16 -> 0 | DD16: =IF(AG16="",0,EDATE(DATE(YEAR(AG16),MONTH(AG16),1),5)) -> 0 | DE16: 2025 | DJ16: 800 | DK16: =DJ16*DI16*DH16 -> 0 | DM16: =IF(R16="Digital",0,IF(SUM(AK16:CJ16)=0,0,LARGE(AK16:CJ16,1))) -> 0 | DP16: =ROUNDUP(DN16*DM16*(1+DO16),0) -> 0 | DU16: =PRODUCT(DP16:DT16) -> 0 | DW16: =(DU16+DV16) -> 0 | EB16: =AJ16 | EC16: =IFERROR(IF(DZ16<>"",DZ16/7*EB16,$EA16/30*EB16),0) -> 0 | ED16: =IF(DY16="",0,IF(DY16="Face",CM16,CL16)) -> 0 | EE16: =IF(DY16="Sem base de dados",DY16,EC16*ED16) -> 0 | EF16: =IF(R16="digital",(EI16*EH16),EJ16*EH16) -> 0 | EG16: =+EE16*EF16 -> 0 | EH16: =IFERROR(IF(N16="via pública",VLOOKUP($O16,Parametros!$J:$L,3,0),VLOOKUP(N16,Parametros!V:W,2,0)),0) -> 0 | EI16: =IFERROR(Z16/Y16,0) -> 0 | EJ16: =IFERROR(VLOOKUP(AC16,Parametros!AL:AM,2,0),1) -> 1 | EM16: =SUM(EP16:GO16) -> 0 | EN16: =EM16=CV16 -> TRUE | EP16: {=_xlfn.IFS(AK16="","",AK16,$CV16/$CM16/$CK16*AK16)} | EQ16: {=_xlfn.IFS(AL16="","",AL16,$CV16/$CM16/$CK16*AL16)} | ER16: {=_xlfn.IFS(AM16="","",AM16,$CV16/$CM16/$CK16*AM16)} | ES16: {=_xlfn.IFS(AN16="","",AN16,$CV16/$CM16/$CK16*AN16)} | ET16: {=_xlfn.IFS(AO16="","",AO16,$CV16/$CM16/$CK16*AO16)} | EU16: {=_xlfn.IFS(AP16="","",AP16,$CV16/$CM16/$CK16*AP16)} | EV16: {=_xlfn.IFS(AQ16="","",AQ16,$CV16/$CM16/$CK16*AQ16)} | EW16: {=_xlfn.IFS(AR16="","",AR16,$CV16/$CM16/$CK16*AR16)} | ... GO16: {=_xlfn.IFS(CJ16="","",CJ16,$CV16/$CM16/$CK16*CJ16)} | GQ16: =SUM(EP16:ES16) -> 0 | GR16: =SUM(ET16:EW16) -> 0 | GS16: =SUM(EX16:FB16) -> 0 | GT16: =SUM(FC16:FF16) -> 0 | GU16: =SUM(FG16:FK16) -> 0 | GV16: =SUM(FL16:FO16) -> 0 | GW16: =SUM(FP16:FS16) -> 0 | GX16: =SUM(FT16:FX16) -> 0 | GY16: =SUM(FY16:GB16) -> 0 | GZ16: =SUM(GC16:GF16) -> 0 | HA16: =SUM(GG16:GK16) -> 0 | HB16: =SUM(GL16:GO16) -> 0
A17: tt | C17: =+C16+1 -> 15 | G17: =IF(M17="","",IF(ISERROR(VLOOKUP(M17,Parametros!AI:AJ,2,0)),"Demais OOH",VLOOKUP(M17,Parametros!AI:AJ,2,0))) | J17: =IFERROR(VLOOKUP(K17,'GEOS AMBEV'!B:C,2,0),"") | Q17: =IFERROR(VLOOKUP(O17,Parametros!J:K,2,0),"") | T17: =IF(R17="","",IF(R17="digital",W17&"""- "&V17&" ins/dia",TEXT(AA17,"0,00")&" x "&TEXT(AB17,"0,00")&"m")) | Y17: =IFERROR(86400/W17/24*X17,0) -> 0 | Z17: =+U17*V17 -> 0 | AJ17: =IF(AG17="","",AH17-AG17+1) | BT17: =SUM(BT3:BT16) -> 0 | BU17: =SUM(BU3:BU16) -> 0 | BV17: =SUM(BV3:BV16) -> 0 | BW17: =SUM(BW3:BW16) -> 0 | BX17: =SUM(BX3:BX16) -> 0 | BY17: =SUM(BY3:BY16) -> 0 | BZ17: =SUM(BZ3:BZ16) -> 0 | CA17: =SUM(CA3:CA16) -> 0 | ... CJ17: =SUM(CJ3:CJ16) -> 0 | CU17: =SUM(CU3:CU16) -> 0 | CV17: =SUM(CV3:CV16) -> 0 | CX17: =SUM(CX3:CX16) -> 0 | DA17: =SUM(DA3:DA16) -> 0 | DB17: =SUM(DB3:DB16) -> 0 | DK17: =DJ17*DI17*DH17 -> 0 | DM17: =IF(R17="Digital",0,IF(SUM(AK17:CJ17)=0,0,LARGE(AK17:CJ17,1))) -> 0 | DP17: =ROUNDUP(DN17*DM17*(1+DO17),0) -> 0 | DU17: =PRODUCT(DP17:DT17) -> 0 | DW17: =(DU17+DV17) -> 0 | EB17: =AJ17 | EC17: =IFERROR(IF(DZ17<>"",DZ17/7*EB17,$EA17/30*EB17),0) -> 0 | ED17: =IF(DY17="",0,IF(DY17="Face",CM17,CL17)) -> 0 | EE17: =IF(DY17="Sem base de dados",DY17,EC17*ED17) -> 0 | EI17: =IFERROR(Z17/Y17,0) -> 0 | EJ17: =IFERROR(VLOOKUP(AC17,Parametros!AL:AM,2,0),1) -> 1 | EM17: =SUM(EP17:GO17) -> 0 | EN17: =EM17=CV17 -> TRUE | EP17: {=_xlfn.IFS(AK17="","",AK17,$CV17/$CM17/$CK17*AK17)} | EQ17: {=_xlfn.IFS(AL17="","",AL17,$CV17/$CM17/$CK17*AL17)} | ER17: {=_xlfn.IFS(AM17="","",AM17,$CV17/$CM17/$CK17*AM17)} | ES17: {=_xlfn.IFS(AN17="","",AN17,$CV17/$CM17/$CK17*AN17)} | ET17: {=_xlfn.IFS(AO17="","",AO17,$CV17/$CM17/$CK17*AO17)} | EU17: {=_xlfn.IFS(AP17="","",AP17,$CV17/$CM17/$CK17*AP17)} | EV17: {=_xlfn.IFS(AQ17="","",AQ17,$CV17/$CM17/$CK17*AQ17)} | EW17: {=_xlfn.IFS(AR17="","",AR17,$CV17/$CM17/$CK17*AR17)} | ... FX17: {=_xlfn.IFS(BS17="","",BS17,$CV17/$CM17/$CK17*BS17)} | FY17: =SUM(FY3:FY16) -> 0 | FZ17: =SUM(FZ3:FZ16) -> 0 | GA17: =SUM(GA3:GA16) -> 0 | GB17: =SUM(GB3:GB16) -> 0 | GC17: =SUM(GC3:GC16) -> 0 | GD17: =SUM(GD3:GD16) -> 0 | GE17: =SUM(GE3:GE16) -> 0 | GF17: =SUM(GF3:GF16) -> 0 | ... GO17: =SUM(GO3:GO16) -> 0 | GQ17: =SUM(EP17:ES17) -> 0 | GR17: =SUM(ET17:EW17) -> 0 | GS17: =SUM(EX17:FB17) -> 0 | GT17: =SUM(FC17:FF17) -> 0 | GU17: =SUM(FG17:FK17) -> 0 | GV17: =SUM(FL17:FO17) -> 0 | GW17: =SUM(FP17:FS17) -> 0 | GX17: =SUM(FT17:FX17) -> 0 | GY17: =SUM(FY17:GB17) -> 0 | GZ17: =SUM(GC17:GF17) -> 0 | HA17: =SUM(GG17:GK17) -> 0 | HB17: =SUM(GL17:GO17) -> 0
C18: =+C17+1 -> 16 | D18: 0 | E18: 0 | F18: 0 | G18: =IF(M18="","",IF(ISERROR(VLOOKUP(M18,Parametros!AI:AJ,2,0)),"Demais OOH",VLOOKUP(M18,Parametros!AI:AJ,2,0))) | I18: - | J18: =IFERROR(VLOOKUP(K18,'GEOS AMBEV'!B:C,2,0),"") | K18: =_xlfn.XLOOKUP(L18,POPULAÇÃO!D:D,POPULAÇÃO!C:C) -> 0 | Q18: =IFERROR(VLOOKUP(O18,Parametros!J:K,2,0),"") | T18: =IF(R18="","",IF(R18="digital",W18&"""- "&V18&" ins/dia",TEXT(AA18,"0,00")&" x "&TEXT(AB18,"0,00")&"m")) | Y18: =IFERROR(86400/W18/24*X18,0) -> 0 | Z18: =+U18*V18 -> 0 | AF18: =IFERROR(VLOOKUP(AE18,Parametros!E:F,2,0),0) -> 0 | AJ18: =IF(AG18="","",AH18-AG18+1) | CL18: =IFERROR(COUNT(AK18:CJ18)/CK18,0) -> 0 | CM18: =IFERROR(SUM(AK18:CJ18)/CK18,0) -> 0 | CQ18: =IF(AE18="diária",CP18*AJ18*U18,IF(AJ18>AF18,CP18,AJ18/AF18*CP18)*U18) -> 0 | CR18: =IF(CN18="","0",IF(CN18="Faces",CQ18*CM18,CQ18*CL18)) -> 0 | CS18: 0.25 | CT18: =CP18*(1-CS18) -> 0 | CU18: =CR18*(1-CS18) -> 0 | CV18: =CU18*0.8 -> 0 | CW18: =IF(H18="","",IFERROR(VLOOKUP(H18,Parametros!B:C,2,0),0)) | CX18: =EG18 -> 0 | CY18: =IF(OR(CX18=0,CX18="Sem base de dados"),0,CV18/CX18*1000) -> 0 | DA18: =DK18 -> 0 | DB18: =DW18 -> 0 | DD18: =IF(AG18="",0,EDATE(DATE(YEAR(AG18),MONTH(AG18),1),5)) -> 0 | DE18: 2025 | DJ18: 800 | DK18: =DJ18*DI18*DH18 -> 0 | DM18: =IF(R18="Digital",0,IF(SUM(AK18:CJ18)=0,0,LARGE(AK18:CJ18,1))) -> 0 | DP18: =ROUNDUP(DN18*DM18*(1+DO18),0) -> 0 | DU18: =PRODUCT(DP18:DT18) -> 0 | DW18: =(DU18+DV18) -> 0 | DZ18: =SUMIFS('Mediana dos Impactos'!D:D,'Mediana dos Impactos'!C:C,OOH!O18,'Mediana dos Impactos'!B:B,OOH!L18) -> 0 | EB18: =AJ18 | EC18: =IFERROR(IF(DZ18<>"",DZ18/7*EB18,$EA18/30*EB18),0) -> 0 | ED18: =IF(DY18="",0,IF(DY18="Face",CM18,CL18)) -> 0 | EE18: =IF(DY18="Sem base de dados",DY18,EC18*ED18) -> 0 | EF18: =IF(R18="digital",(EI18*EH18),EJ18*EH18) -> 0 | EG18: =+EE18*EF18 -> 0 | EH18: =IFERROR(IF(N18="via pública",VLOOKUP($O18,Parametros!$J:$L,3,0),VLOOKUP(N18,Parametros!V:W,2,0)),0) -> 0 | EI18: =IFERROR(Z18/Y18,0) -> 0 | EJ18: =IFERROR(VLOOKUP(AC18,Parametros!AL:AM,2,0),1) -> 1 | EM18: =SUM(EP18:GO18) -> 0 | EN18: =EM18=CV18 -> TRUE | EP18: {=_xlfn.IFS(AK18="","",AK18,$CV18/$CM18/$CK18*AK18)} | EQ18: {=_xlfn.IFS(AL18="","",AL18,$CV18/$CM18/$CK18*AL18)} | ER18: {=_xlfn.IFS(AM18="","",AM18,$CV18/$CM18/$CK18*AM18)} | ES18: {=_xlfn.IFS(AN18="","",AN18,$CV18/$CM18/$CK18*AN18)} | ET18: {=_xlfn.IFS(AO18="","",AO18,$CV18/$CM18/$CK18*AO18)} | EU18: {=_xlfn.IFS(AP18="","",AP18,$CV18/$CM18/$CK18*AP18)} | EV18: {=_xlfn.IFS(AQ18="","",AQ18,$CV18/$CM18/$CK18*AQ18)} | EW18: {=_xlfn.IFS(AR18="","",AR18,$CV18/$CM18/$CK18*AR18)} | ... GO18: {=_xlfn.IFS(CJ18="","",CJ18,$CV18/$CM18/$CK18*CJ18)} | GQ18: =SUM(EP18:ES18) -> 0 | GR18: =SUM(ET18:EW18) -> 0 | GS18: =SUM(EX18:FB18) -> 0 | GT18: =SUM(FC18:FF18) -> 0 | GU18: =SUM(FG18:FK18) -> 0 | GV18: =SUM(FL18:FO18) -> 0 | GW18: =SUM(FP18:FS18) -> 0 | GX18: =SUM(FT18:FX18) -> 0 | GY18: =SUM(FY18:GB18) -> 0 | GZ18: =SUM(GC18:GF18) -> 0 | HA18: =SUM(GG18:GK18) -> 0 | HB18: =SUM(GL18:GO18) -> 0
C19: =+C18+1 -> 17 | D19: 0 | E19: 0 | F19: 0 | G19: =IF(M19="","",IF(ISERROR(VLOOKUP(M19,Parametros!AI:AJ,2,0)),"Demais OOH",VLOOKUP(M19,Parametros!AI:AJ,2,0))) | I19: - | J19: =IFERROR(VLOOKUP(K19,'GEOS AMBEV'!B:C,2,0),"") | K19: =_xlfn.XLOOKUP(L19,POPULAÇÃO!D:D,POPULAÇÃO!C:C) -> 0 | Q19: =IFERROR(VLOOKUP(O19,Parametros!J:K,2,0),"") | T19: =IF(R19="","",IF(R19="digital",W19&"""- "&V19&" ins/dia",TEXT(AA19,"0,00")&" x "&TEXT(AB19,"0,00")&"m")) | Y19: =IFERROR(86400/W19/24*X19,0) -> 0 | Z19: =+U19*V19 -> 0 | AF19: =IFERROR(VLOOKUP(AE19,Parametros!E:F,2,0),0) -> 0 | AJ19: =IF(AG19="","",AH19-AG19+1) | CL19: =IFERROR(COUNT(AK19:CJ19)/CK19,0) -> 0 | CM19: =IFERROR(SUM(AK19:CJ19)/CK19,0) -> 0 | CQ19: =IF(AE19="diária",CP19*AJ19*U19,IF(AJ19>AF19,CP19,AJ19/AF19*CP19)*U19) -> 0 | CR19: =IF(CN19="","0",IF(CN19="Faces",CQ19*CM19,CQ19*CL19)) -> 0 | CS19: 0.25 | CT19: =CP19*(1-CS19) -> 0 | CU19: =CR19*(1-CS19) -> 0 | CV19: =CU19*0.8 -> 0 | CW19: =IF(H19="","",IFERROR(VLOOKUP(H19,Parametros!B:C,2,0),0)) | CX19: =EG19 -> 0 | CY19: =IF(OR(CX19=0,CX19="Sem base de dados"),0,CV19/CX19*1000) -> 0 | DA19: =DK19 -> 0 | DB19: =DW19 -> 0 | DD19: =IF(AG19="",0,EDATE(DATE(YEAR(AG19),MONTH(AG19),1),5)) -> 0 | DE19: 2025 | DJ19: 800 | DK19: =DJ19*DI19*DH19 -> 0 | DM19: =IF(R19="Digital",0,IF(SUM(AK19:CJ19)=0,0,LARGE(AK19:CJ19,1))) -> 0 | DP19: =ROUNDUP(DN19*DM19*(1+DO19),0) -> 0 | DU19: =PRODUCT(DP19:DT19) -> 0 | DW19: =(DU19+DV19) -> 0 | DZ19: =SUMIFS('Mediana dos Impactos'!D:D,'Mediana dos Impactos'!C:C,OOH!O19,'Mediana dos Impactos'!B:B,OOH!L19) -> 0 | EB19: =AJ19 | EC19: =IFERROR(IF(DZ19<>"",DZ19/7*EB19,$EA19/30*EB19),0) -> 0 | ED19: =IF(DY19="",0,IF(DY19="Face",CM19,CL19)) -> 0 | EE19: =IF(DY19="Sem base de dados",DY19,EC19*ED19) -> 0 | EF19: =IF(R19="digital",(EI19*EH19),EJ19*EH19) -> 0 | EG19: =+EE19*EF19 -> 0 | EH19: =IFERROR(IF(N19="via pública",VLOOKUP($O19,Parametros!$J:$L,3,0),VLOOKUP(N19,Parametros!V:W,2,0)),0) -> 0 | EI19: =IFERROR(Z19/Y19,0) -> 0 | EJ19: =IFERROR(VLOOKUP(AC19,Parametros!AL:AM,2,0),1) -> 1 | EM19: =SUM(EP19:GO19) -> 0 | EN19: =EM19=CV19 -> TRUE | EP19: {=_xlfn.IFS(AK19="","",AK19,$CV19/$CM19/$CK19*AK19)} | EQ19: {=_xlfn.IFS(AL19="","",AL19,$CV19/$CM19/$CK19*AL19)} | ER19: {=_xlfn.IFS(AM19="","",AM19,$CV19/$CM19/$CK19*AM19)} | ES19: {=_xlfn.IFS(AN19="","",AN19,$CV19/$CM19/$CK19*AN19)} | ET19: {=_xlfn.IFS(AO19="","",AO19,$CV19/$CM19/$CK19*AO19)} | EU19: {=_xlfn.IFS(AP19="","",AP19,$CV19/$CM19/$CK19*AP19)} | EV19: {=_xlfn.IFS(AQ19="","",AQ19,$CV19/$CM19/$CK19*AQ19)} | EW19: {=_xlfn.IFS(AR19="","",AR19,$CV19/$CM19/$CK19*AR19)} | ... GO19: {=_xlfn.IFS(CJ19="","",CJ19,$CV19/$CM19/$CK19*CJ19)} | GQ19: =SUM(EP19:ES19) -> 0 | GR19: =SUM(ET19:EW19) -> 0 | GS19: =SUM(EX19:FB19) -> 0 | GT19: =SUM(FC19:FF19) -> 0 | GU19: =SUM(FG19:FK19) -> 0 | GV19: =SUM(FL19:FO19) -> 0 | GW19: =SUM(FP19:FS19) -> 0 | GX19: =SUM(FT19:FX19) -> 0 | GY19: =SUM(FY19:GB19) -> 0 | GZ19: =SUM(GC19:GF19) -> 0 | HA19: =SUM(GG19:GK19) -> 0 | HB19: =SUM(GL19:GO19) -> 0
C20: =+C19+1 -> 18 | D20: 0 | E20: 0 | F20: 0 | G20: =IF(M20="","",IF(ISERROR(VLOOKUP(M20,Parametros!AI:AJ,2,0)),"Demais OOH",VLOOKUP(M20,Parametros!AI:AJ,2,0))) | I20: - | J20: =IFERROR(VLOOKUP(K20,'GEOS AMBEV'!B:C,2,0),"") | K20: =_xlfn.XLOOKUP(L20,POPULAÇÃO!D:D,POPULAÇÃO!C:C) -> 0 | Q20: =IFERROR(VLOOKUP(O20,Parametros!J:K,2,0),"") | T20: =IF(R20="","",IF(R20="digital",W20&"""- "&V20&" ins/dia",TEXT(AA20,"0,00")&" x "&TEXT(AB20,"0,00")&"m")) | Y20: =IFERROR(86400/W20/24*X20,0) -> 0 | Z20: =+U20*V20 -> 0 | AF20: =IFERROR(VLOOKUP(AE20,Parametros!E:F,2,0),0) -> 0 | AJ20: =IF(AG20="","",AH20-AG20+1) | CL20: =IFERROR(COUNT(AK20:CJ20)/CK20,0) -> 0 | CM20: =IFERROR(SUM(AK20:CJ20)/CK20,0) -> 0 | CQ20: =IF(AE20="diária",CP20*AJ20*U20,IF(AJ20>AF20,CP20,AJ20/AF20*CP20)*U20) -> 0 | CR20: =IF(CN20="","0",IF(CN20="Faces",CQ20*CM20,CQ20*CL20)) -> 0 | CS20: 0.25 | CT20: =CP20*(1-CS20) -> 0 | CU20: =CR20*(1-CS20) -> 0 | CV20: =CU20*0.8 -> 0 | CW20: =IF(H20="","",IFERROR(VLOOKUP(H20,Parametros!B:C,2,0),0)) | CX20: =EG20 -> 0 | CY20: =IF(OR(CX20=0,CX20="Sem base de dados"),0,CV20/CX20*1000) -> 0 | DA20: =DK20 -> 0 | DB20: =DW20 -> 0 | DD20: =IF(AG20="",0,EDATE(DATE(YEAR(AG20),MONTH(AG20),1),5)) -> 0 | DE20: 2025 | DJ20: 800 | DK20: =DJ20*DI20*DH20 -> 0 | DM20: =IF(R20="Digital",0,IF(SUM(AK20:CJ20)=0,0,LARGE(AK20:CJ20,1))) -> 0 | DP20: =ROUNDUP(DN20*DM20*(1+DO20),0) -> 0 | DU20: =PRODUCT(DP20:DT20) -> 0 | DW20: =(DU20+DV20) -> 0 | DZ20: =SUMIFS('Mediana dos Impactos'!D:D,'Mediana dos Impactos'!C:C,OOH!O20,'Mediana dos Impactos'!B:B,OOH!L20) -> 0 | EB20: =AJ20 | EC20: =IFERROR(IF(DZ20<>"",DZ20/7*EB20,$EA20/30*EB20),0) -> 0 | ED20: =IF(DY20="",0,IF(DY20="Face",CM20,CL20)) -> 0 | EE20: =IF(DY20="Sem base de dados",DY20,EC20*ED20) -> 0 | EF20: =IF(R20="digital",(EI20*EH20),EJ20*EH20) -> 0 | EG20: =+EE20*EF20 -> 0 | EH20: =IFERROR(IF(N20="via pública",VLOOKUP($O20,Parametros!$J:$L,3,0),VLOOKUP(N20,Parametros!V:W,2,0)),0) -> 0 | EI20: =IFERROR(Z20/Y20,0) -> 0 | EJ20: =IFERROR(VLOOKUP(AC20,Parametros!AL:AM,2,0),1) -> 1 | EM20: =SUM(EP20:GO20) -> 0 | EN20: =EM20=CV20 -> TRUE | EP20: {=_xlfn.IFS(AK20="","",AK20,$CV20/$CM20/$CK20*AK20)} | EQ20: {=_xlfn.IFS(AL20="","",AL20,$CV20/$CM20/$CK20*AL20)} | ER20: {=_xlfn.IFS(AM20="","",AM20,$CV20/$CM20/$CK20*AM20)} | ES20: {=_xlfn.IFS(AN20="","",AN20,$CV20/$CM20/$CK20*AN20)} | ET20: {=_xlfn.IFS(AO20="","",AO20,$CV20/$CM20/$CK20*AO20)} | EU20: {=_xlfn.IFS(AP20="","",AP20,$CV20/$CM20/$CK20*AP20)} | EV20: {=_xlfn.IFS(AQ20="","",AQ20,$CV20/$CM20/$CK20*AQ20)} | EW20: {=_xlfn.IFS(AR20="","",AR20,$CV20/$CM20/$CK20*AR20)} | ... GO20: {=_xlfn.IFS(CJ20="","",CJ20,$CV20/$CM20/$CK20*CJ20)} | GQ20: =SUM(EP20:ES20) -> 0 | GR20: =SUM(ET20:EW20) -> 0 | GS20: =SUM(EX20:FB20) -> 0 | GT20: =SUM(FC20:FF20) -> 0 | GU20: =SUM(FG20:FK20) -> 0 | GV20: =SUM(FL20:FO20) -> 0 | GW20: =SUM(FP20:FS20) -> 0 | GX20: =SUM(FT20:FX20) -> 0 | GY20: =SUM(FY20:GB20) -> 0 | GZ20: =SUM(GC20:GF20) -> 0 | HA20: =SUM(GG20:GK20) -> 0 | HB20: =SUM(GL20:GO20) -> 0
A21: tt | C21: =+C20+1 -> 19 | G21: =IF(M21="","",IF(ISERROR(VLOOKUP(M21,Parametros!AI:AJ,2,0)),"Demais OOH",VLOOKUP(M21,Parametros!AI:AJ,2,0))) | J21: =IFERROR(VLOOKUP(K21,'GEOS AMBEV'!B:C,2,0),"") | Q21: =IFERROR(VLOOKUP(O21,Parametros!J:K,2,0),"") | T21: =IF(R21="","",IF(R21="digital",W21&"""- "&V21&" ins/dia",TEXT(AA21,"0,00")&" x "&TEXT(AB21,"0,00")&"m")) | Y21: =IFERROR(86400/W21/24*X21,0) -> 0 | Z21: =+U21*V21 -> 0 | AJ21: =IF(AG21="","",AH21-AG21+1) | BT21: =SUM(BT18:BT20) -> 0 | BU21: =SUM(BU18:BU20) -> 0 | BV21: =SUM(BV18:BV20) -> 0 | BW21: =SUM(BW18:BW20) -> 0 | BX21: =SUM(BX18:BX20) -> 0 | BY21: =SUM(BY18:BY20) -> 0 | BZ21: =SUM(BZ18:BZ20) -> 0 | CA21: =SUM(CA18:CA20) -> 0 | ... CJ21: =SUM(CJ18:CJ20) -> 0 | CU21: =SUM(CU18:CU20) -> 0 | CV21: =SUM(CV18:CV20) -> 0 | CW21: =IF(H21="","",IFERROR(VLOOKUP(H21,Parametros!B:C,2,0),0)) | CX21: =SUM(CX18:CX20) -> 0 | DA21: =SUM(DA18:DA20) -> 0 | DB21: =SUM(DB18:DB20) -> 0 | DK21: =DJ21*DI21*DH21 -> 0 | DM21: =IF(R21="Digital",0,IF(SUM(AK21:CJ21)=0,0,LARGE(AK21:CJ21,1))) -> 0 | DP21: =ROUNDUP(DN21*DM21*(1+DO21),0) -> 0 | DU21: =PRODUCT(DP21:DT21) -> 0 | DW21: =(DU21+DV21) -> 0 | EB21: =AJ21 | EC21: =IFERROR(IF(DZ21<>"",DZ21/7*EB21,$EA21/30*EB21),0) -> 0 | ED21: =IF(DY21="",0,IF(DY21="Face",CM21,CL21)) -> 0 | EE21: =IF(DY21="Sem base de dados",DY21,EC21*ED21) -> 0 | EI21: =IFERROR(Z21/Y21,0) -> 0 | EJ21: =IFERROR(VLOOKUP(AC21,Parametros!AL:AM,2,0),1) -> 1 | EM21: =SUM(EP21:GO21) -> 0 | EN21: =EM21=CV21 -> TRUE | EP21: {=_xlfn.IFS(AK21="","",AK21,$CV21/$CM21/$CK21*AK21)} | EQ21: {=_xlfn.IFS(AL21="","",AL21,$CV21/$CM21/$CK21*AL21)} | ER21: {=_xlfn.IFS(AM21="","",AM21,$CV21/$CM21/$CK21*AM21)} | ES21: {=_xlfn.IFS(AN21="","",AN21,$CV21/$CM21/$CK21*AN21)} | ET21: {=_xlfn.IFS(AO21="","",AO21,$CV21/$CM21/$CK21*AO21)} | EU21: {=_xlfn.IFS(AP21="","",AP21,$CV21/$CM21/$CK21*AP21)} | EV21: {=_xlfn.IFS(AQ21="","",AQ21,$CV21/$CM21/$CK21*AQ21)} | EW21: {=_xlfn.IFS(AR21="","",AR21,$CV21/$CM21/$CK21*AR21)} | ... FX21: {=_xlfn.IFS(BS21="","",BS21,$CV21/$CM21/$CK21*BS21)} | FY21: =SUM(FY18:FY20) -> 0 | FZ21: =SUM(FZ18:FZ20) -> 0 | GA21: =SUM(GA18:GA20) -> 0 | GB21: =SUM(GB18:GB20) -> 0 | GC21: =SUM(GC18:GC20) -> 0 | GD21: =SUM(GD18:GD20) -> 0 | GE21: =SUM(GE18:GE20) -> 0 | GF21: =SUM(GF18:GF20) -> 0 | ... GO21: =SUM(GO18:GO20) -> 0 | GQ21: =SUM(EP21:ES21) -> 0 | GR21: =SUM(ET21:EW21) -> 0 | GS21: =SUM(EX21:FB21) -> 0 | GT21: =SUM(FC21:FF21) -> 0 | GU21: =SUM(FG21:FK21) -> 0 | GV21: =SUM(FL21:FO21) -> 0 | GW21: =SUM(FP21:FS21) -> 0 | GX21: =SUM(FT21:FX21) -> 0 | GY21: =SUM(FY21:GB21) -> 0 | GZ21: =SUM(GC21:GF21) -> 0 | HA21: =SUM(GG21:GK21) -> 0 | HB21: =SUM(GL21:GO21) -> 0
C22: =+C21+1 -> 20 | D22: 0 | E22: 0 | F22: 0 | G22: =IF(M22="","",IF(ISERROR(VLOOKUP(M22,Parametros!AI:AJ,2,0)),"Demais OOH",VLOOKUP(M22,Parametros!AI:AJ,2,0))) | J22: =IFERROR(VLOOKUP(K22,'GEOS AMBEV'!B:C,2,0),"") | K22: =_xlfn.XLOOKUP(L22,POPULAÇÃO!D:D,POPULAÇÃO!C:C) -> 0 | Q22: =IFERROR(VLOOKUP(O22,Parametros!J:K,2,0),"") | T22: =IF(R22="","",IF(R22="digital",W22&"""- "&V22&" ins/dia",TEXT(AA22,"0,00")&" x "&TEXT(AB22,"0,00")&"m")) | Y22: =IFERROR(86400/W22/24*X22,0) -> 0 | Z22: =+U22*V22 -> 0 | AF22: =IFERROR(VLOOKUP(AE22,Parametros!E:F,2,0),0) -> 0 | AJ22: =IF(AG22="","",AH22-AG22+1) | CL22: =IFERROR(COUNT(AK22:CJ22)/CK22,0) -> 0 | CM22: =IFERROR(SUM(AK22:CJ22)/CK22,0) -> 0 | CQ22: =IF(AE22="diária",CP22*AJ22*U22,IF(AJ22>AF22,CP22,AJ22/AF22*CP22)*U22) -> 0 | CR22: =IF(CN22="","0",IF(CN22="Faces",CQ22*CM22,CQ22*CL22)) -> 0 | CS22: 0.83 | CT22: =CP22*(1-CS22) -> 0 | CU22: =CR22*(1-CS22) -> 0 | CV22: =CU22*0.8 -> 0 | CW22: =IF(H22="","",IFERROR(VLOOKUP(H22,Parametros!B:C,2,0),0)) | CX22: =EG22 -> 0 | CY22: =IF(OR(CX22=0,CX22="Sem base de dados"),0,CV22/CX22*1000) -> 0 | DA22: =DK22 -> 0 | DB22: =DW22 -> 0 | DD22: =IF(AG22="",0,EDATE(DATE(YEAR(AG22),MONTH(AG22),1),5)) -> 0 | DE22: 2025 | DJ22: 800 | DK22: =DJ22*DI22*DH22 -> 0 | DM22: =IF(R22="Digital",0,IF(SUM(AK22:CJ22)=0,0,LARGE(AK22:CJ22,1))) -> 0 | DP22: =ROUNDUP(DN22*DM22*(1+DO22),0) -> 0 | DU22: =PRODUCT(DP22:DT22) -> 0 | DW22: =(DU22+DV22) -> 0 | DZ22: =SUMIFS('Mediana dos Impactos'!D:D,'Mediana dos Impactos'!C:C,OOH!O22,'Mediana dos Impactos'!B:B,OOH!L22) -> 0 | EB22: =AJ22 | EC22: =IFERROR(IF(DZ22<>"",DZ22/7*EB22,$EA22/30*EB22),0) -> 0 | ED22: =IF(DY22="",0,IF(DY22="Face",CM22,CL22)) -> 0 | EE22: =IF(DY22="Sem base de dados",DY22,EC22*ED22) -> 0 | EF22: =IF(R22="digital",(EI22*EH22),EJ22*EH22) -> 0 | EG22: =+EE22*EF22 -> 0 | EH22: =IFERROR(IF(N22="via pública",VLOOKUP($O22,Parametros!$J:$L,3,0),VLOOKUP(N22,Parametros!V:W,2,0)),0) -> 0 | EI22: =IFERROR(Z22/Y22,0) -> 0 | EJ22: =IFERROR(VLOOKUP(AC22,Parametros!AL:AM,2,0),1) -> 1 | EM22: =SUM(EP22:GO22) -> 0 | EN22: =EM22=CV22 -> TRUE | EP22: {=_xlfn.IFS(AK22="","",AK22,$CV22/$CM22/$CK22*AK22)} | EQ22: {=_xlfn.IFS(AL22="","",AL22,$CV22/$CM22/$CK22*AL22)} | ER22: {=_xlfn.IFS(AM22="","",AM22,$CV22/$CM22/$CK22*AM22)} | ES22: {=_xlfn.IFS(AN22="","",AN22,$CV22/$CM22/$CK22*AN22)} | ET22: {=_xlfn.IFS(AO22="","",AO22,$CV22/$CM22/$CK22*AO22)} | EU22: {=_xlfn.IFS(AP22="","",AP22,$CV22/$CM22/$CK22*AP22)} | EV22: {=_xlfn.IFS(AQ22="","",AQ22,$CV22/$CM22/$CK22*AQ22)} | EW22: {=_xlfn.IFS(AR22="","",AR22,$CV22/$CM22/$CK22*AR22)} | ... GO22: {=_xlfn.IFS(CJ22="","",CJ22,$CV22/$CM22/$CK22*CJ22)} | GQ22: =SUM(EP22:ES22) -> 0 | GR22: =SUM(ET22:EW22) -> 0 | GS22: =SUM(EX22:FB22) -> 0 | GT22: =SUM(FC22:FF22) -> 0 | GU22: =SUM(FG22:FK22) -> 0 | GV22: =SUM(FL22:FO22) -> 0 | GW22: =SUM(FP22:FS22) -> 0 | GX22: =SUM(FT22:FX22) -> 0 | GY22: =SUM(FY22:GB22) -> 0 | GZ22: =SUM(GC22:GF22) -> 0 | HA22: =SUM(GG22:GK22) -> 0 | HB22: =SUM(GL22:GO22) -> 0
C23: =+C22+1 -> 21 | D23: 0 | E23: 0 | F23: 0 | G23: =IF(M23="","",IF(ISERROR(VLOOKUP(M23,Parametros!AI:AJ,2,0)),"Demais OOH",VLOOKUP(M23,Parametros!AI:AJ,2,0))) | J23: =IFERROR(VLOOKUP(K23,'GEOS AMBEV'!B:C,2,0),"") | K23: =_xlfn.XLOOKUP(L23,POPULAÇÃO!D:D,POPULAÇÃO!C:C) -> 0 | Q23: =IFERROR(VLOOKUP(O23,Parametros!J:K,2,0),"") | T23: =IF(R23="","",IF(R23="digital",W23&"""- "&V23&" ins/dia",TEXT(AA23,"0,00")&" x "&TEXT(AB23,"0,00")&"m")) | Y23: =IFERROR(86400/W23/24*X23,0) -> 0 | Z23: =+U23*V23 -> 0 | AF23: =IFERROR(VLOOKUP(AE23,Parametros!E:F,2,0),0) -> 0 | AJ23: =IF(AG23="","",AH23-AG23+1) | CL23: =IFERROR(COUNT(AK23:CJ23)/CK23,0) -> 0 | CM23: =IFERROR(SUM(AK23:CJ23)/CK23,0) -> 0 | CQ23: =IF(AE23="diária",CP23*AJ23*U23,IF(AJ23>AF23,CP23,AJ23/AF23*CP23)*U23) -> 0 | CR23: =IF(CN23="","0",IF(CN23="Faces",CQ23*CM23,CQ23*CL23)) -> 0 | CS23: 0.83 | CT23: =CP23*(1-CS23) -> 0 | CU23: =CR23*(1-CS23) -> 0 | CV23: =CU23*0.8 -> 0 | CW23: =IF(H23="","",IFERROR(VLOOKUP(H23,Parametros!B:C,2,0),0)) | CX23: =EG23 -> 0 | CY23: =IF(OR(CX23=0,CX23="Sem base de dados"),0,CV23/CX23*1000) -> 0 | DA23: =DK23 -> 0 | DB23: =DW23 -> 0 | DD23: =IF(AG23="",0,EDATE(DATE(YEAR(AG23),MONTH(AG23),1),5)) -> 0 | DE23: 2025 | DJ23: 800 | DK23: =DJ23*DI23*DH23 -> 0 | DM23: =IF(R23="Digital",0,IF(SUM(AK23:CJ23)=0,0,LARGE(AK23:CJ23,1))) -> 0 | DP23: =ROUNDUP(DN23*DM23*(1+DO23),0) -> 0 | DU23: =PRODUCT(DP23:DT23) -> 0 | DW23: =(DU23+DV23) -> 0 | DZ23: =SUMIFS('Mediana dos Impactos'!D:D,'Mediana dos Impactos'!C:C,OOH!O23,'Mediana dos Impactos'!B:B,OOH!L23) -> 0 | EB23: =AJ23 | EC23: =IFERROR(IF(DZ23<>"",DZ23/7*EB23,$EA23/30*EB23),0) -> 0 | ED23: =IF(DY23="",0,IF(DY23="Face",CM23,CL23)) -> 0 | EE23: =IF(DY23="Sem base de dados",DY23,EC23*ED23) -> 0 | EF23: =IF(R23="digital",(EI23*EH23),EJ23*EH23) -> 0 | EG23: =+EE23*EF23 -> 0 | EH23: =IFERROR(IF(N23="via pública",VLOOKUP($O23,Parametros!$J:$L,3,0),VLOOKUP(N23,Parametros!V:W,2,0)),0) -> 0 | EI23: =IFERROR(Z23/Y23,0) -> 0 | EJ23: =IFERROR(VLOOKUP(AC23,Parametros!AL:AM,2,0),1) -> 1 | EM23: =SUM(EP23:GO23) -> 0 | EN23: =EM23=CV23 -> TRUE | EP23: {=_xlfn.IFS(AK23="","",AK23,$CV23/$CM23/$CK23*AK23)} | EQ23: {=_xlfn.IFS(AL23="","",AL23,$CV23/$CM23/$CK23*AL23)} | ER23: {=_xlfn.IFS(AM23="","",AM23,$CV23/$CM23/$CK23*AM23)} | ES23: {=_xlfn.IFS(AN23="","",AN23,$CV23/$CM23/$CK23*AN23)} | ET23: {=_xlfn.IFS(AO23="","",AO23,$CV23/$CM23/$CK23*AO23)} | EU23: {=_xlfn.IFS(AP23="","",AP23,$CV23/$CM23/$CK23*AP23)} | EV23: {=_xlfn.IFS(AQ23="","",AQ23,$CV23/$CM23/$CK23*AQ23)} | EW23: {=_xlfn.IFS(AR23="","",AR23,$CV23/$CM23/$CK23*AR23)} | ... GO23: {=_xlfn.IFS(CJ23="","",CJ23,$CV23/$CM23/$CK23*CJ23)} | GQ23: =SUM(EP23:ES23) -> 0 | GR23: =SUM(ET23:EW23) -> 0 | GS23: =SUM(EX23:FB23) -> 0 | GT23: =SUM(FC23:FF23) -> 0 | GU23: =SUM(FG23:FK23) -> 0 | GV23: =SUM(FL23:FO23) -> 0 | GW23: =SUM(FP23:FS23) -> 0 | GX23: =SUM(FT23:FX23) -> 0 | GY23: =SUM(FY23:GB23) -> 0 | GZ23: =SUM(GC23:GF23) -> 0 | HA23: =SUM(GG23:GK23) -> 0 | HB23: =SUM(GL23:GO23) -> 0
C24: =+C23+1 -> 22 | D24: 0 | E24: 0 | F24: 0 | G24: =IF(M24="","",IF(ISERROR(VLOOKUP(M24,Parametros!AI:AJ,2,0)),"Demais OOH",VLOOKUP(M24,Parametros!AI:AJ,2,0))) | J24: =IFERROR(VLOOKUP(K24,'GEOS AMBEV'!B:C,2,0),"") | K24: =_xlfn.XLOOKUP(L24,POPULAÇÃO!D:D,POPULAÇÃO!C:C) -> 0 | Q24: =IFERROR(VLOOKUP(O24,Parametros!J:K,2,0),"") | T24: =IF(R24="","",IF(R24="digital",W24&"""- "&V24&" ins/dia",TEXT(AA24,"0,00")&" x "&TEXT(AB24,"0,00")&"m")) | Y24: =IFERROR(86400/W24/24*X24,0) -> 0 | Z24: =+U24*V24 -> 0 | AF24: =IFERROR(VLOOKUP(AE24,Parametros!E:F,2,0),0) -> 0 | AJ24: =IF(AG24="","",AH24-AG24+1) | CL24: =IFERROR(COUNT(AK24:CJ24)/CK24,0) -> 0 | CM24: =IFERROR(SUM(AK24:CJ24)/CK24,0) -> 0 | CQ24: =IF(AE24="diária",CP24*AJ24*U24,IF(AJ24>AF24,CP24,AJ24/AF24*CP24)*U24) -> 0 | CR24: =IF(CN24="","0",IF(CN24="Faces",CQ24*CM24,CQ24*CL24)) -> 0 | CS24: 0.83 | CT24: =CP24*(1-CS24) -> 0 | CU24: =CR24*(1-CS24) -> 0 | CV24: =CU24*0.8 -> 0 | CW24: =IF(H24="","",IFERROR(VLOOKUP(H24,Parametros!B:C,2,0),0)) | CX24: =EG24 -> 0 | CY24: =IF(OR(CX24=0,CX24="Sem base de dados"),0,CV24/CX24*1000) -> 0 | DA24: =DK24 -> 0 | DB24: =DW24 -> 0 | DD24: =IF(AG24="",0,EDATE(DATE(YEAR(AG24),MONTH(AG24),1),5)) -> 0 | DE24: 2025 | DJ24: 800 | DK24: =DJ24*DI24*DH24 -> 0 | DM24: =IF(R24="Digital",0,IF(SUM(AK24:CJ24)=0,0,LARGE(AK24:CJ24,1))) -> 0 | DP24: =ROUNDUP(DN24*DM24*(1+DO24),0) -> 0 | DU24: =PRODUCT(DP24:DT24) -> 0 | DW24: =(DU24+DV24) -> 0 | DZ24: =SUMIFS('Mediana dos Impactos'!D:D,'Mediana dos Impactos'!C:C,OOH!O24,'Mediana dos Impactos'!B:B,OOH!L24) -> 0 | EB24: =AJ24 | EC24: =IFERROR(IF(DZ24<>"",DZ24/7*EB24,$EA24/30*EB24),0) -> 0 | ED24: =IF(DY24="",0,IF(DY24="Face",CM24,CL24)) -> 0 | EE24: =IF(DY24="Sem base de dados",DY24,EC24*ED24) -> 0 | EF24: =IF(R24="digital",(EI24*EH24),EJ24*EH24) -> 0 | EG24: =+EE24*EF24 -> 0 | EH24: =IFERROR(IF(N24="via pública",VLOOKUP($O24,Parametros!$J:$L,3,0),VLOOKUP(N24,Parametros!V:W,2,0)),0) -> 0 | EI24: =IFERROR(Z24/Y24,0) -> 0 | EJ24: =IFERROR(VLOOKUP(AC24,Parametros!AL:AM,2,0),1) -> 1 | EM24: =SUM(EP24:GO24) -> 0 | EN24: =EM24=CV24 -> TRUE | EP24: {=_xlfn.IFS(AK24="","",AK24,$CV24/$CM24/$CK24*AK24)} | EQ24: {=_xlfn.IFS(AL24="","",AL24,$CV24/$CM24/$CK24*AL24)} | ER24: {=_xlfn.IFS(AM24="","",AM24,$CV24/$CM24/$CK24*AM24)} | ES24: {=_xlfn.IFS(AN24="","",AN24,$CV24/$CM24/$CK24*AN24)} | ET24: {=_xlfn.IFS(AO24="","",AO24,$CV24/$CM24/$CK24*AO24)} | EU24: {=_xlfn.IFS(AP24="","",AP24,$CV24/$CM24/$CK24*AP24)} | EV24: {=_xlfn.IFS(AQ24="","",AQ24,$CV24/$CM24/$CK24*AQ24)} | EW24: {=_xlfn.IFS(AR24="","",AR24,$CV24/$CM24/$CK24*AR24)} | ... GO24: {=_xlfn.IFS(CJ24="","",CJ24,$CV24/$CM24/$CK24*CJ24)} | GQ24: =SUM(EP24:ES24) -> 0 | GR24: =SUM(ET24:EW24) -> 0 | GS24: =SUM(EX24:FB24) -> 0 | GT24: =SUM(FC24:FF24) -> 0 | GU24: =SUM(FG24:FK24) -> 0 | GV24: =SUM(FL24:FO24) -> 0 | GW24: =SUM(FP24:FS24) -> 0 | GX24: =SUM(FT24:FX24) -> 0 | GY24: =SUM(FY24:GB24) -> 0 | GZ24: =SUM(GC24:GF24) -> 0 | HA24: =SUM(GG24:GK24) -> 0 | HB24: =SUM(GL24:GO24) -> 0
C25: =+C24+1 -> 23 | D25: 0 | E25: 0 | F25: 0 | G25: =IF(M25="","",IF(ISERROR(VLOOKUP(M25,Parametros!AI:AJ,2,0)),"Demais OOH",VLOOKUP(M25,Parametros!AI:AJ,2,0))) | J25: =IFERROR(VLOOKUP(K25,'GEOS AMBEV'!B:C,2,0),"") | K25: =_xlfn.XLOOKUP(L25,POPULAÇÃO!D:D,POPULAÇÃO!C:C) -> 0 | Q25: =IFERROR(VLOOKUP(O25,Parametros!J:K,2,0),"") | T25: =IF(R25="","",IF(R25="digital",W25&"""- "&V25&" ins/dia",TEXT(AA25,"0,00")&" x "&TEXT(AB25,"0,00")&"m")) | Y25: =IFERROR(86400/W25/24*X25,0) -> 0 | Z25: =+U25*V25 -> 0 | AF25: =IFERROR(VLOOKUP(AE25,Parametros!E:F,2,0),0) -> 0 | AJ25: =IF(AG25="","",AH25-AG25+1) | CL25: =IFERROR(COUNT(AK25:CJ25)/CK25,0) -> 0 | CM25: =IFERROR(SUM(AK25:CJ25)/CK25,0) -> 0 | CQ25: =IF(AE25="diária",CP25*AJ25*U25,IF(AJ25>AF25,CP25,AJ25/AF25*CP25)*U25) -> 0 | CR25: =IF(CN25="","0",IF(CN25="Faces",CQ25*CM25,CQ25*CL25)) -> 0 | CS25: 0.83 | CT25: =CP25*(1-CS25) -> 0 | CU25: =CR25*(1-CS25) -> 0 | CV25: =CU25*0.8 -> 0 | CW25: =IF(H25="","",IFERROR(VLOOKUP(H25,Parametros!B:C,2,0),0)) | CX25: =EG25 -> 0 | CY25: =IF(OR(CX25=0,CX25="Sem base de dados"),0,CV25/CX25*1000) -> 0 | DA25: =DK25 -> 0 | DB25: =DW25 -> 0 | DD25: =IF(AG25="",0,EDATE(DATE(YEAR(AG25),MONTH(AG25),1),5)) -> 0 | DE25: 2025 | DJ25: 800 | DK25: =DJ25*DI25*DH25 -> 0 | DM25: =IF(R25="Digital",0,IF(SUM(AK25:CJ25)=0,0,LARGE(AK25:CJ25,1))) -> 0 | DP25: =ROUNDUP(DN25*DM25*(1+DO25),0) -> 0 | DU25: =PRODUCT(DP25:DT25) -> 0 | DW25: =(DU25+DV25) -> 0 | DZ25: =SUMIFS('Mediana dos Impactos'!D:D,'Mediana dos Impactos'!C:C,OOH!O25,'Mediana dos Impactos'!B:B,OOH!L25) -> 0 | EB25: =AJ25 | EC25: =IFERROR(IF(DZ25<>"",DZ25/7*EB25,$EA25/30*EB25),0) -> 0 | ED25: =IF(DY25="",0,IF(DY25="Face",CM25,CL25)) -> 0 | EE25: =IF(DY25="Sem base de dados",DY25,EC25*ED25) -> 0 | EF25: =IF(R25="digital",(EI25*EH25),EJ25*EH25) -> 0 | EG25: =+EE25*EF25 -> 0 | EH25: =IFERROR(IF(N25="via pública",VLOOKUP($O25,Parametros!$J:$L,3,0),VLOOKUP(N25,Parametros!V:W,2,0)),0) -> 0 | EI25: =IFERROR(Z25/Y25,0) -> 0 | EJ25: =IFERROR(VLOOKUP(AC25,Parametros!AL:AM,2,0),1) -> 1 | EM25: =SUM(EP25:GO25) -> 0 | EN25: =EM25=CV25 -> TRUE | EP25: {=_xlfn.IFS(AK25="","",AK25,$CV25/$CM25/$CK25*AK25)} | EQ25: {=_xlfn.IFS(AL25="","",AL25,$CV25/$CM25/$CK25*AL25)} | ER25: {=_xlfn.IFS(AM25="","",AM25,$CV25/$CM25/$CK25*AM25)} | ES25: {=_xlfn.IFS(AN25="","",AN25,$CV25/$CM25/$CK25*AN25)} | ET25: {=_xlfn.IFS(AO25="","",AO25,$CV25/$CM25/$CK25*AO25)} | EU25: {=_xlfn.IFS(AP25="","",AP25,$CV25/$CM25/$CK25*AP25)} | EV25: {=_xlfn.IFS(AQ25="","",AQ25,$CV25/$CM25/$CK25*AQ25)} | EW25: {=_xlfn.IFS(AR25="","",AR25,$CV25/$CM25/$CK25*AR25)} | ... GO25: {=_xlfn.IFS(CJ25="","",CJ25,$CV25/$CM25/$CK25*CJ25)} | GQ25: =SUM(EP25:ES25) -> 0 | GR25: =SUM(ET25:EW25) -> 0 | GS25: =SUM(EX25:FB25) -> 0 | GT25: =SUM(FC25:FF25) -> 0 | GU25: =SUM(FG25:FK25) -> 0 | GV25: =SUM(FL25:FO25) -> 0 | GW25: =SUM(FP25:FS25) -> 0 | GX25: =SUM(FT25:FX25) -> 0 | GY25: =SUM(FY25:GB25) -> 0 | GZ25: =SUM(GC25:GF25) -> 0 | HA25: =SUM(GG25:GK25) -> 0 | HB25: =SUM(GL25:GO25) -> 0
C26: =+C25+1 -> 24 | D26: 0 | E26: 0 | F26: 0 | G26: =IF(M26="","",IF(ISERROR(VLOOKUP(M26,Parametros!AI:AJ,2,0)),"Demais OOH",VLOOKUP(M26,Parametros!AI:AJ,2,0))) | J26: =IFERROR(VLOOKUP(K26,'[40]GEOS AMBEV'!B:C,2,0),"") | K26: =_xlfn.XLOOKUP(L26,POPULAÇÃO!D:D,POPULAÇÃO!C:C) -> 0 | Q26: =IFERROR(VLOOKUP(O26,Parametros!J:K,2,0),"") | T26: =IF(R26="","",IF(R26="digital",W26&"""- "&V26&" ins/dia",TEXT(AA26,"0,00")&" x "&TEXT(AB26,"0,00")&"m")) | Y26: =IFERROR(86400/W26/24*X26,0) -> 0 | Z26: =+U26*V26 -> 0 | AF26: =IFERROR(VLOOKUP(AE26,Parametros!E:F,2,0),0) -> 0 | AJ26: =IF(AG26="","",AH26-AG26+1) | CL26: =IFERROR(COUNT(AK26:CJ26)/CK26,0) -> 0 | CM26: =IFERROR(SUM(AK26:CJ26)/CK26,0) -> 0 | CQ26: =IF(AE26="diária",CP26*AJ26*U26,IF(AJ26>AF26,CP26,AJ26/AF26*CP26)*U26) -> 0 | CR26: =IF(CN26="","0",IF(CN26="Faces",CQ26*CM26,CQ26*CL26)) -> 0 | CS26: 0.83 | CT26: =CP26*(1-CS26) -> 0 | CU26: =CR26*(1-CS26) -> 0 | CV26: =CU26*0.8 -> 0 | CW26: =IF(H26="","",IFERROR(VLOOKUP(H26,[40]Parametros!B:C,2,0),0)) | CX26: =EG26 -> 0 | CY26: =IF(OR(CX26=0,CX26="Sem base de dados"),0,CV26/CX26*1000) -> 0 | DA26: =DK26 -> 0 | DB26: =DW26 -> 0 | DD26: =IF(AG26="",0,EDATE(DATE(YEAR(AG26),MONTH(AG26),1),5)) -> 0 | DE26: 2025 | DJ26: 800 | DK26: =DJ26*DI26*DH26 -> 0 | DM26: =IF(R26="Digital",0,IF(SUM(AK26:CJ26)=0,0,LARGE(AK26:CJ26,1))) -> 0 | DP26: =ROUNDUP(DN26*DM26*(1+DO26),0) -> 0 | DU26: =PRODUCT(DP26:DT26) -> 0 | DW26: =(DU26+DV26) -> 0 | DZ26: =SUMIFS('Mediana dos Impactos'!D:D,'Mediana dos Impactos'!C:C,OOH!O26,'Mediana dos Impactos'!B:B,OOH!L26) -> 0 | EB26: =AJ26 | EC26: =IFERROR(IF(DZ26<>"",DZ26/7*EB26,$EA26/30*EB26),0) -> 0 | ED26: =IF(DY26="",0,IF(DY26="Face",CM26,CL26)) -> 0 | EE26: =IF(DY26="Sem base de dados",DY26,EC26*ED26) -> 0 | EF26: =IF(R26="digital",(EI26*EH26),EJ26*EH26) -> 0 | EG26: =+EE26*EF26 -> 0 | EH26: =IFERROR(IF(N26="via pública",VLOOKUP($O26,Parametros!$J:$L,3,0),VLOOKUP(N26,Parametros!V:W,2,0)),0) -> 0 | EI26: =IFERROR(Z26/Y26,0) -> 0 | EJ26: =IFERROR(VLOOKUP(AC26,Parametros!AL:AM,2,0),1) -> 1 | EM26: =SUM(EP26:GO26) -> 0 | EN26: =EM26=CV26 -> TRUE | EP26: {=_xlfn.IFS(AK26="","",AK26,$CV26/$CM26/$CK26*AK26)} | EQ26: {=_xlfn.IFS(AL26="","",AL26,$CV26/$CM26/$CK26*AL26)} | ER26: {=_xlfn.IFS(AM26="","",AM26,$CV26/$CM26/$CK26*AM26)} | ES26: {=_xlfn.IFS(AN26="","",AN26,$CV26/$CM26/$CK26*AN26)} | ET26: {=_xlfn.IFS(AO26="","",AO26,$CV26/$CM26/$CK26*AO26)} | EU26: {=_xlfn.IFS(AP26="","",AP26,$CV26/$CM26/$CK26*AP26)} | EV26: {=_xlfn.IFS(AQ26="","",AQ26,$CV26/$CM26/$CK26*AQ26)} | EW26: {=_xlfn.IFS(AR26="","",AR26,$CV26/$CM26/$CK26*AR26)} | ... GO26: {=_xlfn.IFS(CJ26="","",CJ26,$CV26/$CM26/$CK26*CJ26)} | GQ26: =SUM(EP26:ES26) -> 0 | GR26: =SUM(ET26:EW26) -> 0 | GS26: =SUM(EX26:FB26) -> 0 | GT26: =SUM(FC26:FF26) -> 0 | GU26: =SUM(FG26:FK26) -> 0 | GV26: =SUM(FL26:FO26) -> 0 | GW26: =SUM(FP26:FS26) -> 0 | GX26: =SUM(FT26:FX26) -> 0 | GY26: =SUM(FY26:GB26) -> 0 | GZ26: =SUM(GC26:GF26) -> 0 | HA26: =SUM(GG26:GK26) -> 0 | HB26: =SUM(GL26:GO26) -> 0
C27: =+C26+1 -> 25 | D27: 0 | E27: 0 | F27: 0 | G27: =IF(M27="","",IF(ISERROR(VLOOKUP(M27,Parametros!AI:AJ,2,0)),"Demais OOH",VLOOKUP(M27,Parametros!AI:AJ,2,0))) | J27: =IFERROR(VLOOKUP(K27,'[40]GEOS AMBEV'!B:C,2,0),"") | K27: =_xlfn.XLOOKUP(L27,POPULAÇÃO!D:D,POPULAÇÃO!C:C) -> 0 | Q27: =IFERROR(VLOOKUP(O27,Parametros!J:K,2,0),"") | T27: =IF(R27="","",IF(R27="digital",W27&"""- "&V27&" ins/dia",TEXT(AA27,"0,00")&" x "&TEXT(AB27,"0,00")&"m")) | Y27: =IFERROR(86400/W27/24*X27,0) -> 0 | Z27: =+U27*V27 -> 0 | AF27: =IFERROR(VLOOKUP(AE27,Parametros!E:F,2,0),0) -> 0 | AJ27: =IF(AG27="","",AH27-AG27+1) | CL27: =IFERROR(COUNT(AK27:CJ27)/CK27,0) -> 0 | CM27: =IFERROR(SUM(AK27:CJ27)/CK27,0) -> 0 | CQ27: =IF(AE27="diária",CP27*AJ27*U27,IF(AJ27>AF27,CP27,AJ27/AF27*CP27)*U27) -> 0 | CR27: =IF(CN27="","0",IF(CN27="Faces",CQ27*CM27,CQ27*CL27)) -> 0 | CS27: 0.83 | CT27: =CP27*(1-CS27) -> 0 | CU27: =CR27*(1-CS27) -> 0 | CV27: =CU27*0.8 -> 0 | CW27: =IF(H27="","",IFERROR(VLOOKUP(H27,[40]Parametros!B:C,2,0),0)) | CX27: =EG27 -> 0 | CY27: =IF(OR(CX27=0,CX27="Sem base de dados"),0,CV27/CX27*1000) -> 0 | DA27: =DK27 -> 0 | DB27: =DW27 -> 0 | DD27: =IF(AG27="",0,EDATE(DATE(YEAR(AG27),MONTH(AG27),1),5)) -> 0 | DE27: 2025 | DJ27: 800 | DK27: =DJ27*DI27*DH27 -> 0 | DM27: =IF(R27="Digital",0,IF(SUM(AK27:CJ27)=0,0,LARGE(AK27:CJ27,1))) -> 0 | DP27: =ROUNDUP(DN27*DM27*(1+DO27),0) -> 0 | DU27: =PRODUCT(DP27:DT27) -> 0 | DW27: =(DU27+DV27) -> 0 | DZ27: =SUMIFS('Mediana dos Impactos'!D:D,'Mediana dos Impactos'!C:C,OOH!O27,'Mediana dos Impactos'!B:B,OOH!L27) -> 0 | EB27: =AJ27 | EC27: =IFERROR(IF(DZ27<>"",DZ27/7*EB27,$EA27/30*EB27),0) -> 0 | ED27: =IF(DY27="",0,IF(DY27="Face",CM27,CL27)) -> 0 | EE27: =IF(DY27="Sem base de dados",DY27,EC27*ED27) -> 0 | EF27: =IF(R27="digital",(EI27*EH27),EJ27*EH27) -> 0 | EG27: =+EE27*EF27 -> 0 | EH27: =IFERROR(IF(N27="via pública",VLOOKUP($O27,Parametros!$J:$L,3,0),VLOOKUP(N27,Parametros!V:W,2,0)),0) -> 0 | EI27: =IFERROR(Z27/Y27,0) -> 0 | EJ27: =IFERROR(VLOOKUP(AC27,Parametros!AL:AM,2,0),1) -> 1 | EM27: =SUM(EP27:GO27) -> 0 | EN27: =EM27=CV27 -> TRUE | EP27: {=_xlfn.IFS(AK27="","",AK27,$CV27/$CM27/$CK27*AK27)} | EQ27: {=_xlfn.IFS(AL27="","",AL27,$CV27/$CM27/$CK27*AL27)} | ER27: {=_xlfn.IFS(AM27="","",AM27,$CV27/$CM27/$CK27*AM27)} | ES27: {=_xlfn.IFS(AN27="","",AN27,$CV27/$CM27/$CK27*AN27)} | ET27: {=_xlfn.IFS(AO27="","",AO27,$CV27/$CM27/$CK27*AO27)} | EU27: {=_xlfn.IFS(AP27="","",AP27,$CV27/$CM27/$CK27*AP27)} | EV27: {=_xlfn.IFS(AQ27="","",AQ27,$CV27/$CM27/$CK27*AQ27)} | EW27: {=_xlfn.IFS(AR27="","",AR27,$CV27/$CM27/$CK27*AR27)} | ... GO27: {=_xlfn.IFS(CJ27="","",CJ27,$CV27/$CM27/$CK27*CJ27)} | GQ27: =SUM(EP27:ES27) -> 0 | GR27: =SUM(ET27:EW27) -> 0 | GS27: =SUM(EX27:FB27) -> 0 | GT27: =SUM(FC27:FF27) -> 0 | GU27: =SUM(FG27:FK27) -> 0 | GV27: =SUM(FL27:FO27) -> 0 | GW27: =SUM(FP27:FS27) -> 0 | GX27: =SUM(FT27:FX27) -> 0 | GY27: =SUM(FY27:GB27) -> 0 | GZ27: =SUM(GC27:GF27) -> 0 | HA27: =SUM(GG27:GK27) -> 0 | HB27: =SUM(GL27:GO27) -> 0
C28: =+C27+1 -> 26 | D28: 0 | E28: 0 | F28: 0 | G28: =IF(M28="","",IF(ISERROR(VLOOKUP(M28,Parametros!AI:AJ,2,0)),"Demais OOH",VLOOKUP(M28,Parametros!AI:AJ,2,0))) | J28: =IFERROR(VLOOKUP(K28,'[40]GEOS AMBEV'!B:C,2,0),"") | K28: =_xlfn.XLOOKUP(L28,POPULAÇÃO!D:D,POPULAÇÃO!C:C) -> 0 | Q28: =IFERROR(VLOOKUP(O28,Parametros!J:K,2,0),"") | T28: =IF(R28="","",IF(R28="digital",W28&"""- "&V28&" ins/dia",TEXT(AA28,"0,00")&" x "&TEXT(AB28,"0,00")&"m")) | Y28: =IFERROR(86400/W28/24*X28,0) -> 0 | Z28: =+U28*V28 -> 0 | AF28: =IFERROR(VLOOKUP(AE28,Parametros!E:F,2,0),0) -> 0 | AJ28: =IF(AG28="","",AH28-AG28+1) | CL28: =IFERROR(COUNT(AK28:CJ28)/CK28,0) -> 0 | CM28: =IFERROR(SUM(AK28:CJ28)/CK28,0) -> 0 | CQ28: =IF(AE28="diária",CP28*AJ28*U28,IF(AJ28>AF28,CP28,AJ28/AF28*CP28)*U28) -> 0 | CR28: =IF(CN28="","0",IF(CN28="Faces",CQ28*CM28,CQ28*CL28)) -> 0 | CS28: 0.83 | CT28: =CP28*(1-CS28) -> 0 | CU28: =CR28*(1-CS28) -> 0 | CV28: =CU28*0.8 -> 0 | CW28: =IF(H28="","",IFERROR(VLOOKUP(H28,[40]Parametros!B:C,2,0),0)) | CX28: =EG28 -> 0 | CY28: =IF(OR(CX28=0,CX28="Sem base de dados"),0,CV28/CX28*1000) -> 0 | DA28: =DK28 -> 0 | DB28: =DW28 -> 0 | DD28: =IF(AG28="",0,EDATE(DATE(YEAR(AG28),MONTH(AG28),1),5)) -> 0 | DE28: 2025 | DJ28: 800 | DK28: =DJ28*DI28*DH28 -> 0 | DM28: =IF(R28="Digital",0,IF(SUM(AK28:CJ28)=0,0,LARGE(AK28:CJ28,1))) -> 0 | DP28: =ROUNDUP(DN28*DM28*(1+DO28),0) -> 0 | DU28: =PRODUCT(DP28:DT28) -> 0 | DW28: =(DU28+DV28) -> 0 | DZ28: =SUMIFS('Mediana dos Impactos'!D:D,'Mediana dos Impactos'!C:C,OOH!O28,'Mediana dos Impactos'!B:B,OOH!L28) -> 0 | EB28: =AJ28 | EC28: =IFERROR(IF(DZ28<>"",DZ28/7*EB28,$EA28/30*EB28),0) -> 0 | ED28: =IF(DY28="",0,IF(DY28="Face",CM28,CL28)) -> 0 | EE28: =IF(DY28="Sem base de dados",DY28,EC28*ED28) -> 0 | EF28: =IF(R28="digital",(EI28*EH28),EJ28*EH28) -> 0 | EG28: =+EE28*EF28 -> 0 | EH28: =IFERROR(IF(N28="via pública",VLOOKUP($O28,Parametros!$J:$L,3,0),VLOOKUP(N28,Parametros!V:W,2,0)),0) -> 0 | EI28: =IFERROR(Z28/Y28,0) -> 0 | EJ28: =IFERROR(VLOOKUP(AC28,Parametros!AL:AM,2,0),1) -> 1 | EM28: =SUM(EP28:GO28) -> 0 | EN28: =EM28=CV28 -> TRUE | EP28: {=_xlfn.IFS(AK28="","",AK28,$CV28/$CM28/$CK28*AK28)} | EQ28: {=_xlfn.IFS(AL28="","",AL28,$CV28/$CM28/$CK28*AL28)} | ER28: {=_xlfn.IFS(AM28="","",AM28,$CV28/$CM28/$CK28*AM28)} | ES28: {=_xlfn.IFS(AN28="","",AN28,$CV28/$CM28/$CK28*AN28)} | ET28: {=_xlfn.IFS(AO28="","",AO28,$CV28/$CM28/$CK28*AO28)} | EU28: {=_xlfn.IFS(AP28="","",AP28,$CV28/$CM28/$CK28*AP28)} | EV28: {=_xlfn.IFS(AQ28="","",AQ28,$CV28/$CM28/$CK28*AQ28)} | EW28: {=_xlfn.IFS(AR28="","",AR28,$CV28/$CM28/$CK28*AR28)} | ... GO28: {=_xlfn.IFS(CJ28="","",CJ28,$CV28/$CM28/$CK28*CJ28)} | GQ28: =SUM(EP28:ES28) -> 0 | GR28: =SUM(ET28:EW28) -> 0 | GS28: =SUM(EX28:FB28) -> 0 | GT28: =SUM(FC28:FF28) -> 0 | GU28: =SUM(FG28:FK28) -> 0 | GV28: =SUM(FL28:FO28) -> 0 | GW28: =SUM(FP28:FS28) -> 0 | GX28: =SUM(FT28:FX28) -> 0 | GY28: =SUM(FY28:GB28) -> 0 | GZ28: =SUM(GC28:GF28) -> 0 | HA28: =SUM(GG28:GK28) -> 0 | HB28: =SUM(GL28:GO28) -> 0
C29: =+C28+1 -> 27 | D29: 0 | E29: 0 | F29: 0 | G29: =IF(M29="","",IF(ISERROR(VLOOKUP(M29,Parametros!AI:AJ,2,0)),"Demais OOH",VLOOKUP(M29,Parametros!AI:AJ,2,0))) | J29: =IFERROR(VLOOKUP(K29,'GEOS AMBEV'!B:C,2,0),"") | K29: =_xlfn.XLOOKUP(L29,POPULAÇÃO!D:D,POPULAÇÃO!C:C) -> 0 | Q29: =IFERROR(VLOOKUP(O29,Parametros!J:K,2,0),"") | T29: =IF(R29="","",IF(R29="digital",W29&"""- "&V29&" ins/dia",TEXT(AA29,"0,00")&" x "&TEXT(AB29,"0,00")&"m")) | Y29: =IFERROR(86400/W29/24*X29,0) -> 0 | Z29: =+U29*V29 -> 0 | AF29: =IFERROR(VLOOKUP(AE29,Parametros!E:F,2,0),0) -> 0 | AJ29: =IF(AG29="","",AH29-AG29+1) | CL29: =IFERROR(COUNT(AK29:CJ29)/CK29,0) -> 0 | CM29: =IFERROR(SUM(AK29:CJ29)/CK29,0) -> 0 | CQ29: =IF(AE29="diária",CP29*AJ29*U29,IF(AJ29>AF29,CP29,AJ29/AF29*CP29)*U29) -> 0 | CR29: =IF(CN29="","0",IF(CN29="Faces",CQ29*CM29,CQ29*CL29)) -> 0 | CS29: 0.83 | CT29: =CP29*(1-CS29) -> 0 | CU29: =CR29*(1-CS29) -> 0 | CV29: =CU29*0.8 -> 0 | CW29: =IF(H29="","",IFERROR(VLOOKUP(H29,Parametros!B:C,2,0),0)) | CX29: =EG29 -> 0 | CY29: =IF(OR(CX29=0,CX29="Sem base de dados"),0,CV29/CX29*1000) -> 0 | DA29: =DK29 -> 0 | DB29: =DW29 -> 0 | DD29: =IF(AG29="",0,EDATE(DATE(YEAR(AG29),MONTH(AG29),1),5)) -> 0 | DE29: 2025 | DJ29: 800 | DK29: =DJ29*DI29*DH29 -> 0 | DM29: =IF(R29="Digital",0,IF(SUM(AK29:CJ29)=0,0,LARGE(AK29:CJ29,1))) -> 0 | DP29: =ROUNDUP(DN29*DM29*(1+DO29),0) -> 0 | DU29: =PRODUCT(DP29:DT29) -> 0 | DW29: =(DU29+DV29) -> 0 | DZ29: =SUMIFS('Mediana dos Impactos'!D:D,'Mediana dos Impactos'!C:C,OOH!O29,'Mediana dos Impactos'!B:B,OOH!L29) -> 0 | EB29: =AJ29 | EC29: =IFERROR(IF(DZ29<>"",DZ29/7*EB29,$EA29/30*EB29),0) -> 0 | ED29: =IF(DY29="",0,IF(DY29="Face",CM29,CL29)) -> 0 | EE29: =IF(DY29="Sem base de dados",DY29,EC29*ED29) -> 0 | EF29: =IF(R29="digital",(EI29*EH29),EJ29*EH29) -> 0 | EG29: =+EE29*EF29 -> 0 | EH29: =IFERROR(IF(N29="via pública",VLOOKUP($O29,Parametros!$J:$L,3,0),VLOOKUP(N29,Parametros!V:W,2,0)),0) -> 0 | EI29: =IFERROR(Z29/Y29,0) -> 0 | EJ29: =IFERROR(VLOOKUP(AC29,Parametros!AL:AM,2,0),1) -> 1 | EM29: =SUM(EP29:GO29) -> 0 | EN29: =EM29=CV29 -> TRUE | EP29: {=_xlfn.IFS(AK29="","",AK29,$CV29/$CM29/$CK29*AK29)} | EQ29: {=_xlfn.IFS(AL29="","",AL29,$CV29/$CM29/$CK29*AL29)} | ER29: {=_xlfn.IFS(AM29="","",AM29,$CV29/$CM29/$CK29*AM29)} | ES29: {=_xlfn.IFS(AN29="","",AN29,$CV29/$CM29/$CK29*AN29)} | ET29: {=_xlfn.IFS(AO29="","",AO29,$CV29/$CM29/$CK29*AO29)} | EU29: {=_xlfn.IFS(AP29="","",AP29,$CV29/$CM29/$CK29*AP29)} | EV29: {=_xlfn.IFS(AQ29="","",AQ29,$CV29/$CM29/$CK29*AQ29)} | EW29: {=_xlfn.IFS(AR29="","",AR29,$CV29/$CM29/$CK29*AR29)} | ... GO29: {=_xlfn.IFS(CJ29="","",CJ29,$CV29/$CM29/$CK29*CJ29)} | GQ29: =SUM(EP29:ES29) -> 0 | GR29: =SUM(ET29:EW29) -> 0 | GS29: =SUM(EX29:FB29) -> 0 | GT29: =SUM(FC29:FF29) -> 0 | GU29: =SUM(FG29:FK29) -> 0 | GV29: =SUM(FL29:FO29) -> 0 | GW29: =SUM(FP29:FS29) -> 0 | GX29: =SUM(FT29:FX29) -> 0 | GY29: =SUM(FY29:GB29) -> 0 | GZ29: =SUM(GC29:GF29) -> 0 | HA29: =SUM(GG29:GK29) -> 0 | HB29: =SUM(GL29:GO29) -> 0
C30: =+C29+1 -> 28 | D30: 0 | E30: 0 | F30: 0 | G30: =IF(M30="","",IF(ISERROR(VLOOKUP(M30,Parametros!AI:AJ,2,0)),"Demais OOH",VLOOKUP(M30,Parametros!AI:AJ,2,0))) | J30: =IFERROR(VLOOKUP(K30,'GEOS AMBEV'!B:C,2,0),"") | K30: =_xlfn.XLOOKUP(L30,POPULAÇÃO!D:D,POPULAÇÃO!C:C) -> 0 | Q30: =IFERROR(VLOOKUP(O30,Parametros!J:K,2,0),"") | T30: =IF(R30="","",IF(R30="digital",W30&"""- "&V30&" ins/dia",TEXT(AA30,"0,00")&" x "&TEXT(AB30,"0,00")&"m")) | Y30: =IFERROR(86400/W30/24*X30,0) -> 0 | Z30: =+U30*V30 -> 0 | AF30: =IFERROR(VLOOKUP(AE30,Parametros!E:F,2,0),0) -> 0 | AJ30: =IF(AG30="","",AH30-AG30+1) | CL30: =IFERROR(COUNT(AK30:CJ30)/CK30,0) -> 0 | CM30: =IFERROR(SUM(AK30:CJ30)/CK30,0) -> 0 | CQ30: =IF(AE30="diária",CP30*AJ30*U30,IF(AJ30>AF30,CP30,AJ30/AF30*CP30)*U30) -> 0 | CR30: =IF(CN30="","0",IF(CN30="Faces",CQ30*CM30,CQ30*CL30)) -> 0 | CS30: 0.83 | CT30: =CP30*(1-CS30) -> 0 | CU30: =CR30*(1-CS30) -> 0 | CV30: =CU30*0.8 -> 0 | CW30: =IF(H30="","",IFERROR(VLOOKUP(H30,Parametros!B:C,2,0),0)) | CX30: =EG30 -> 0 | CY30: =IF(OR(CX30=0,CX30="Sem base de dados"),0,CV30/CX30*1000) -> 0 | DA30: =DK30 -> 0 | DB30: =DW30 -> 0 | DD30: =IF(AG30="",0,EDATE(DATE(YEAR(AG30),MONTH(AG30),1),5)) -> 0 | DE30: 2025 | DJ30: 800 | DK30: =DJ30*DI30*DH30 -> 0 | DM30: =IF(R30="Digital",0,IF(SUM(AK30:CJ30)=0,0,LARGE(AK30:CJ30,1))) -> 0 | DP30: =ROUNDUP(DN30*DM30*(1+DO30),0) -> 0 | DU30: =PRODUCT(DP30:DT30) -> 0 | DW30: =(DU30+DV30) -> 0 | DZ30: =SUMIFS('Mediana dos Impactos'!D:D,'Mediana dos Impactos'!C:C,OOH!O30,'Mediana dos Impactos'!B:B,OOH!L30) -> 0 | EB30: =AJ30 | EC30: =IFERROR(IF(DZ30<>"",DZ30/7*EB30,$EA30/30*EB30),0) -> 0 | ED30: =IF(DY30="",0,IF(DY30="Face",CM30,CL30)) -> 0 | EE30: =IF(DY30="Sem base de dados",DY30,EC30*ED30) -> 0 | EF30: =IF(R30="digital",(EI30*EH30),EJ30*EH30) -> 0 | EG30: =+EE30*EF30 -> 0 | EH30: =IFERROR(IF(N30="via pública",VLOOKUP($O30,Parametros!$J:$L,3,0),VLOOKUP(N30,Parametros!V:W,2,0)),0) -> 0 | EI30: =IFERROR(Z30/Y30,0) -> 0 | EJ30: =IFERROR(VLOOKUP(AC30,Parametros!AL:AM,2,0),1) -> 1 | EM30: =SUM(EP30:GO30) -> 0 | EN30: =EM30=CV30 -> TRUE | EP30: {=_xlfn.IFS(AK30="","",AK30,$CV30/$CM30/$CK30*AK30)} | EQ30: {=_xlfn.IFS(AL30="","",AL30,$CV30/$CM30/$CK30*AL30)} | ER30: {=_xlfn.IFS(AM30="","",AM30,$CV30/$CM30/$CK30*AM30)} | ES30: {=_xlfn.IFS(AN30="","",AN30,$CV30/$CM30/$CK30*AN30)} | ET30: {=_xlfn.IFS(AO30="","",AO30,$CV30/$CM30/$CK30*AO30)} | EU30: {=_xlfn.IFS(AP30="","",AP30,$CV30/$CM30/$CK30*AP30)} | EV30: {=_xlfn.IFS(AQ30="","",AQ30,$CV30/$CM30/$CK30*AQ30)} | EW30: {=_xlfn.IFS(AR30="","",AR30,$CV30/$CM30/$CK30*AR30)} | ... GO30: {=_xlfn.IFS(CJ30="","",CJ30,$CV30/$CM30/$CK30*CJ30)} | GQ30: =SUM(EP30:ES30) -> 0 | GR30: =SUM(ET30:EW30) -> 0 | GS30: =SUM(EX30:FB30) -> 0 | GT30: =SUM(FC30:FF30) -> 0 | GU30: =SUM(FG30:FK30) -> 0 | GV30: =SUM(FL30:FO30) -> 0 | GW30: =SUM(FP30:FS30) -> 0 | GX30: =SUM(FT30:FX30) -> 0 | GY30: =SUM(FY30:GB30) -> 0 | GZ30: =SUM(GC30:GF30) -> 0 | HA30: =SUM(GG30:GK30) -> 0 | HB30: =SUM(GL30:GO30) -> 0
C31: =+C30+1 -> 29 | D31: 0 | E31: 0 | F31: 0 | G31: =IF(M31="","",IF(ISERROR(VLOOKUP(M31,Parametros!AI:AJ,2,0)),"Demais OOH",VLOOKUP(M31,Parametros!AI:AJ,2,0))) | J31: =IFERROR(VLOOKUP(K31,'GEOS AMBEV'!B:C,2,0),"") | K31: =_xlfn.XLOOKUP(L31,POPULAÇÃO!D:D,POPULAÇÃO!C:C) -> 0 | Q31: =IFERROR(VLOOKUP(O31,Parametros!J:K,2,0),"") | T31: =IF(R31="","",IF(R31="digital",W31&"""- "&V31&" ins/dia",TEXT(AA31,"0,00")&" x "&TEXT(AB31,"0,00")&"m")) | Y31: =IFERROR(86400/W31/24*X31,0) -> 0 | Z31: =+U31*V31 -> 0 | AF31: =IFERROR(VLOOKUP(AE31,Parametros!E:F,2,0),0) -> 0 | AJ31: =IF(AG31="","",AH31-AG31+1) | CL31: =IFERROR(COUNT(AK31:CJ31)/CK31,0) -> 0 | CM31: =IFERROR(SUM(AK31:CJ31)/CK31,0) -> 0 | CQ31: =IF(AE31="diária",CP31*AJ31*U31,IF(AJ31>AF31,CP31,AJ31/AF31*CP31)*U31) -> 0 | CR31: =IF(CN31="","0",IF(CN31="Faces",CQ31*CM31,CQ31*CL31)) -> 0 | CS31: 0.83 | CT31: =CP31*(1-CS31) -> 0 | CU31: =CR31*(1-CS31) -> 0 | CV31: =CU31*0.8 -> 0 | CX31: =EG31 -> 0 | CY31: =IF(OR(CX31=0,CX31="Sem base de dados"),0,CV31/CX31*1000) -> 0 | DA31: =DK31 -> 0 | DB31: =DW31 -> 0 | DD31: =IF(AG31="",0,EDATE(DATE(YEAR(AG31),MONTH(AG31),1),5)) -> 0 | DE31: 2025 | DJ31: 800 | DK31: =DJ31*DI31*DH31 -> 0 | DM31: =IF(R31="Digital",0,IF(SUM(AK31:CJ31)=0,0,LARGE(AK31:CJ31,1))) -> 0 | DP31: =ROUNDUP(DN31*DM31*(1+DO31),0) -> 0 | DU31: =PRODUCT(DP31:DT31) -> 0 | DW31: =(DU31+DV31) -> 0 | DZ31: =SUMIFS('Mediana dos Impactos'!D:D,'Mediana dos Impactos'!C:C,OOH!O31,'Mediana dos Impactos'!B:B,OOH!L31) -> 0 | EB31: =AJ31 | EC31: =IFERROR(IF(DZ31<>"",DZ31/7*EB31,$EA31/30*EB31),0) -> 0 | ED31: =IF(DY31="",0,IF(DY31="Face",CM31,CL31)) -> 0 | EE31: =IF(DY31="Sem base de dados",DY31,EC31*ED31) -> 0 | EF31: =IF(R31="digital",(EI31*EH31),EJ31*EH31) -> 0 | EG31: =+EE31*EF31 -> 0 | EH31: =IFERROR(IF(N31="via pública",VLOOKUP($O31,Parametros!$J:$L,3,0),VLOOKUP(N31,Parametros!V:W,2,0)),0) -> 0 | EI31: =IFERROR(Z31/Y31,0) -> 0 | EJ31: =IFERROR(VLOOKUP(AC31,Parametros!AL:AM,2,0),1) -> 1 | EM31: =SUM(EP31:GO31) -> 0 | EN31: =EM31=CV31 -> TRUE | EP31: {=_xlfn.IFS(AK31="","",AK31,$CV31/$CM31/$CK31*AK31)} | EQ31: {=_xlfn.IFS(AL31="","",AL31,$CV31/$CM31/$CK31*AL31)} | ER31: {=_xlfn.IFS(AM31="","",AM31,$CV31/$CM31/$CK31*AM31)} | ES31: {=_xlfn.IFS(AN31="","",AN31,$CV31/$CM31/$CK31*AN31)} | ET31: {=_xlfn.IFS(AO31="","",AO31,$CV31/$CM31/$CK31*AO31)} | EU31: {=_xlfn.IFS(AP31="","",AP31,$CV31/$CM31/$CK31*AP31)} | EV31: {=_xlfn.IFS(AQ31="","",AQ31,$CV31/$CM31/$CK31*AQ31)} | EW31: {=_xlfn.IFS(AR31="","",AR31,$CV31/$CM31/$CK31*AR31)} | ... GO31: {=_xlfn.IFS(CJ31="","",CJ31,$CV31/$CM31/$CK31*CJ31)} | GQ31: =SUM(EP31:ES31) -> 0 | GR31: =SUM(ET31:EW31) -> 0 | GS31: =SUM(EX31:FB31) -> 0 | GT31: =SUM(FC31:FF31) -> 0 | GU31: =SUM(FG31:FK31) -> 0 | GV31: =SUM(FL31:FO31) -> 0 | GW31: =SUM(FP31:FS31) -> 0 | GX31: =SUM(FT31:FX31) -> 0 | GY31: =SUM(FY31:GB31) -> 0 | GZ31: =SUM(GC31:GF31) -> 0 | HA31: =SUM(GG31:GK31) -> 0 | HB31: =SUM(GL31:GO31) -> 0
C32: =+C31+1 -> 30 | D32: 0 | E32: 0 | F32: 0 | G32: =IF(M32="","",IF(ISERROR(VLOOKUP(M32,Parametros!AI:AJ,2,0)),"Demais OOH",VLOOKUP(M32,Parametros!AI:AJ,2,0))) | J32: =IFERROR(VLOOKUP(K32,'GEOS AMBEV'!B:C,2,0),"") | K32: =_xlfn.XLOOKUP(L32,POPULAÇÃO!D:D,POPULAÇÃO!C:C) -> 0 | Q32: =IFERROR(VLOOKUP(O32,Parametros!J:K,2,0),"") | T32: =IF(R32="","",IF(R32="digital",W32&"""- "&V32&" ins/dia",TEXT(AA32,"0,00")&" x "&TEXT(AB32,"0,00")&"m")) | Y32: =IFERROR(86400/W32/24*X32,0) -> 0 | Z32: =+U32*V32 -> 0 | AF32: =IFERROR(VLOOKUP(AE32,Parametros!E:F,2,0),0) -> 0 | AJ32: =IF(AG32="","",AH32-AG32+1) | CL32: =IFERROR(COUNT(AK32:CJ32)/CK32,0) -> 0 | CM32: =IFERROR(SUM(AK32:CJ32)/CK32,0) -> 0 | CQ32: =IF(AE32="diária",CP32*AJ32*U32,IF(AJ32>AF32,CP32,AJ32/AF32*CP32)*U32) -> 0 | CR32: =IF(CN32="","0",IF(CN32="Faces",CQ32*CM32,CQ32*CL32)) -> 0 | CS32: 0.65 | CT32: =CP32*(1-CS32) -> 0 | CU32: =CR32*(1-CS32) -> 0 | CV32: =CU32*0.8 -> 0 | CW32: =IF(H32="","",IFERROR(VLOOKUP(H32,Parametros!B:C,2,0),0)) | CX32: =EG32 -> 0 | CY32: =IF(OR(CX32=0,CX32="Sem base de dados"),0,CV32/CX32*1000) -> 0 | DA32: =DK32 -> 0 | DB32: =DW32 -> 0 | DD32: =IF(AG32="",0,EDATE(DATE(YEAR(AG32),MONTH(AG32),1),5)) -> 0 | DE32: 2025 | DJ32: 800 | DK32: =DJ32*DI32*DH32 -> 0 | DM32: =IF(R32="Digital",0,IF(SUM(AK32:CJ32)=0,0,LARGE(AK32:CJ32,1))) -> 0 | DP32: =ROUNDUP(DN32*DM32*(1+DO32),0) -> 0 | DU32: =PRODUCT(DP32:DT32) -> 0 | DW32: =(DU32+DV32) -> 0 | DZ32: =SUMIFS('Mediana dos Impactos'!D:D,'Mediana dos Impactos'!C:C,OOH!O32,'Mediana dos Impactos'!B:B,OOH!L32) -> 0 | EB32: =AJ32 | EC32: =IFERROR(IF(DZ32<>"",DZ32/7*EB32,$EA32/30*EB32),0) -> 0 | ED32: =IF(DY32="",0,IF(DY32="Face",CM32,CL32)) -> 0 | EE32: =IF(DY32="Sem base de dados",DY32,EC32*ED32) -> 0 | EF32: =IF(R32="digital",(EI32*EH32),EJ32*EH32) -> 0 | EG32: =+EE32*EF32 -> 0 | EH32: =IFERROR(IF(N32="via pública",VLOOKUP($O32,Parametros!$J:$L,3,0),VLOOKUP(N32,Parametros!V:W,2,0)),0) -> 0 | EI32: =IFERROR(Z32/Y32,0) -> 0 | EJ32: =IFERROR(VLOOKUP(AC32,Parametros!AL:AM,2,0),1) -> 1 | EM32: =SUM(EP32:GO32) -> 0 | EN32: =EM32=CV32 -> TRUE | EP32: {=_xlfn.IFS(AK32="","",AK32,$CV32/$CM32/$CK32*AK32)} | EQ32: {=_xlfn.IFS(AL32="","",AL32,$CV32/$CM32/$CK32*AL32)} | ER32: {=_xlfn.IFS(AM32="","",AM32,$CV32/$CM32/$CK32*AM32)} | ES32: {=_xlfn.IFS(AN32="","",AN32,$CV32/$CM32/$CK32*AN32)} | ET32: {=_xlfn.IFS(AO32="","",AO32,$CV32/$CM32/$CK32*AO32)} | EU32: {=_xlfn.IFS(AP32="","",AP32,$CV32/$CM32/$CK32*AP32)} | EV32: {=_xlfn.IFS(AQ32="","",AQ32,$CV32/$CM32/$CK32*AQ32)} | EW32: {=_xlfn.IFS(AR32="","",AR32,$CV32/$CM32/$CK32*AR32)} | ... GO32: {=_xlfn.IFS(CJ32="","",CJ32,$CV32/$CM32/$CK32*CJ32)} | GQ32: =SUM(EP32:ES32) -> 0 | GR32: =SUM(ET32:EW32) -> 0 | GS32: =SUM(EX32:FB32) -> 0 | GT32: =SUM(FC32:FF32) -> 0 | GU32: =SUM(FG32:FK32) -> 0 | GV32: =SUM(FL32:FO32) -> 0 | GW32: =SUM(FP32:FS32) -> 0 | GX32: =SUM(FT32:FX32) -> 0 | GY32: =SUM(FY32:GB32) -> 0 | GZ32: =SUM(GC32:GF32) -> 0 | HA32: =SUM(GG32:GK32) -> 0 | HB32: =SUM(GL32:GO32) -> 0
C33: =+C32+1 -> 31 | D33: 0 | E33: 0 | F33: 0 | G33: =IF(M33="","",IF(ISERROR(VLOOKUP(M33,Parametros!AI:AJ,2,0)),"Demais OOH",VLOOKUP(M33,Parametros!AI:AJ,2,0))) | J33: =IFERROR(VLOOKUP(K33,'GEOS AMBEV'!B:C,2,0),"") | K33: =_xlfn.XLOOKUP(L33,POPULAÇÃO!D:D,POPULAÇÃO!C:C) -> 0 | Q33: =IFERROR(VLOOKUP(O33,Parametros!J:K,2,0),"") | T33: =IF(R33="","",IF(R33="digital",W33&"""- "&V33&" ins/dia",TEXT(AA33,"0,00")&" x "&TEXT(AB33,"0,00")&"m")) | Y33: =IFERROR(86400/W33/24*X33,0) -> 0 | Z33: =+U33*V33 -> 0 | AF33: =IFERROR(VLOOKUP(AE33,Parametros!E:F,2,0),0) -> 0 | AJ33: =IF(AG33="","",AH33-AG33+1) | CL33: =IFERROR(COUNT(AK33:CJ33)/CK33,0) -> 0 | CM33: =IFERROR(SUM(AK33:CJ33)/CK33,0) -> 0 | CQ33: =IF(AE33="diária",CP33*AJ33*U33,IF(AJ33>AF33,CP33,AJ33/AF33*CP33)*U33) -> 0 | CR33: =IF(CN33="","0",IF(CN33="Faces",CQ33*CM33,CQ33*CL33)) -> 0 | CS33: 0.65 | CT33: =CP33*(1-CS33) -> 0 | CU33: =CR33*(1-CS33) -> 0 | CV33: =CU33*0.8 -> 0 | CW33: =IF(H33="","",IFERROR(VLOOKUP(H33,Parametros!B:C,2,0),0)) | CX33: =EG33 -> 0 | CY33: =IF(OR(CX33=0,CX33="Sem base de dados"),0,CV33/CX33*1000) -> 0 | DA33: =DK33 -> 0 | DB33: =DW33 -> 0 | DD33: =IF(AG33="",0,EDATE(DATE(YEAR(AG33),MONTH(AG33),1),5)) -> 0 | DE33: 2025 | DJ33: 800 | DK33: =DJ33*DI33*DH33 -> 0 | DM33: =IF(R33="Digital",0,IF(SUM(AK33:CJ33)=0,0,LARGE(AK33:CJ33,1))) -> 0 | DP33: =ROUNDUP(DN33*DM33*(1+DO33),0) -> 0 | DU33: =PRODUCT(DP33:DT33) -> 0 | DW33: =(DU33+DV33) -> 0 | DZ33: =SUMIFS('Mediana dos Impactos'!D:D,'Mediana dos Impactos'!C:C,OOH!O33,'Mediana dos Impactos'!B:B,OOH!L33) -> 0 | EB33: =AJ33 | EC33: =IFERROR(IF(DZ33<>"",DZ33/7*EB33,$EA33/30*EB33),0) -> 0 | ED33: =IF(DY33="",0,IF(DY33="Face",CM33,CL33)) -> 0 | EE33: =IF(DY33="Sem base de dados",DY33,EC33*ED33) -> 0 | EF33: =IF(R33="digital",(EI33*EH33),EJ33*EH33) -> 0 | EG33: =+EE33*EF33 -> 0 | EH33: =IFERROR(IF(N33="via pública",VLOOKUP($O33,Parametros!$J:$L,3,0),VLOOKUP(N33,Parametros!V:W,2,0)),0) -> 0 | EI33: =IFERROR(Z33/Y33,0) -> 0 | EJ33: =IFERROR(VLOOKUP(AC33,Parametros!AL:AM,2,0),1) -> 1 | EM33: =SUM(EP33:GO33) -> 0 | EN33: =EM33=CV33 -> TRUE | EP33: {=_xlfn.IFS(AK33="","",AK33,$CV33/$CM33/$CK33*AK33)} | EQ33: {=_xlfn.IFS(AL33="","",AL33,$CV33/$CM33/$CK33*AL33)} | ER33: {=_xlfn.IFS(AM33="","",AM33,$CV33/$CM33/$CK33*AM33)} | ES33: {=_xlfn.IFS(AN33="","",AN33,$CV33/$CM33/$CK33*AN33)} | ET33: {=_xlfn.IFS(AO33="","",AO33,$CV33/$CM33/$CK33*AO33)} | EU33: {=_xlfn.IFS(AP33="","",AP33,$CV33/$CM33/$CK33*AP33)} | EV33: {=_xlfn.IFS(AQ33="","",AQ33,$CV33/$CM33/$CK33*AQ33)} | EW33: {=_xlfn.IFS(AR33="","",AR33,$CV33/$CM33/$CK33*AR33)} | ... GO33: {=_xlfn.IFS(CJ33="","",CJ33,$CV33/$CM33/$CK33*CJ33)} | GQ33: =SUM(EP33:ES33) -> 0 | GR33: =SUM(ET33:EW33) -> 0 | GS33: =SUM(EX33:FB33) -> 0 | GT33: =SUM(FC33:FF33) -> 0 | GU33: =SUM(FG33:FK33) -> 0 | GV33: =SUM(FL33:FO33) -> 0 | GW33: =SUM(FP33:FS33) -> 0 | GX33: =SUM(FT33:FX33) -> 0 | GY33: =SUM(FY33:GB33) -> 0 | GZ33: =SUM(GC33:GF33) -> 0 | HA33: =SUM(GG33:GK33) -> 0 | HB33: =SUM(GL33:GO33) -> 0
A34: tt | C34: =+C33+1 -> 32 | G34: =IF(M34="","",IF(ISERROR(VLOOKUP(M34,Parametros!AI:AJ,2,0)),"Demais OOH",VLOOKUP(M34,Parametros!AI:AJ,2,0))) | J34: =IFERROR(VLOOKUP(K34,'GEOS AMBEV'!B:C,2,0),"") | Q34: =IFERROR(VLOOKUP(O34,Parametros!J:K,2,0),"") | T34: =IF(R34="","",IF(R34="digital",W34&"""- "&V34&" ins/dia",TEXT(AA34,"0,00")&" x "&TEXT(AB34,"0,00")&"m")) | Y34: =IFERROR(86400/W34/24*X34,0) -> 0 | Z34: =+U34*V34 -> 0 | AJ34: =IF(AG34="","",AH34-AG34+1) | BT34: =SUM(BT22:BT33) -> 0 | BU34: =SUM(BU22:BU33) -> 0 | BV34: =SUM(BV22:BV33) -> 0 | BW34: =SUM(BW22:BW33) -> 0 | BX34: =SUM(BX22:BX33) -> 0 | BY34: =SUM(BY22:BY33) -> 0 | BZ34: =SUM(BZ22:BZ33) -> 0 | CA34: =SUM(CA22:CA33) -> 0 | ... CJ34: =SUM(CJ22:CJ33) -> 0 | CU34: =SUM(CU22:CU33) -> 0 | CV34: =SUM(CV22:CV33) -> 0 | CW34: =IF(H34="","",IFERROR(VLOOKUP(H34,Parametros!B:C,2,0),0)) | CX34: =SUM(CX22:CX33) -> 0 | DA34: =SUM(DA22:DA33) -> 0 | DB34: =SUM(DB22:DB33) -> 0 | DK34: =DJ34*DI34*DH34 -> 0 | DM34: =IF(R34="Digital",0,IF(SUM(AK34:CJ34)=0,0,LARGE(AK34:CJ34,1))) -> 0 | DP34: =ROUNDUP(DN34*DM34*(1+DO34),0) -> 0 | DU34: =PRODUCT(DP34:DT34) -> 0 | DW34: =(DU34+DV34) -> 0 | EB34: =AJ34 | EC34: =IFERROR(IF(DZ34<>"",DZ34/7*EB34,$EA34/30*EB34),0) -> 0 | ED34: =IF(DY34="",0,IF(DY34="Face",CM34,CL34)) -> 0 | EE34: =IF(DY34="Sem base de dados",DY34,EC34*ED34) -> 0 | EI34: =IFERROR(Z34/Y34,0) -> 0 | EJ34: =IFERROR(VLOOKUP(AC34,Parametros!AL:AM,2,0),1) -> 1 | EM34: =SUM(EP34:GO34) -> 0 | EN34: =EM34=CV34 -> TRUE | EP34: {=_xlfn.IFS(AK34="","",AK34,$CV34/$CM34/$CK34*AK34)} | EQ34: {=_xlfn.IFS(AL34="","",AL34,$CV34/$CM34/$CK34*AL34)} | ER34: {=_xlfn.IFS(AM34="","",AM34,$CV34/$CM34/$CK34*AM34)} | ES34: {=_xlfn.IFS(AN34="","",AN34,$CV34/$CM34/$CK34*AN34)} | ET34: {=_xlfn.IFS(AO34="","",AO34,$CV34/$CM34/$CK34*AO34)} | EU34: {=_xlfn.IFS(AP34="","",AP34,$CV34/$CM34/$CK34*AP34)} | EV34: {=_xlfn.IFS(AQ34="","",AQ34,$CV34/$CM34/$CK34*AQ34)} | EW34: {=_xlfn.IFS(AR34="","",AR34,$CV34/$CM34/$CK34*AR34)} | ... FX34: {=_xlfn.IFS(BS34="","",BS34,$CV34/$CM34/$CK34*BS34)} | FY34: =SUM(FY22:FY33) -> 0 | FZ34: =SUM(FZ22:FZ33) -> 0 | GA34: =SUM(GA22:GA33) -> 0 | GB34: =SUM(GB22:GB33) -> 0 | GC34: =SUM(GC22:GC33) -> 0 | GD34: =SUM(GD22:GD33) -> 0 | GE34: =SUM(GE22:GE33) -> 0 | GF34: =SUM(GF22:GF33) -> 0 | ... GK34: =SUM(GK22:GK33) -> 0 | GL34: =SUM(GL25:GL31) -> 0 | GM34: =SUM(GM25:GM31) -> 0 | GN34: =SUM(GN25:GN31) -> 0 | GO34: =SUM(GO25:GO31) -> 0 | GQ34: =SUM(EP34:ES34) -> 0 | GR34: =SUM(ET34:EW34) -> 0 | GS34: =SUM(EX34:FB34) -> 0 | GT34: =SUM(FC34:FF34) -> 0 | GU34: =SUM(FG34:FK34) -> 0 | GV34: =SUM(FL34:FO34) -> 0 | GW34: =SUM(FP34:FS34) -> 0 | GX34: =SUM(FT34:FX34) -> 0 | GY34: =SUM(FY34:GB34) -> 0 | GZ34: =SUM(GC34:GF34) -> 0 | HA34: =SUM(GG34:GK34) -> 0 | HB34: =SUM(GL34:GO34) -> 0
C35: =+C34+1 -> 33 | D35: 0 | E35: 0 | F35: 0 | G35: =IF(M35="","",IF(ISERROR(VLOOKUP(M35,Parametros!AI:AJ,2,0)),"Demais OOH",VLOOKUP(M35,Parametros!AI:AJ,2,0))) | I35: - | J35: =IFERROR(VLOOKUP(K35,'GEOS AMBEV'!B:C,2,0),"") | K35: =_xlfn.XLOOKUP(L35,POPULAÇÃO!D:D,POPULAÇÃO!C:C) -> 0 | Q35: =IFERROR(VLOOKUP(O35,[41]Parametros!J:K,2,0),"") | T35: =IF(R35="","",IF(R35="digital",W35&"""- "&V35&" ins/dia",TEXT(AA35,"0,00")&" x "&TEXT(AB35,"0,00")&"m")) | Y35: =IFERROR(86400/W35/24*X35,0) -> 0 | Z35: =+U35*V35 -> 0 | AF35: =IFERROR(VLOOKUP(AE35,Parametros!E:F,2,0),0) -> 0 | AJ35: =IF(AG35="","",AH35-AG35+1) | CL35: =IFERROR(COUNT(AK35:CJ35)/CK35,0) -> 0 | CM35: =IFERROR(SUM(AK35:CJ35)/CK35,0) -> 0 | CQ35: =IF(AE35="diária",CP35*AJ35*U35,IF(AJ35>AF35,CP35,AJ35/AF35*CP35)*U35) -> 0 | CR35: =IF(CN35="","0",IF(CN35="Faces",CQ35*CM35,CQ35*CL35)) -> 0 | CS35: 0.2875 | CT35: =CP35*(1-CS35) -> 0 | CU35: =CR35*(1-CS35) -> 0 | CV35: =CU35*0.8 -> 0 | CW35: =IF(H35="","",IFERROR(VLOOKUP(H35,Parametros!B:C,2,0),0)) | CX35: =EG35 -> 0 | CY35: =IF(OR(CX35=0,CX35="Sem base de dados"),0,CV35/CX35*1000) -> 0 | DA35: =DK35 -> 0 | DB35: =DW35 -> 0 | DD35: =IF(AG35="",0,EDATE(DATE(YEAR(AG35),MONTH(AG35),1),5)) -> 0 | DE35: 2025 | DJ35: 800 | DK35: =DJ35*DI35*DH35 -> 0 | DM35: =IF(R35="Digital",0,IF(SUM(AK35:CJ35)=0,0,LARGE(AK35:CJ35,1))) -> 0 | DP35: =ROUNDUP(DN35*DM35*(1+DO35),0) -> 0 | DU35: =PRODUCT(DP35:DT35) -> 0 | DW35: =(DU35+DV35) -> 0 | DZ35: =SUMIFS('Mediana dos Impactos'!D:D,'Mediana dos Impactos'!C:C,OOH!O35,'Mediana dos Impactos'!B:B,OOH!L35) -> 0 | EB35: =AJ35 | EC35: =IFERROR(IF(DZ35<>"",DZ35/7*EB35,$EA35/30*EB35),0) -> 0 | ED35: =IF(DY35="",0,IF(DY35="Face",CM35,CL35)) -> 0 | EE35: =IF(DY35="Sem base de dados",DY35,EC35*ED35) -> 0 | EF35: =IF(R35="digital",(EI35*EH35),EJ35*EH35) -> 0 | EG35: =+EE35*EF35 -> 0 | EH35: =IFERROR(IF(N35="via pública",VLOOKUP($O35,Parametros!$J:$L,3,0),VLOOKUP(N35,Parametros!V:W,2,0)),0) -> 0 | EI35: =IFERROR(Z35/Y35,0) -> 0 | EJ35: =IFERROR(VLOOKUP(AC35,Parametros!AL:AM,2,0),1) -> 1 | EM35: =SUM(EP35:GO35) -> 0 | EN35: =EM35=CV35 -> TRUE | EP35: {=_xlfn.IFS(AK35="","",AK35,$CV35/$CM35/$CK35*AK35)} | EQ35: {=_xlfn.IFS(AL35="","",AL35,$CV35/$CM35/$CK35*AL35)} | ER35: {=_xlfn.IFS(AM35="","",AM35,$CV35/$CM35/$CK35*AM35)} | ES35: {=_xlfn.IFS(AN35="","",AN35,$CV35/$CM35/$CK35*AN35)} | ET35: {=_xlfn.IFS(AO35="","",AO35,$CV35/$CM35/$CK35*AO35)} | EU35: {=_xlfn.IFS(AP35="","",AP35,$CV35/$CM35/$CK35*AP35)} | EV35: {=_xlfn.IFS(AQ35="","",AQ35,$CV35/$CM35/$CK35*AQ35)} | EW35: {=_xlfn.IFS(AR35="","",AR35,$CV35/$CM35/$CK35*AR35)} | ... GO35: {=_xlfn.IFS(CJ35="","",CJ35,$CV35/$CM35/$CK35*CJ35)} | GQ35: =SUM(EP35:ES35) -> 0 | GR35: =SUM(ET35:EW35) -> 0 | GS35: =SUM(EX35:FB35) -> 0 | GT35: =SUM(FC35:FF35) -> 0 | GU35: =SUM(FG35:FK35) -> 0 | GV35: =SUM(FL35:FO35) -> 0 | GW35: =SUM(FP35:FS35) -> 0 | GX35: =SUM(FT35:FX35) -> 0 | GY35: =SUM(FY35:GB35) -> 0 | GZ35: =SUM(GC35:GF35) -> 0 | HA35: =SUM(GG35:GK35) -> 0 | HB35: =SUM(GL35:GO35) -> 0
C36: =+C35+1 -> 34 | D36: 0 | E36: 0 | F36: 0 | G36: =IF(M36="","",IF(ISERROR(VLOOKUP(M36,Parametros!AI:AJ,2,0)),"Demais OOH",VLOOKUP(M36,Parametros!AI:AJ,2,0))) | I36: - | J36: =IFERROR(VLOOKUP(K36,'GEOS AMBEV'!B:C,2,0),"") | K36: =_xlfn.XLOOKUP(L36,POPULAÇÃO!D:D,POPULAÇÃO!C:C) -> 0 | Q36: =IFERROR(VLOOKUP(O36,Parametros!J:K,2,0),"") | T36: =IF(R36="","",IF(R36="digital",W36&"""- "&V36&" ins/dia",TEXT(AA36,"0,00")&" x "&TEXT(AB36,"0,00")&"m")) | Y36: =IFERROR(86400/W36/24*X36,0) -> 0 | Z36: =+U36*V36 -> 0 | AF36: =IFERROR(VLOOKUP(AE36,Parametros!E:F,2,0),0) -> 0 | AJ36: =IF(AG36="","",AH36-AG36+1) | CL36: =IFERROR(COUNT(AK36:CJ36)/CK36,0) -> 0 | CM36: =IFERROR(SUM(AK36:CJ36)/CK36,0) -> 0 | CQ36: =IF(AE36="diária",CP36*AJ36*U36,IF(AJ36>AF36,CP36,AJ36/AF36*CP36)*U36) -> 0 | CR36: =IF(CN36="","0",IF(CN36="Faces",CQ36*CM36,CQ36*CL36)) -> 0 | CS36: 0.58 | CT36: =CP36*(1-CS36) -> 0 | CU36: =CR36*(1-CS36) -> 0 | CV36: =CU36*0.8 -> 0 | CW36: =IF(H36="","",IFERROR(VLOOKUP(H36,Parametros!B:C,2,0),0)) | CX36: =EG36 -> 0 | CY36: =IF(OR(CX36=0,CX36="Sem base de dados"),0,CV36/CX36*1000) -> 0 | DA36: =DK36 -> 0 | DB36: =DW36 -> 0 | DD36: =IF(AG36="",0,EDATE(DATE(YEAR(AG36),MONTH(AG36),1),5)) -> 0 | DE36: 2025 | DJ36: 800 | DK36: =DJ36*DI36*DH36 -> 0 | DM36: =IF(R36="Digital",0,IF(SUM(AK36:CJ36)=0,0,LARGE(AK36:CJ36,1))) -> 0 | DP36: =ROUNDUP(DN36*DM36*(1+DO36),0) -> 0 | DU36: =PRODUCT(DP36:DT36) -> 0 | DW36: =(DU36+DV36) -> 0 | DZ36: =SUMIFS('Mediana dos Impactos'!D:D,'Mediana dos Impactos'!C:C,OOH!O36,'Mediana dos Impactos'!B:B,OOH!L36) -> 0 | EB36: =AJ36 | EC36: =IFERROR(IF(DZ36<>"",DZ36/7*EB36,$EA36/30*EB36),0) -> 0 | ED36: =IF(DY36="",0,IF(DY36="Face",CM36,CL36)) -> 0 | EE36: =IF(DY36="Sem base de dados",DY36,EC36*ED36) -> 0 | EF36: =IF(R36="digital",(EI36*EH36),EJ36*EH36) -> 0 | EG36: =+EE36*EF36 -> 0 | EH36: =IFERROR(IF(N36="via pública",VLOOKUP($O36,Parametros!$J:$L,3,0),VLOOKUP(N36,Parametros!V:W,2,0)),0) -> 0 | EI36: =IFERROR(Z36/Y36,0) -> 0 | EJ36: =IFERROR(VLOOKUP(AC36,Parametros!AL:AM,2,0),1) -> 1 | EM36: =SUM(EP36:GO36) -> 0 | EN36: =EM36=CV36 -> TRUE | EP36: {=_xlfn.IFS(AK36="","",AK36,$CV36/$CM36/$CK36*AK36)} | EQ36: {=_xlfn.IFS(AL36="","",AL36,$CV36/$CM36/$CK36*AL36)} | ER36: {=_xlfn.IFS(AM36="","",AM36,$CV36/$CM36/$CK36*AM36)} | ES36: {=_xlfn.IFS(AN36="","",AN36,$CV36/$CM36/$CK36*AN36)} | ET36: {=_xlfn.IFS(AO36="","",AO36,$CV36/$CM36/$CK36*AO36)} | EU36: {=_xlfn.IFS(AP36="","",AP36,$CV36/$CM36/$CK36*AP36)} | EV36: {=_xlfn.IFS(AQ36="","",AQ36,$CV36/$CM36/$CK36*AQ36)} | EW36: {=_xlfn.IFS(AR36="","",AR36,$CV36/$CM36/$CK36*AR36)} | ... GO36: {=_xlfn.IFS(CJ36="","",CJ36,$CV36/$CM36/$CK36*CJ36)} | GQ36: =SUM(EP36:ES36) -> 0 | GR36: =SUM(ET36:EW36) -> 0 | GS36: =SUM(EX36:FB36) -> 0 | GT36: =SUM(FC36:FF36) -> 0 | GU36: =SUM(FG36:FK36) -> 0 | GV36: =SUM(FL36:FO36) -> 0 | GW36: =SUM(FP36:FS36) -> 0 | GX36: =SUM(FT36:FX36) -> 0 | GY36: =SUM(FY36:GB36) -> 0 | GZ36: =SUM(GC36:GF36) -> 0 | HA36: =SUM(GG36:GK36) -> 0 | HB36: =SUM(GL36:GO36) -> 0
C37: =+C36+1 -> 35 | D37: 0 | E37: 0 | F37: 0 | G37: =IF(M37="","",IF(ISERROR(VLOOKUP(M37,Parametros!AI:AJ,2,0)),"Demais OOH",VLOOKUP(M37,Parametros!AI:AJ,2,0))) | I37: - | J37: =IFERROR(VLOOKUP(K37,'GEOS AMBEV'!B:C,2,0),"") | K37: =_xlfn.XLOOKUP(L37,POPULAÇÃO!D:D,POPULAÇÃO!C:C) -> 0 | Q37: =IFERROR(VLOOKUP(O37,Parametros!J:K,2,0),"") | T37: =IF(R37="","",IF(R37="digital",W37&"""- "&V37&" ins/dia",TEXT(AA37,"0,00")&" x "&TEXT(AB37,"0,00")&"m")) | Y37: =IFERROR(86400/W37/24*X37,0) -> 0 | Z37: =+U37*V37 -> 0 | AF37: =IFERROR(VLOOKUP(AE37,Parametros!E:F,2,0),0) -> 0 | AJ37: =IF(AG37="","",AH37-AG37+1) | CL37: =IFERROR(COUNT(AK37:CJ37)/CK37,0) -> 0 | CM37: =IFERROR(SUM(AK37:CJ37)/CK37,0) -> 0 | CQ37: =IF(AE37="diária",CP37*AJ37*U37,IF(AJ37>AF37,CP37,AJ37/AF37*CP37)*U37) -> 0 | CR37: =IF(CN37="","0",IF(CN37="Faces",CQ37*CM37,CQ37*CL37)) -> 0 | CS37: 0.58 | CT37: =CP37*(1-CS37) -> 0 | CU37: =CR37*(1-CS37) -> 0 | CV37: =CU37*0.8 -> 0 | CW37: =IF(H37="","",IFERROR(VLOOKUP(H37,Parametros!B:C,2,0),0)) | CX37: =EG37 -> 0 | CY37: =IF(OR(CX37=0,CX37="Sem base de dados"),0,CV37/CX37*1000) -> 0 | DA37: =DK37 -> 0 | DB37: =DW37 -> 0 | DD37: =IF(AG37="",0,EDATE(DATE(YEAR(AG37),MONTH(AG37),1),5)) -> 0 | DE37: 2025 | DJ37: 800 | DK37: =DJ37*DI37*DH37 -> 0 | DM37: =IF(R37="Digital",0,IF(SUM(AK37:CJ37)=0,0,LARGE(AK37:CJ37,1))) -> 0 | DP37: =ROUNDUP(DN37*DM37*(1+DO37),0) -> 0 | DU37: =PRODUCT(DP37:DT37) -> 0 | DW37: =(DU37+DV37) -> 0 | DZ37: =SUMIFS('Mediana dos Impactos'!D:D,'Mediana dos Impactos'!C:C,OOH!O37,'Mediana dos Impactos'!B:B,OOH!L37) -> 0 | EB37: =AJ37 | EC37: =IFERROR(IF(DZ37<>"",DZ37/7*EB37,$EA37/30*EB37),0) -> 0 | ED37: =IF(DY37="",0,IF(DY37="Face",CM37,CL37)) -> 0 | EE37: =IF(DY37="Sem base de dados",DY37,EC37*ED37) -> 0 | EF37: =IF(R37="digital",(EI37*EH37),EJ37*EH37) -> 0 | EG37: =+EE37*EF37 -> 0 | EH37: =IFERROR(IF(N37="via pública",VLOOKUP($O37,Parametros!$J:$L,3,0),VLOOKUP(N37,Parametros!V:W,2,0)),0) -> 0 | EI37: =IFERROR(Z37/Y37,0) -> 0 | EJ37: =IFERROR(VLOOKUP(AC37,Parametros!AL:AM,2,0),1) -> 1 | EM37: =SUM(EP37:GO37) -> 0 | EN37: =EM37=CV37 -> TRUE | EP37: {=_xlfn.IFS(AK37="","",AK37,$CV37/$CM37/$CK37*AK37)} | EQ37: {=_xlfn.IFS(AL37="","",AL37,$CV37/$CM37/$CK37*AL37)} | ER37: {=_xlfn.IFS(AM37="","",AM37,$CV37/$CM37/$CK37*AM37)} | ES37: {=_xlfn.IFS(AN37="","",AN37,$CV37/$CM37/$CK37*AN37)} | ET37: {=_xlfn.IFS(AO37="","",AO37,$CV37/$CM37/$CK37*AO37)} | EU37: {=_xlfn.IFS(AP37="","",AP37,$CV37/$CM37/$CK37*AP37)} | EV37: {=_xlfn.IFS(AQ37="","",AQ37,$CV37/$CM37/$CK37*AQ37)} | EW37: {=_xlfn.IFS(AR37="","",AR37,$CV37/$CM37/$CK37*AR37)} | ... GO37: {=_xlfn.IFS(CJ37="","",CJ37,$CV37/$CM37/$CK37*CJ37)} | GQ37: =SUM(EP37:ES37) -> 0 | GR37: =SUM(ET37:EW37) -> 0 | GS37: =SUM(EX37:FB37) -> 0 | GT37: =SUM(FC37:FF37) -> 0 | GU37: =SUM(FG37:FK37) -> 0 | GV37: =SUM(FL37:FO37) -> 0 | GW37: =SUM(FP37:FS37) -> 0 | GX37: =SUM(FT37:FX37) -> 0 | GY37: =SUM(FY37:GB37) -> 0 | GZ37: =SUM(GC37:GF37) -> 0 | HA37: =SUM(GG37:GK37) -> 0 | HB37: =SUM(GL37:GO37) -> 0
C38: =+C37+1 -> 36 | D38: 0 | E38: 0 | F38: 0 | G38: =IF(M38="","",IF(ISERROR(VLOOKUP(M38,Parametros!AI:AJ,2,0)),"Demais OOH",VLOOKUP(M38,Parametros!AI:AJ,2,0))) | I38: - | J38: =IFERROR(VLOOKUP(K38,'GEOS AMBEV'!B:C,2,0),"") | K38: =_xlfn.XLOOKUP(L38,POPULAÇÃO!D:D,POPULAÇÃO!C:C) -> 0 | Q38: =IFERROR(VLOOKUP(O38,Parametros!J:K,2,0),"") | T38: =IF(R38="","",IF(R38="digital",W38&"""- "&V38&" ins/dia",TEXT(AA38,"0,00")&" x "&TEXT(AB38,"0,00")&"m")) | Y38: =IFERROR(86400/W38/24*X38,0) -> 0 | Z38: =+U38*V38 -> 0 | AF38: =IFERROR(VLOOKUP(AE38,Parametros!E:F,2,0),0) -> 0 | AJ38: =IF(AG38="","",AH38-AG38+1) | CL38: =IFERROR(COUNT(AK38:CJ38)/CK38,0) -> 0 | CM38: =IFERROR(SUM(AK38:CJ38)/CK38,0) -> 0 | CQ38: =IF(AE38="diária",CP38*AJ38*U38,IF(AJ38>AF38,CP38,AJ38/AF38*CP38)*U38) -> 0 | CR38: =IF(CN38="","0",IF(CN38="Faces",CQ38*CM38,CQ38*CL38)) -> 0 | CS38: 0.8 | CT38: =CP38*(1-CS38) -> 0 | CU38: =CR38*(1-CS38) -> 0 | CV38: =CU38*0.8 -> 0 | CW38: =IF(H38="","",IFERROR(VLOOKUP(H38,Parametros!B:C,2,0),0)) | CX38: =EG38 -> 0 | CY38: =IF(OR(CX38=0,CX38="Sem base de dados"),0,CV38/CX38*1000) -> 0 | DA38: =DK38 -> 0 | DB38: =DW38 -> 0 | DD38: =IF(AG38="",0,EDATE(DATE(YEAR(AG38),MONTH(AG38),1),5)) -> 0 | DE38: 2025 | DJ38: 800 | DK38: =DJ38*DI38*DH38 -> 0 | DM38: =IF(R38="Digital",0,IF(SUM(AK38:CJ38)=0,0,LARGE(AK38:CJ38,1))) -> 0 | DP38: =ROUNDUP(DN38*DM38*(1+DO38),0) -> 0 | DU38: =PRODUCT(DP38:DT38) -> 0 | DW38: =(DU38+DV38) -> 0 | DZ38: =SUMIFS('Mediana dos Impactos'!D:D,'Mediana dos Impactos'!C:C,OOH!O38,'Mediana dos Impactos'!B:B,OOH!L38) -> 0 | EB38: =AJ38 | EC38: =IFERROR(IF(DZ38<>"",DZ38/7*EB38,$EA38/30*EB38),0) -> 0 | ED38: =IF(DY38="",0,IF(DY38="Face",CM38,CL38)) -> 0 | EE38: =IF(DY38="Sem base de dados",DY38,EC38*ED38) -> 0 | EF38: =IF(R38="digital",(EI38*EH38),EJ38*EH38) -> 0 | EG38: =+EE38*EF38 -> 0 | EH38: =IFERROR(IF(N38="via pública",VLOOKUP($O38,Parametros!$J:$L,3,0),VLOOKUP(N38,Parametros!V:W,2,0)),0) -> 0 | EI38: =IFERROR(Z38/Y38,0) -> 0 | EJ38: =IFERROR(VLOOKUP(AC38,Parametros!AL:AM,2,0),1) -> 1 | EM38: =SUM(EP38:GO38) -> 0 | EN38: =EM38=CV38 -> TRUE | EP38: {=_xlfn.IFS(AK38="","",AK38,$CV38/$CM38/$CK38*AK38)} | EQ38: {=_xlfn.IFS(AL38="","",AL38,$CV38/$CM38/$CK38*AL38)} | ER38: {=_xlfn.IFS(AM38="","",AM38,$CV38/$CM38/$CK38*AM38)} | ES38: {=_xlfn.IFS(AN38="","",AN38,$CV38/$CM38/$CK38*AN38)} | ET38: {=_xlfn.IFS(AO38="","",AO38,$CV38/$CM38/$CK38*AO38)} | EU38: {=_xlfn.IFS(AP38="","",AP38,$CV38/$CM38/$CK38*AP38)} | EV38: {=_xlfn.IFS(AQ38="","",AQ38,$CV38/$CM38/$CK38*AQ38)} | EW38: {=_xlfn.IFS(AR38="","",AR38,$CV38/$CM38/$CK38*AR38)} | ... GO38: {=_xlfn.IFS(CJ38="","",CJ38,$CV38/$CM38/$CK38*CJ38)} | GQ38: =SUM(EP38:ES38) -> 0 | GR38: =SUM(ET38:EW38) -> 0 | GS38: =SUM(EX38:FB38) -> 0 | GT38: =SUM(FC38:FF38) -> 0 | GU38: =SUM(FG38:FK38) -> 0 | GV38: =SUM(FL38:FO38) -> 0 | GW38: =SUM(FP38:FS38) -> 0 | GX38: =SUM(FT38:FX38) -> 0 | GY38: =SUM(FY38:GB38) -> 0 | GZ38: =SUM(GC38:GF38) -> 0 | HA38: =SUM(GG38:GK38) -> 0 | HB38: =SUM(GL38:GO38) -> 0
C39: =+C38+1 -> 37 | D39: 0 | E39: 0 | F39: 0 | G39: =IF(M39="","",IF(ISERROR(VLOOKUP(M39,Parametros!AI:AJ,2,0)),"Demais OOH",VLOOKUP(M39,Parametros!AI:AJ,2,0))) | I39: - | J39: =IFERROR(VLOOKUP(K39,'GEOS AMBEV'!B:C,2,0),"") | K39: =_xlfn.XLOOKUP(L39,POPULAÇÃO!D:D,POPULAÇÃO!C:C) -> 0 | Q39: =IFERROR(VLOOKUP(O39,Parametros!J:K,2,0),"") | T39: =IF(R39="","",IF(R39="digital",W39&"""- "&V39&" ins/dia",TEXT(AA39,"0,00")&" x "&TEXT(AB39,"0,00")&"m")) | Y39: =IFERROR(86400/W39/24*X39,0) -> 0 | Z39: =+U39*V39 -> 0 | AF39: =IFERROR(VLOOKUP(AE39,Parametros!E:F,2,0),0) -> 0 | AJ39: =IF(AG39="","",AH39-AG39+1) | CL39: =IFERROR(COUNT(AK39:CJ39)/CK39,0) -> 0 | CM39: =IFERROR(SUM(AK39:CJ39)/CK39,0) -> 0 | CQ39: =IF(AE39="diária",CP39*AJ39*U39,IF(AJ39>AF39,CP39,AJ39/AF39*CP39)*U39) -> 0 | CR39: =IF(CN39="","0",IF(CN39="Faces",CQ39*CM39,CQ39*CL39)) -> 0 | CS39: 0.8 | CT39: =CP39*(1-CS39) -> 0 | CU39: =CR39*(1-CS39) -> 0 | CV39: =CU39*0.8 -> 0 | CW39: =IF(H39="","",IFERROR(VLOOKUP(H39,Parametros!B:C,2,0),0)) | CX39: =EG39 -> 0 | CY39: =IF(OR(CX39=0,CX39="Sem base de dados"),0,CV39/CX39*1000) -> 0 | DA39: =DK39 -> 0 | DB39: =DW39 -> 0 | DD39: =IF(AG39="",0,EDATE(DATE(YEAR(AG39),MONTH(AG39),1),5)) -> 0 | DE39: 2025 | DJ39: 800 | DK39: =DJ39*DI39*DH39 -> 0 | DM39: =IF(R39="Digital",0,IF(SUM(AK39:CJ39)=0,0,LARGE(AK39:CJ39,1))) -> 0 | DP39: =ROUNDUP(DN39*DM39*(1+DO39),0) -> 0 | DU39: =PRODUCT(DP39:DT39) -> 0 | DW39: =(DU39+DV39) -> 0 | DZ39: =SUMIFS('Mediana dos Impactos'!D:D,'Mediana dos Impactos'!C:C,OOH!O39,'Mediana dos Impactos'!B:B,OOH!L39) -> 0 | EB39: =AJ39 | EC39: =IFERROR(IF(DZ39<>"",DZ39/7*EB39,$EA39/30*EB39),0) -> 0 | ED39: =IF(DY39="",0,IF(DY39="Face",CM39,CL39)) -> 0 | EE39: =IF(DY39="Sem base de dados",DY39,EC39*ED39) -> 0 | EF39: =IF(R39="digital",(EI39*EH39),EJ39*EH39) -> 0 | EG39: =+EE39*EF39 -> 0 | EH39: =IFERROR(IF(N39="via pública",VLOOKUP($O39,Parametros!$J:$L,3,0),VLOOKUP(N39,Parametros!V:W,2,0)),0) -> 0 | EI39: =IFERROR(Z39/Y39,0) -> 0 | EJ39: =IFERROR(VLOOKUP(AC39,Parametros!AL:AM,2,0),1) -> 1 | EM39: =SUM(EP39:GO39) -> 0 | EN39: =EM39=CV39 -> TRUE | EP39: {=_xlfn.IFS(AK39="","",AK39,$CV39/$CM39/$CK39*AK39)} | EQ39: {=_xlfn.IFS(AL39="","",AL39,$CV39/$CM39/$CK39*AL39)} | ER39: {=_xlfn.IFS(AM39="","",AM39,$CV39/$CM39/$CK39*AM39)} | ES39: {=_xlfn.IFS(AN39="","",AN39,$CV39/$CM39/$CK39*AN39)} | ET39: {=_xlfn.IFS(AO39="","",AO39,$CV39/$CM39/$CK39*AO39)} | EU39: {=_xlfn.IFS(AP39="","",AP39,$CV39/$CM39/$CK39*AP39)} | EV39: {=_xlfn.IFS(AQ39="","",AQ39,$CV39/$CM39/$CK39*AQ39)} | EW39: {=_xlfn.IFS(AR39="","",AR39,$CV39/$CM39/$CK39*AR39)} | ... GO39: {=_xlfn.IFS(CJ39="","",CJ39,$CV39/$CM39/$CK39*CJ39)} | GQ39: =SUM(EP39:ES39) -> 0 | GR39: =SUM(ET39:EW39) -> 0 | GS39: =SUM(EX39:FB39) -> 0 | GT39: =SUM(FC39:FF39) -> 0 | GU39: =SUM(FG39:FK39) -> 0 | GV39: =SUM(FL39:FO39) -> 0 | GW39: =SUM(FP39:FS39) -> 0 | GX39: =SUM(FT39:FX39) -> 0 | GY39: =SUM(FY39:GB39) -> 0 | GZ39: =SUM(GC39:GF39) -> 0 | HA39: =SUM(GG39:GK39) -> 0 | HB39: =SUM(GL39:GO39) -> 0
A40: tt | C40: =+C39+1 -> 38 | G40: =IF(M40="","",IF(ISERROR(VLOOKUP(M40,Parametros!AI:AJ,2,0)),"Demais OOH",VLOOKUP(M40,Parametros!AI:AJ,2,0))) | J40: =IFERROR(VLOOKUP(K40,'GEOS AMBEV'!B:C,2,0),"") | Q40: =IFERROR(VLOOKUP(O40,Parametros!J:K,2,0),"") | T40: =IF(R40="","",IF(R40="digital",W40&"""- "&V40&" ins/dia",TEXT(AA40,"0,00")&" x "&TEXT(AB40,"0,00")&"m")) | Y40: =IFERROR(86400/W40/24*X40,0) -> 0 | Z40: =+U40*V40 -> 0 | AJ40: =IF(AG40="","",AH40-AG40+1) | BT40: =SUM(BT35:BT39) -> 0 | BU40: =SUM(BU35:BU39) -> 0 | BV40: =SUM(BV35:BV39) -> 0 | BW40: =SUM(BW35:BW39) -> 0 | BX40: =SUM(BX35:BX39) -> 0 | BY40: =SUM(BY35:BY39) -> 0 | BZ40: =SUM(BZ35:BZ39) -> 0 | CA40: =SUM(CA35:CA39) -> 0 | ... CJ40: =SUM(CJ35:CJ39) -> 0 | CT40: =SUM(CT35:CT39) -> 0 | CU40: =SUM(CU35:CU39) -> 0 | CV40: =SUM(CV35:CV39) -> 0 | CW40: =IF(H40="","",IFERROR(VLOOKUP(H40,Parametros!B:C,2,0),0)) | CX40: =SUM(CX35:CX39) -> 0 | DA40: =SUM(DA35:DA39) -> 0 | DB40: =SUM(DB35:DB39) -> 0 | DK40: =DJ40*DI40*DH40 -> 0 | DM40: =IF(R40="Digital",0,IF(SUM(AK40:CJ40)=0,0,LARGE(AK40:CJ40,1))) -> 0 | DP40: =ROUNDUP(DN40*DM40*(1+DO40),0) -> 0 | DU40: =PRODUCT(DP40:DT40) -> 0 | DW40: =(DU40+DV40) -> 0 | EB40: =AJ40 | EC40: =IFERROR(IF(DZ40<>"",DZ40/7*EB40,$EA40/30*EB40),0) -> 0 | ED40: =IF(DY40="",0,IF(DY40="Face",CM40,CL40)) -> 0 | EE40: =IF(DY40="Sem base de dados",DY40,EC40*ED40) -> 0 | EI40: =IFERROR(Z40/Y40,0) -> 0 | EM40: =SUM(EP40:GO40) -> 0 | EN40: =EM40=CV40 -> TRUE | EP40: {=_xlfn.IFS(AK40="","",AK40,$CV40/$CM40/$CK40*AK40)} | EQ40: {=_xlfn.IFS(AL40="","",AL40,$CV40/$CM40/$CK40*AL40)} | ER40: {=_xlfn.IFS(AM40="","",AM40,$CV40/$CM40/$CK40*AM40)} | ES40: {=_xlfn.IFS(AN40="","",AN40,$CV40/$CM40/$CK40*AN40)} | ET40: {=_xlfn.IFS(AO40="","",AO40,$CV40/$CM40/$CK40*AO40)} | EU40: {=_xlfn.IFS(AP40="","",AP40,$CV40/$CM40/$CK40*AP40)} | EV40: {=_xlfn.IFS(AQ40="","",AQ40,$CV40/$CM40/$CK40*AQ40)} | EW40: {=_xlfn.IFS(AR40="","",AR40,$CV40/$CM40/$CK40*AR40)} | ... FX40: {=_xlfn.IFS(BS40="","",BS40,$CV40/$CM40/$CK40*BS40)} | FY40: =SUM(FY35:FY39) -> 0 | FZ40: =SUM(FZ35:FZ39) -> 0 | GA40: =SUM(GA35:GA39) -> 0 | GB40: =SUM(GB35:GB39) -> 0 | GC40: =SUM(GC35:GC39) -> 0 | GD40: =SUM(GD35:GD39) -> 0 | GE40: =SUM(GE35:GE39) -> 0 | GF40: =SUM(GF35:GF39) -> 0 | ... GO40: =SUM(GO35:GO39) -> 0 | GQ40: =SUM(EP40:ES40) -> 0 | GR40: =SUM(ET40:EW40) -> 0 | GS40: =SUM(EX40:FB40) -> 0 | GT40: =SUM(FC40:FF40) -> 0 | GU40: =SUM(FG40:FK40) -> 0 | GV40: =SUM(FL40:FO40) -> 0 | GW40: =SUM(FP40:FS40) -> 0 | GX40: =SUM(FT40:FX40) -> 0 | GY40: =SUM(FY40:GB40) -> 0 | GZ40: =SUM(GC40:GF40) -> 0 | HA40: =SUM(GG40:GK40) -> 0 | HB40: =SUM(GL40:GO40) -> 0
C41: =+C40+1 -> 39 | D41: TOTAL GERAL | E41: TOTAL GERAL | G41: =IF(M41="","",IF(ISERROR(VLOOKUP(M41,Parametros!AI:AJ,2,0)),"Demais OOH",VLOOKUP(M41,Parametros!AI:AJ,2,0))) | J41: =IFERROR(VLOOKUP(K41,'GEOS AMBEV'!B:C,2,0),"") | Q41: =IFERROR(VLOOKUP(O41,Parametros!J:K,2,0),"") | T41: =IF(R41="","",IF(R41="digital",W41&"""- "&V41&" ins/dia",TEXT(AA41,"0,00")&" x "&TEXT(AB41,"0,00")&"m")) | AJ41: =IF(AG41="","",AH41-AG41+1) | AK41: =SUMIFS(AK3:AK40,$A$3:$A$40,"tt") -> 0 | AL41: =SUMIFS(AL3:AL40,$A$3:$A$40,"tt") -> 0 | AM41: =SUMIFS(AM3:AM40,$A$3:$A$40,"tt") -> 0 | AN41: =SUMIFS(AN3:AN40,$A$3:$A$40,"tt") -> 0 | AO41: =SUMIFS(AO3:AO40,$A$3:$A$40,"tt") -> 0 | AP41: =SUMIFS(AP3:AP40,$A$3:$A$40,"tt") -> 0 | AQ41: =SUMIFS(AQ3:AQ40,$A$3:$A$40,"tt") -> 0 | AR41: =SUMIFS(AR3:AR40,$A$3:$A$40,"tt") -> 0 | ... CJ41: =SUMIFS(CJ3:CJ40,$A$3:$A$40,"tt") -> 0 | CL41: =SUMIFS(CL3:CL40,$A$3:$A$40,"tt") -> 0 | CM41: =SUMIFS(CM3:CM40,$A$3:$A$40,"tt") -> 0 | CT41: =SUMIFS(CT3:CT40,$A$3:$A$40,"tt") -> 0 | CU41: =SUMIFS(CU3:CU40,$A$3:$A$40,"tt") -> 0 | CV41: =SUMIFS(CV3:CV40,$A$3:$A$40,"tt") -> 0 | CW41: =IF(H41="","",IFERROR(VLOOKUP(H41,Parametros!B:C,2,0),0)) | CX41: =SUMIFS(CX3:CX40,$A$3:$A$40,"tt") -> 0 | DA41: =SUMIFS(DA3:DA40,$A$3:$A$40,"tt") -> 0 | DB41: =SUMIFS(DB3:DB40,$A$3:$A$40,"tt") -> 0 | DK41: =SUMIFS(DK3:DK40,$A$3:$A$40,"tt") -> 0 | DM41: =SUMIFS(DM3:DM40,$A$3:$A$40,"tt") -> 0 | DP41: =SUMIFS(DP3:DP40,$A$3:$A$40,"tt") -> 0 | DU41: =SUMIFS(DU3:DU40,$A$3:$A$40,"tt") -> 0 | DW41: =SUMIFS(DW3:DW40,$A$3:$A$40,"tt") -> 0 | EB41: =AJ41 | EC41: =SUMIFS(EC3:EC40,$A$3:$A$40,"tt") -> 0 | ED41: =SUMIFS(ED3:ED40,$A$3:$A$40,"tt") -> 0 | EE41: =SUMIFS(EE3:EE40,$A$3:$A$40,"tt") -> 0 | EF41: =SUMIFS(EF3:EF40,$A$3:$A$40,"tt") -> 0 | EG41: =SUMIFS(EG3:EG40,$A$3:$A$40,"tt") -> 0 | EH41: =SUMIFS(EH3:EH40,$A$3:$A$40,"tt") -> 0 | EI41: =IFERROR(Z41/Y41,0) -> 0 | EM41: =SUMIFS(EM3:EM40,$A$3:$A$40,"tt") -> 0 | EN41: =EM41=CV41 -> TRUE | EP41: =SUMIFS(EP3:EP40,$A$3:$A$40,"tt") -> 0 | EQ41: =SUMIFS(EQ3:EQ40,$A$3:$A$40,"tt") -> 0 | ER41: =SUMIFS(ER3:ER40,$A$3:$A$40,"tt") -> 0 | ES41: =SUMIFS(ES3:ES40,$A$3:$A$40,"tt") -> 0 | ET41: =SUMIFS(ET3:ET40,$A$3:$A$40,"tt") -> 0 | EU41: =SUMIFS(EU3:EU40,$A$3:$A$40,"tt") -> 0 | EV41: =SUMIFS(EV3:EV40,$A$3:$A$40,"tt") -> 0 | EW41: =SUMIFS(EW3:EW40,$A$3:$A$40,"tt") -> 0 | ... HB41: =SUMIFS(HB3:HB40,$A$3:$A$40,"tt") -> 0 | HC41: =SUM(GQ41:HB41) -> 0 | HD41: =HC41=CV41 -> TRUE
C42: =+C41+1 -> 40
C43: =+C42+1 -> 41

Sheet Mediana dos Impactos
B2: Cidade | C2: Tipo de mídia | D2: Mediana do fluxo de passantes
B3: Abadia de Goiás | C3: Frontlight | D3: 38304
B4: Abadia de Goiás | C4: Outdoor papel simples | D4: 38304
B5: Abadia de Goiás Total | D5: 38304
B6: Abreu e Lima | C6: Outdoor lonado | D6: 181657
B7: Abreu e Lima | C7: Outdoor papel simples | D7: 128656
B8: Abreu e Lima Total | D8: 155157
B9: Agrestina | C9: Outdoor papel simples | D9: 363552
B10: Agrestina Total | D10: 363552
B11: Alagoinhas | C11: Outdoor lonado | D11: 104076
B12: Alagoinhas | C12: Outdoor papel simples | D12: 115943
B13: Alagoinhas | C13: Painel de LED | D13: 171351
B14: Alagoinhas Total | D14: 104209
B15: Alambari | C15: Painel de LED | D15: 9868
B16: Alambari Total | D16: 9868
B17: Alcobaça | C17: Outdoor lonado | D17: 29436
B18: Alcobaça Total | D18: 29436
B19: Amargosa | C19: Outdoor lonado | D19: 39258
B20: Amargosa | C20: Outdoor lonado simples | D20: 35416
B21: Amargosa Total | D21: 37821
B22: Amélia Rodrigues | C22: Frontlight | D22: 48596
B23: Amélia Rodrigues | C23: Outdoor lonado | D23: 38975
B24: Amélia Rodrigues Total | D24: 48596
B25: América Dourada | C25: Outdoor lonado | D25: 13514
B26: América Dourada Total | D26: 13514
B27: Americana | C27: Frontlight | D27: 126761
B28: Americana | C28: Outdoor papel simples | D28: 56625
B29: Americana Total | D29: 59466
B30: Amparo | C30: Painel de LED | D30: 325395
B31: Amparo Total | D31: 325395
B32: Anagé | C32: Outdoor lonado | D32: 35765
B33: Anagé Total | D33: 35765
B34: Ananindeua | C34: Frontlight | D34: 311466
B35: Ananindeua | C35: MUB estático | D35: 651004
B36: Ananindeua | C36: Outdoor papel simples | D36: 311466
B37: Ananindeua | C37: Painel de LED | D37: 329615
B38: Ananindeua Total | D38: 311466
B39: Anápolis | C39: Frontlight | D39: 206305
B40: Anápolis | C40: Outdoor lonado | D40: 206305
B41: Anápolis | C41: Outdoor papel simples | D41: 106792
B42: Anápolis | C42: Painel de LED | D42: 129533
B43: Anápolis Total | D43: 196428
B44: Andaraí | C44: Outdoor lonado | D44: 12226
B45: Andaraí Total | D45: 12226
B46: Antônio Gonçalves | C46: Outdoor lonado | D46: 580
B47: Antônio Gonçalves Total | D47: 580
B48: Aparecida de Goiânia | C48: Edifício comercial | D48: 2857
B49: Aparecida de Goiânia | C49: Edifício residencial | D49: 3383
B50: Aparecida de Goiânia | C50: Frontlight | D50: 166190
B51: Aparecida de Goiânia | C51: Painel de LED | D51: 184792
B52: Aparecida de Goiânia Total | D52: 105814
B53: Aquiraz | C53: Frontlight | D53: 48356
B54: Aquiraz | C54: MUB digital | D54: 22735
B55: Aquiraz | C55: Outdoor lonado simples | D55: 36151
B56: Aquiraz | C56: Outdoor papel simples | D56: 21523
B57: Aquiraz | C57: Painel de LED | D57: 23947
B58: Aquiraz Total | D58: 23947
B59: Aracaju | C59: Frontlight | D59: 497996
B60: Aracaju | C60: MUB estático | D60: 497996
B61: Aracaju | C61: Outdoor lonado simples | D61: 302819
B62: Aracaju | C62: Outdoor papel simples | D62: 497996
B63: Aracaju | C63: Painel de LED | D63: 487973
B64: Aracaju Total | D64: 497996
B65: Araçás | C65: Outdoor lonado | D65: 27997
B66: Araçás Total | D66: 27997
B67: Aracati | C67: Outdoor papel simples | D67: 45774
B68: Aracati Total | D68: 45774
B69: Aracatu | C69: Outdoor lonado | D69: 18448
B70: Aracatu Total | D70: 18448
B71: Araçatuba | C71: Outdoor papel simples | D71: 64980
B72: Araçatuba Total | D72: 64980
B73: Araci | C73: Outdoor lonado | D73: 33417
B74: Araci Total | D74: 33417
B75: Aramari | C75: Outdoor lonado | D75: 19758
B76: Aramari Total | D76: 19758
B77: Aramina | C77: Outdoor lonado | D77: 13070
B78: Aramina Total | D78: 13070
B79: Arapiraca | C79: Abrigo de ônibus estático | D79: 46430
B80: Arapiraca | C80: Outdoor papel simples | D80: 87888
B81: Arapiraca Total | D81: 46799
B82: Arapongas | C82: Outdoor adesivado | D82: 97709
B83: Arapongas | C83: Outdoor lonado | D83: 47564
B84: Arapongas | C84: Outdoor lonado simples | D84: 47564
B85: Arapongas Total | D85: 53226
B86: Araquari | C86: Frontlight | D86: 48898
B87: Araquari | C87: Mega top | D87: 48898
B88: Araquari | C88: Painel de estrada estático | D88: 48898
B89: Araquari Total | D89: 48898
B90: Araraquara | C90: Painel de LED | D90: 115371
B91: Araraquara Total | D91: 115371
B92: Araruama | C92: Painel de LED | D92: 91164
B93: Araruama Total | D93: 91164
B94: Araucária | C94: Mega top | D94: 99887
B95: Araucária | C95: Topsight | D95: 99887
B96: Araucária Total | D96: 99887
B97: Arcoverde | C97: Outdoor lonado simples | D97: 56281
B98: Arcoverde | C98: Outdoor papel simples | D98: 82106
B99: Arcoverde Total | D99: 82106
B100: Areia | C100: Outdoor papel simples | D100: 10148
B101: Areia Total | D101: 10148
...

Sheet GEOS AMBEV
A1: ESTADOS | C1: GEOS
A2: São Paulo | B2: SP | C2: GEO SP
A3: Rio de Janeiro | B3: RJ | C3: GEO RJ / ES
A4: Espírito Santo | B4: ES | C4: GEO RJ / ES
A5: Minas Gerais | B5: MG | C5: GEO MG
A6: Rio Grande do Sul | B6: RS | C6: GEO SUL
A7: Santa Catarina | B7: SC | C7: GEO SUL
A8: Paraná | B8: PR | C8: GEO SUL
A9: Alagoas | B9: AL | C9: GEO NE
A10: Bahia | B10: BA | C10: GEO NE
A11: Paraiba | B11: PB | C11: GEO NE
A12: Pernambuco | B12: PE | C12: GEO NE
A13: Sergipe | B13: SE | C13: GEO NE
... A28: Rondônia | B28: RO | C28: GEO CO

Sheet POPULAÇÃO
A1: UF&Municicio | C1: Estado | D1: Municípios | E1: População
B2: =C2&D2 -> SPSão Paulo | C2: SP | D2: São Paulo | E2: 12396372
B3: =C3&D3 -> RJRio de Janeiro | C3: RJ | D3: Rio de Janeiro | E3: 6775561
B4: =C4&D4 -> DFBrasília | C4: DF | D4: Brasília | E4: 3094325
B5: =C5&D5 -> BASalvador | C5: BA | D5: Salvador | E5: 2900319
B6: =C6&D6 -> CEFortaleza | C6: CE | D6: Fortaleza | E6: 2703391
B7: =C7&D7 -> MGBelo Horizonte | C7: MG | D7: Belo Horizonte | E7: 2530701
A8: =_xlfn.CONCAT(C8,D8) -> AMManaus | B8: =C8&D8 -> AMManaus | C8: AM | D8: Manaus | E8: 2255903
B9: =C9&D9 -> PRCuritiba | C9: PR | D9: Curitiba | E9: 1963726
B10: =C10&D10 -> PERecife | C10: PE | D10: Recife | E10: 1661017
B11: =C11&D11 -> GOGoiânia | C11: GO | D11: Goiânia | E11: 1555626
A12: =_xlfn.CONCAT(C12,D12) -> PABelém | B12: =C12&D12 -> PABelém | C12: PA | D12: Belém | E12: 1506420
B13: =C13&D13 -> RSPorto Alegre | C13: RS | D13: Porto Alegre | E13: 1492530
B14: =C14&D14 -> SPGuarulhos | C14: SP | D14: Guarulhos | E14: 1404694
B15: =C15&D15 -> SPCampinas | C15: SP | D15: Campinas | E15: 1223237
A16: =_xlfn.CONCAT(C16,D16) -> MASão Luís | B16: =C16&D16 -> MASão Luís | C16: MA | D16: São Luís | E16: 1115932
B17: =C17&D17 -> RJSão Gonçalo | C17: RJ | D17: São Gonçalo | E17: 1098357
B18: =C18&D18 -> ALMaceió | C18: AL | D18: Maceió | E18: 1031597
B19: =C19&D19 -> RJDuque de Caxias | C19: RJ | D19: Duque de Caxias | E19: 929449
B20: =C20&D20 -> MSCampo Grande | C20: MS | D20: Campo Grande | E20: 916001
B21: =C21&D21 -> RNNatal | C21: RN | D21: Natal | E21: 896708
B22: =C22&D22 -> PITeresina | C22: PI | D22: Teresina | E22: 871126
B23: =C23&D23 -> SPSão Bernardo do Campo | C23: SP | D23: São Bernardo do Campo | E23: 849874
B24: =C24&D24 -> PBJoão Pessoa | C24: PB | D24: João Pessoa | E24: 825796
B25: =C25&D25 -> RJNova Iguaçu | C25: RJ | D25: Nova Iguaçu | E25: 825388
B26: =C26&D26 -> SPSão José dos Campos | C26: SP | D26: São José dos Campos | E26: 737310
B27: =C27&D27 -> SPSanto André | C27: SP | D27: Santo André | E27: 723889
B28: =C28&D28 -> SPRibeirão Preto | C28: SP | D28: Ribeirão Preto | E28: 720116
... B40: =C40&D40 -> MGJuiz de Fora | C40: MG | D40: Juiz de Fora | E40: 577532
A41: =_xlfn.CONCAT(C41,D41) -> ROPorto Velho | B41: =C41&D41 -> ROPorto Velho | C41: RO | D41: Porto Velho | E41: 548952
A42: =_xlfn.CONCAT(C42,D42) -> PAAnanindeua | B42: =C42&D42 -> PAAnanindeua | C42: PA | D42: Ananindeua | E42: 540410
B43: =C43&D43 -> ESSerra | C43: ES | D43: Serra | E43: 536765
B44: =C44&D44 -> RSCaxias do Sul | C44: RS | D44: Caxias do Sul | E44: 523716
A45: =_xlfn.CONCAT(C45,D45) -> APMacapá | B45: =C45&D45 -> APMacapá | C45: AP | D45: Macapá | E45: 522357
B46: =C46&D46 -> RJNiterói | C46: RJ | D46: Niterói | E46: 516981
B47: =C47&D47 -> SCFlorianópolis | C47: SC | D47: Florianópolis | E47: 516524
B48: =C48&D48 -> RJBelford Roxo | C48: RJ | D48: Belford Roxo | E48: 515239
B49: =C49&D49 -> RJCampos dos Goytacazes | C49: RJ | D49: Campos dos Goytacazes | E49: 514643
B50: =C50&D50 -> ESVila Velha | C50: ES | D50: Vila Velha | E50: 508655
B51: =C51&D51 -> SPMauá | C51: SP | D51: Mauá | E51: 481725
B52: =C52&D52 -> RJSão João de Meriti | C52: RJ | D52: São João de Meriti | E52: 473385
B53: =C53&D53 -> SPSão José do Rio Preto | C53: SP | D53: São José do Rio Preto | E53: 469173
B54: =C54&D54 -> SPMogi das Cruzes | C54: SP | D54: Mogi das Cruzes | E54: 455587
B55: =C55&D55 -> MGBetim | C55: MG | D55: Betim | E55: 450024
A56: =_xlfn.CONCAT(C56,D56) -> RRBoa Vista | B56: =C56&D56 -> RRBoa Vista | C56: RR | D56: Boa Vista | E56: 436591
B57: =C57&D57 -> PRMaringá | C57: PR | D57: Maringá | E57: 436472
B58: =C58&D58 -> SPSantos | C58: SP | D58: Santos | E58: 433991
B59: =C59&D59 -> SPDiadema | C59: SP | D59: Diadema | E59: 429550
B60: =C60&D60 -> SPJundiaí | C60: SP | D60: Jundiaí | E60: 426935
A61: =_xlfn.CONCAT(C61,D61) -> ACRio Branco | B61: =C61&D61 -> ACRio Branco | C61: AC | D61: Rio Branco | E61: 419452
B62: =C62&D62 -> MGMontes Claros | C62: MG | D62: Montes Claros | E62: 417478
B63: =C63&D63 -> PBCampina Grande | C63: PB | D63: Campina Grande | E63: 413830
B64: =C64&D64 -> SPPiracicaba | C64: SP | D64: Piracicaba | E64: 410275
B65: =C65&D65 -> SPCarapicuíba | C65: SP | D65: Carapicuíba | E65: 405375
B66: =C66&D66 -> GOAnápolis | C66: GO | D66: Anápolis | E66: 396526
B67: =C67&D67 -> PEOlinda | C67: PE | D67: Olinda | E67: 393734
B68: =C68&D68 -> ESCariacica | C68: ES | D68: Cariacica | E68: 386495
B69: =C69&D69 -> SPBauru | C69: SP | D69: Bauru | E69: 381706
B70: =C70&D70 -> SPItaquaquecetuba | C70: SP | D70: Itaquaquecetuba | E70: 379082
B71: =C71&D71 -> SPSão Vicente | C71: SP | D71: São Vicente | E71: 370839
B72: =C72&D72 -> ESVitória | C72: ES | D72: Vitória | E72: 369534
B73: =C73&D73 -> PECaruaru | C73: PE | D73: Caruaru | E73: 369343
... B89: =C89&D89 -> SPTaubaté | C89: SP | D89: Taubaté | E89: 320820
A90: =_xlfn.CONCAT(C90,D90) -> TOPalmas | B90: =C90&D90 -> TOPalmas | C90: TO | D90: Palmas | E90: 313349
B91: =C91&D91 -> SPLimeira | C91: SP | D91: Limeira | E91: 310783
B92: =C92&D92 -> BACamaçari | C92: BA | D92: Camaçari | E92: 309208
A93: =_xlfn.CONCAT(C93,D93) -> PASantarém | B93: =C93&D93 -> PASantarém | C93: PA | D93: Santarém | E93: 308339
B94: =C94&D94 -> RJPetrópolis | C94: RJ | D94: Petrópolis | E94: 307144
B95: =C95&D95 -> RNMossoró | C95: RN | D95: Mossoró | E95: 303792
B96: =C96&D96 -> SPSuzano | C96: SP | D96: Suzano | E96: 303397
B97: =C97&D97 -> SPTaboão da Serra | C97: SP | D97: Taboão da Serra | E97: 297528
B98: =C98&D98 -> MTVárzea Grande | C98: MT | D98: Várzea Grande | E98: 290383
B99: =C99&D99 -> SPSumaré | C99: SP | D99: Sumaré | E99: 289875
A100: =_xlfn.CONCAT(C100,D100) -> PAMarabá | B100: =C100&D100 -> PAMarabá | C100: PA | D100: Marabá | E100: 287664
B101: =C101&D101 -> RSGravataí | C101: RS | D101: Gravataí | E101: 285564
B102: =C102&D102 -> RSSanta Maria | C102: RS | D102: Santa Maria | E102: 285159
B103: =C103&D103 -> MGGovernador Valadares | C103: MG | D103: Governador Valadares | E103: 282164
B104: =C104&D104 -> SPBarueri | C104: SP | D104: Barueri | E104: 279704
B105: =C105&D105 -> SPEmbu das Artes | C105: SP | D105: Embu das Artes | E105: 279264
B106: =C106&D106 -> CEJuazeiro do Norte | C106: CE | D106: Juazeiro do Norte | E106: 278264
B107: =C107&D107 -> RJVolta Redonda | C107: RJ | D107: Volta Redonda | E107: 274925
B108: =C108&D108 -> RNParnamirim | C108: RN | D108: Parnamirim | E108: 272490
B109: =C109&D109 -> MGIpatinga | C109: MG | D109: Ipatinga | E109: 267333
B110: =C110&D110 -> RJMacaé | C110: RJ | D110: Macaé | E110: 266136
B111: =C111&D111 -> SPIndaiatuba | C111: SP | D111: Indaiatuba | E111: 260690
A112: =_xlfn.CONCAT(C112,D112) -> MAImperatriz | B112: =C112&D112 -> MAImperatriz | C112: MA | D112: Imperatriz | E112: 259980
B113: =C113&D113 -> PRFoz do Iguaçu | C113: PR | D113: Foz do Iguaçu | E113: 257971
B114: =C114&D114 -> SPCotia | C114: SP | D114: Cotia | E114: 257882
B115: =C115&D115 -> RSViamão | C115: RS | D115: Viamão | E115: 257330
B116: =C116&D116 -> SPSão Carlos | C116: SP | D116: São Carlos | E116: 256915
B117: =C117&D117 -> SCSão José | C117: SC | D117: São José | E117: 253705
B118: =C118&D118 -> PRColombo | C118: PR | D118: Colombo | E118: 249277
B119: =C119&D119 -> RJMagé | C119: RJ | D119: Magé | E119: 247741
B120: =C120&D120 -> RSNovo Hamburgo | C120: RS | D120: Novo Hamburgo | E120: 247303
B121: =C121&D121 -> GORio Verde | C121: GO | D121: Rio Verde | E121: 247259
B122: =C122&D122 -> RJItaboraí | C122: RJ | D122: Itaboraí | E122: 244416
B123: =C123&D123 -> SPAmericana | C123: SP | D123: Americana | E123: 244370
B124: =C124&D124 -> SPItapevi | C124: SP | D124: Itapevi | E124: 244131
... B143: =C143&D143 -> SCCriciúma | C143: SC | D143: Criciúma | E143: 219393
A144: =_xlfn.CONCAT(C144,D144) -> PAParauapebas | B144: =C144&D144 -> PAParauapebas | C144: PA | D144: Parauapebas | E144: 218787
...
